{
  "components": [
    {
      "data": {
        "contents_checksum": "4bf866f839ba9c416823a1249b62b908bbbf91117abe99a76e9e6a4fd689d9dd", 
        "source": "", 
        "type": "tar"
      }, 
      "dependencies": [
        "core-nix", 
        "core-win", 
        "gcloud-deps", 
        "ssh-tools"
      ], 
      "details": {
        "description": "Handles all core functionality for the Cloud SDK.", 
        "display_name": "Cloud SDK Core Libraries"
      }, 
      "id": "core", 
      "is_configuration": false, 
      "is_hidden": false, 
      "is_required": true, 
      "platform": {}, 
      "version": {
        "build_number": 20190308170552, 
        "version_string": "2019.03.08"
      }
    }
  ], 
  "revision": 20190308170552, 
  "schema_version": {
    "no_update": false, 
    "url": "https://dl.google.com/dl/cloudsdk/channels/rapid/google-cloud-sdk.tar.gz", 
    "version": 3
  }, 
  "version": "238.0.0"
}