{
  "LANG_CONTROLS_FOREACH_INPUT_COLLAPSED_SUFFIX": "na liście",
  "COLLAPSE_ALL": "Zwiń bloki",
  "TEXT_CHANGECASE_OPERATOR_UPPERCASE": "zmień na WIELKIE LITERY",
  "LANG_CONTROLS_CLOSE_APPLICATION_TITLE": "zamknij aplikację",
  "DIALOG_RENDEZVOUS_NEGOTIATING": "15 Rendezvous (please wait)",
  "LANG_MATH_FORMAT_AS_DECIMAL_INPUT_NUM": "liczba",
  "LANG_MATH_DIVIDE_TOOLTIP_MODULO": "Zwraca modulo.",
  "CONTROLS_FOR_TOOLTIP": "Przypisuje zmiennej %1 wartości od numeru startowego do numeru końcowego, licząc co określony interwał, wykonując określone bloki.",
  "LANG_LISTS_IS_EMPTY_TOOLTIP": "Zwraca Prawdę, jeśli lista jest pusta.",
  "VARIABLES_SET_CREATE_GET": "Utwórz blok 'pobierz %1'",
  "CONTROLS_WHILEUNTIL_OPERATOR_UNTIL": "powtarzaj aż",
  "LANG_MATH_CONVERT_ANGLES_OP_RAD_TO_DEG": "radiany na stopnie",
  "MATH_ONLIST_TOOLTIP_MEDIAN": "Zwróć medianę listy.",
  "LANG_TEXT_COMPARE_GT": ">",
  "COLOUR_RGB_HELPURL": "http://www.december.com/html/spec/colorper.html",
  "LANG_CONTROLS_DO_THEN_RETURN_INPUT_DO": "wykonaj",
  "MATH_ROUND_HELPURL": "https://pl.wikipedia.org/wiki/Zaokrąglanie",
  "LOGIC_BOOLEAN_TOOLTIP": "Zwraca 'prawda' lub 'fałsz'.",
  "LISTS_REPEAT_TOOLTIP": "Tworzy listę składającą się z podanej wartości powtórzonej odpowiednią liczbę razy.",
  "LANG_CONTROLS_IF_IF_TOOLTIP": "Dodaj, usuń lub zmień kolejność sekcji, aby zmienić konfigurację, bloku 'Jeśli'.",
  "LANG_VARIABLES_GLOBAL_DECLARATION_COLLAPSED_TEXT": "globalna",
  "LANG_LISTS_ADD_ITEM_TITLE": "pozycja",
  "LANG_MATH_TRIG_SIN": "sin",
  "LANG_CONTROLS_CLOSE_SCREEN_COLLAPSED_TEXT": "zamknij ekran",
  "LANG_LISTS_CREATE_WITH_ITEM_TITLE": "pozycja",
  "PROCEDURES_DEFNORETURN_PROCEDURE": "zrób coś",
  "LISTS_GET_SUBLIST_START_FIRST": "Pobierz listę podrzędną z pierwszego",
  "LANG_LISTS_IS_IN_TOOLTIP": "Zwraca Prawdę, jeśli obiekt jest elementem listy, a Fałsz, jeśli nie.",
  "MATH_ARITHMETIC_TOOLTIP_MULTIPLY": "Zwróć iloczyn dwóch liczb.",
  "LANG_VARIABLES_SET_TOOLTIP": "Ustawia tę zmienną na równą wartości wejściowej.",
  "TIME_YEARS": "Years",
  "TIME_DURATION": "Duration",
  "TEXT_GET_SUBSTRING_END_FROM_END": "do # litery od końca",
  "LANG_CONTROLS_FOREACH_INPUT_COLLAPSED_TEXT": "dla pozycji na liście",
  "LOGIC_COMPARE_TOOLTIP_EQ": "Zwróć \"prawda\", jeśli oba wejścia są sobie równe.",
  "LANG_TEXT_TEXT_RIGHT_QUOTE": "\u201d",
  "TEXT_APPEND_TOOLTIP": "Dołącz tekst do zmiennej '%1'.",
  "TEXT_TRIM_OPERATOR_RIGHT": "usuń spacje z prawej strony",
  "TEXT_JOIN_TOOLTIP": "Tworzy fragment tekstu, łącząc ze sobą dowolną liczbę tekstów.",
  "LISTS_SET_INDEX_TOOLTIP_SET_FIRST": "Ustawia pierwszy element na liście.",
  "TIME_HOURS": "Hours",
  "MATH_SINGLE_HELPURL": "https://pl.wikipedia.org/wiki/Pierwiastek_kwadratowy",
  "LANG_CONTROLS_FOREACH_INPUT_ITEM": "dla każdej",
  "COLOUR_PICKER_TOOLTIP": "Wybierz kolor z palety.",
  "LANG_MATH_COMPARE_LTE": "≤",
  "ENABLE_GRID": "Włącz siatkę Pulpi",
  "LANG_CONTROLS_WHILEUNTIL_INPUT_DO": "wykonaj",
  "LANG_CONTROLS_FORRANGE_INPUT_DO": "wykonaj",
  "LANG_CONTROLS_CHOOSE_TITLE": "jeśli",
  "LANG_LISTS_TO_CSV_ROW_TITLE_TO_CSV": "lista do wiersza csv",
  "LANG_TEXT_CHANGECASE_TOOLTIP_UPPERCASE": "Zwraca kopię argumentu łańcucha tekstowego przekonwertowanego na wielkie litery.",
  "LANG_CONTROLS_CLOSE_SCREEN_WITH_PLAIN_TEXT_COLLAPSED_TEXT": "zamknij ekran ze zwykłym tekstem",
  "BACKPACK_DOCUMENTATION": "Plecak to funkcja kopiowania/wklejania. Pozwala kopiować bloki z jednego projektu lub ekranu i wklejać je do innego projektu lub ekranu. Aby skopiować, możesz przeciągać i upuszczać bloki do plecaka. Aby wkleić, kliknij ikonę Plecaka i przeciągnij i upuść bloki do obszaru roboczego. <\/p><p> Jeśli opuścisz MIT App Inventor z blokami pozostawionymi w plecaku, będą tam przy następnym logowaniu. <\/p><p><a href='/reference/other/backpack.html' target='_blank'> Kliknij tutaj <\/a>, aby uzyskać dalszą dokumentację i wideo \u201ejak to zrobić\u201d.",
  "LANG_MATH_MUTATOR_ITEM_INPUT_NUMBER": "numer",
  "LISTS_SORT_ORDER_DESCENDING": "malejąco",
  "CONTROLS_FLOW_STATEMENTS_TOOLTIP_CONTINUE": "Pomiń resztę pętli i kontynuuj w kolejnej iteracji.",
  "VARIABLES_SET_TOOLTIP": "Nadaj tej zmiennej wartość.",
  "REPL_KEEP_TRYING": "Keep Trying",
  "MATH_SINGLE_TOOLTIP_POW10": "Zwróć 10 do potęgi danej liczby.",
  "LANG_LISTS_CREATE_WITH_TITLE_MAKE_LIST": "twórz listę",
  "LANG_LOGIC_NEGATE_TOOLTIP": "Zwraca Prawda, jeśli dane wejściowe są fałszywe. Zwraca fałsz, jeśli dane wejściowe są prawdziwe.",
  "LANG_PROCEDURES_DEF_DUPLICATE_WARNING": "Ostrzeżenie: Ta funkcja ma zduplikowane wejścia.",
  "LANG_CONTROLS_FOREACH_INPUT_COLLAPSED_PREFIX": "dla",
  "LANG_TEXT_COMPARE_EQUAL": "=",
  "LOGIC_OPERATION_HELPURL": "https://github.com/google/blockly/wiki/Logic#logical-operations",
  "REMOVE_FROM_BACKPACK": "Usuń z plecaka",
  "LANG_LISTS_IS_IN_INPUT_LIST": "lista",
  "TEXT_PROMPT_TYPE_NUMBER": "poproś o liczbę z tą wiadomością",
  "LANG_TEXT_CHANGECASE_OPERATOR_UPPERCASE": "wielkie litery",
  "CONTROLS_FOR_TITLE": "licz z %1 od %2 do %3 co %4 (wartość kroku)",
  "LANG_CATEGORY_MATH": "Matematyczne",
  "DOWNLOAD_BLOCKS_AS_PNG": "Download Blocks as PNG",
  "LANG_VARIABLES_LOCAL_MUTATOR_CONTAINER_TITLE_LOCAL_NAMES": "lokalne nazwy",
  "LANG_MATH_CONVERT_NUMBER_TOOLTIP_DEC_TO_HEX": "Przekształca liczbę dodatnią całkowitą na ciąg stanowiący liczbę heksadecymalną",
  "LANG_TEXT_TEXT_TOOLTIP": "Ciąg tekstowy.",
  "TEXT_INDEXOF_OPERATOR_LAST": "znajdź ostatnie wystąpienie tekstu",
  "LANG_CONTROLS_OPEN_ANOTHER_SCREEN_TITLE": "otwórz inny ekran",
  "LISTS_CREATE_EMPTY_HELPURL": "https://github.com/google/blockly/wiki/Lists#create-empty-list",
  "LANG_TEXT_REPLACE_ALL_INPUT_TEXT": "tekst",
  "ARRANGE_H": "Rozmieść bloki w poziomie",
  "LANG_LISTS_JOIN_WITH_SEPARATOR_TITLE": "połącz z separatorem",
  "UNDO": "Cofnij",
  "PROCEDURES_ALLOW_STATEMENTS": "zezwól na instrukcje",
  "COLOUR_RANDOM_TOOLTIP": "Wybierz kolor w sposób losowy.",
  "LISTS_CREATE_WITH_HELPURL": "https://github.com/google/blockly/wiki/Lists#create-list-with",
  "LANG_TEXT_SEGMENT_TITLE_SEGMENT": "człon",
  "LANG_MATH_TRIG_TOOLTIP_ATAN2": "Podaje kąt w zakresie (-180, +180]\nstopni ze współrzędnymi prostokątnymi.",
  "LANG_MATH_IS_A_BINARY_TOOLTIP": "Sprawdza czy dane są ciągiem stanowiącym liczbę binarną.",
  "LISTS_LENGTH_TITLE": "długość %1",
  "MATH_TRIG_TOOLTIP_ATAN": "Zwróć arcus tangens danej liczby.",
  "MATH_ONLIST_TOOLTIP_RANDOM": "Zwróć losowy element z listy.",
  "MATH_ONLIST_TOOLTIP_AVERAGE": "Zwróć średnią (średnią arytmetyczną) wartości liczbowych z listy.",
  "LANG_VARIABLES_SET_TITLE_SET": "ustaw",
  "LANG_CONTROLS_CLOSE_SCREEN_WITH_PLAIN_TEXT_INPUT_TEXT": "tekst",
  "SHOW_WARNINGS": "Show Warnings",
  "LISTS_GET_INDEX_TOOLTIP_REMOVE_FROM": "Usuwa element z określonej pozycji na liście.",
  "LANG_MATH_DIVIDE_TOOLTIP_QUOTIENT": "Zwraca iloraz.",
  "PROCEDURES_MUTATORCONTAINER_TOOLTIP": "Dodaj, usuń lub zmień kolejność danych wejściowych dla tej funkcji.",
  "ARRANGE_V": "Rozmieść bloki pionowo",
  "LANG_LISTS_IS_LIST_INPUT_THING": "obiekt",
  "ARRANGE_S": "Ułóż bloki po przekątnej",
  "LANG_LISTS_FROM_CSV_ROW_INPUT_TEXT": "tekst",
  "LANG_LISTS_LOOKUP_IN_PAIRS_INPUT_PAIRS": "pary",
  "MATH_TRIG_COS": "cos",
  "MATH_TRIG_ATAN": "arctg",
  "REPL_APPROVE_UPDATE": " screen because you will be asked to approve the update.",
  "BACKPACK_DOC_TITLE": "Informacje o plecaku",
  "REPL_SECONDS_ENSURE_RUNNING": " seconds to ensure all is running.",
  "MATH_TRIG_TOOLTIP_SIN": "Zwróć wartość sinusa o stopniu (nie w radianach).",
  "LANG_MATH_DIVIDE": "÷",
  "CONTROLS_FLOW_STATEMENTS_HELPURL": "https://github.com/google/blockly/wiki/Loops#loop-termination-blocks",
  "TEXT_GET_SUBSTRING_INPUT_IN_TEXT": "w tekście",
  "LANG_TEXT_COMPARE_TOOLTIP_EQUAL": "Sprawdza czy ciągi tekstowe są identyczne, np., mają takie same\nznaki w tej samej kolejności. To jest inne niż zwykłe =\nw przypadku gdy ciągi tekstowe są liczbami: 123 1 0123 są równe,\nale nie są równe tekstowo.",
  "REPL_STARTING_EMULATOR": "Starting the Android Emulator<br/>Please wait: This might take a minute or two.",
  "LANG_LISTS_CREATE_EMPTY_TITLE": "utwórz pustą listę",
  "MATH_ARITHMETIC_TOOLTIP_DIVIDE": "Zwróć iloraz dwóch liczb.",
  "LANG_TEXT_ISEMPTY_INPUT_ISEMPTY": "czy pusty?",
  "LANG_CONTROLS_FOREACH_INPUT_DO": "wykonaj",
  "LOGIC_COMPARE_TOOLTIP_LT": "Zwróć \"prawda\" jeśli pierwsze wejście jest większe od drugiego.",
  "MATH_NUMBER_TOOLTIP": "Liczba.",
  "LANG_MATH_TRIG_ACOS": "acos",
  "PROCEDURES_DEFRETURN_RETURN": "zwróć",
  "LANG_MATH_BITWISE_IOR": "bitowo lub",
  "LANG_COMPONENT_BLOCK_GENERIC_SETTER_TITLE_TO": "do",
  "INLINE_INPUTS": "Wejścia liniowe",
  "LISTS_CREATE_WITH_INPUT_WITH": "Tworzenie listy z",
  "LANG_MATH_COMPARE_TOOLTIP_LT": "Zwraca Prawda, jeśli pierwsza liczba jest mniejsza niż druga liczba.",
  "LANG_CONTROLS_GET_PLAIN_START_TEXT_TOOLTIP": "Zwraca zwykły tekst, który został przekazany do tego ekranu, gdy został uruchomiony przez inną aplikację. Jeśli nie przekazano żadnej wartości, zwraca pusty tekst. W przypadku aplikacji z wieloma ekranami użyj wartości początkowej, a nie zwykłego tekstu początkowego.",
  "LANG_TEXT_LENGTH_INPUT_LENGTH": "długość",
  "LANG_MATH_ARITHMETIC_TOOLTIP_MULTIPLY": "Zwraca iloczyn dwóch liczb.",
  "LANG_LISTS_REVERSE_INPUT_LIST": "lista",
  "LANG_VARIABLES_SET_TITLE_TO": "do",
  "LANG_LISTS_SELECT_ITEM_INPUT_LIST": "lista",
  "LANG_COLOUR_SPLIT_COLOUR_TOOLTIP": "Lista czterech elementów, z których każdy mieści się w zakresie od 0 do 255, reprezentujących składniki czerwony, zielony, niebieski i alfa.",
  "LANG_CONTROLS_IF_ELSE_TITLE_ELSE": "inaczej",
  "MATH_IS_PRIME": "jest liczbą pierwszą",
  "LISTS_GET_SUBLIST_START_FROM_START": "Pobierz listę podrzędną z #",
  "LANG_PROCEDURES_DEFNORETURN_PROCEDURE": "funkcja",
  "LISTS_SORT_ORDER_ASCENDING": "rosnąco",
  "LISTS_GET_SUBLIST_TAIL": "",
  "TEXT_INDEXOF_INPUT_INTEXT": "w tekście",
  "TEXT_PRINT_HELPURL": "https://github.com/google/blockly/wiki/Text#printing-text",
  "SHOW_ALL_COMMENTS": "Pokaż wszystkie komentarze",
  "TEXT_TEXT_TOOLTIP": "Litera, wyraz lub linia tekstu.",
  "LISTS_SET_INDEX_INSERT": "wstaw w",
  "LANG_MATH_RANDOM_INT_TOOLTIP": "Zwraca losową liczbę całkowitą pomiędzy\npodanymi górnym i dolnym zakresem. Zakresy będą obcięte do liczb mniejszych\nniż 2**30.",
  "LOGIC_TERNARY_CONDITION": "test",
  "LOGIC_COMPARE_TOOLTIP_NEQ": "Zwróć \"prawda\", jeśli oba wejścia są sobie nierówne.",
  "LANG_CONTROLS_CHOOSE_COLLAPSED_TEXT": "Jeśli",
  "LANG_MATH_CONVERT_NUMBER_OP_DEC_TO_HEX": "dodatnią całkowitą na hex",
  "LANG_CONTROLS_CLOSE_APPLICATION_COLLAPSED_TEXT": "zamknij aplikację",
  "LANG_TEXT_SPLIT_INPUT_AT_LIST": "na (liście)",
  "MATH_CONSTRAIN_TITLE": "ogranicz %1 z dołu %2 z góry %3",
  "TEXT_ISEMPTY_TITLE": "%1 jest pusty",
  "LANG_CONTROLS_FOR_INPUT_FROM": "od",
  "CONTROLS_FLOW_STATEMENTS_TOOLTIP_BREAK": "Wyjdź z zawierającej pętli.",
  "MATH_ONLIST_TOOLTIP_STD_DEV": "Zwróć odchylenie standardowe listy.",
  "LANG_TEXT_CONTAINS_INPUT_PIECE": "fragment",
  "COLOUR_BLEND_TOOLTIP": "Miesza dwa kolory w danej proporcji (0.0 - 1.0).",
  "TEXT_LENGTH_TITLE": "długość %1",
  "BACKPACK_GET": "Wklej wszystkie bloki z plecaka",
  "TEXT_PROMPT_HELPURL": "https://github.com/google/blockly/wiki/Text#getting-input-from-the-user",
  "LANG_LISTS_ADD_ITEMS_INPUT": "dodaj elementy do listy  lista %1 element %2",
  "LANG_CONTROLS_CLOSE_APPLICATION_TOOLTIP": "Zamyka wszystkie ekrany w tej aplikacji i zatrzymuje aplikację.",
  "CONTROLS_FLOW_STATEMENTS_WARNING": "Uwaga: Ten blok może być użyty tylko w pętli.",
  "LISTS_GET_INDEX_TOOLTIP_GET_RANDOM": "Zwraca losowy element z listy.",
  "LANG_VARIABLES_LOCAL_DECLARATION_DEFAULT_NAME": "nazwa",
  "LANG_COLOUR_WHITE": "biały",
  "LANG_MATH_RANDOM_INT_INPUT_TO": "do",
  "LANG_COLOUR_PICKER_TOOLTIP": "Kliknij kwadrat, aby wybrać kolor.",
  "TIME_WEEKS": "Weeks",
  "LOGIC_NEGATE_TOOLTIP": "Zwraca \"prawda\", jeśli dane wejściowe są fałszywe.  Zwraca \"fałsz\", jeśli dana wejściowa jest prawdziwa.",
  "LANG_VARIABLES_LOCAL_DECLARATION_EXPRESSION_COLLAPSED_TEXT": "lokalna",
  "LANG_CONTROLS_WHILEUNTIL_OPERATOR_UNTIL": "aż do",
  "LANG_TEXT_COMPARE_INPUT_COMPARE": "porównaj tekst",
  "LANG_CONTROLS_IF_MSG_ELSEIF": "inaczej jeśli",
  "LOGIC_COMPARE_TOOLTIP_GT": "Zwróć \"prawda\" jeśli pierwsze wejście jest większe od drugiego.",
  "LANG_COMPONENT_BLOCK_GENERIC_METHOD_TITLE_CALL": "wołaj",
  "LANG_CONTROLS_WHILE_INPUT_TEST": "test",
  "DISABLE_BLOCK": "Wyłącz blok",
  "MATH_ADDITION_SYMBOL": "+",
  "LANG_COMPONENT_BLOCK_METHOD_TITLE_CALL": "wołaj",
  "MATH_IS_DIVISIBLE_BY": "jest podzielna przez",
  "LANG_LISTS_LOOKUP_IN_PAIRS_TITLE_LOOKUP_IN_PAIRS": "przegląda pary",
  "LANG_MATH_CONVERT_NUMBER_TOOLTIP_BIN_TO_DEC": "Przekształca ciąg stanowiący liczbę binarną na ciąg reprezentujący liczbę całkowitą dodatnią",
  "TEXT_CREATE_JOIN_ITEM_TOOLTIP": "Dodaj element do tekstu.",
  "CONTROLS_FLOW_STATEMENTS_OPERATOR_BREAK": "wyjdź z pętli",
  "LANG_MATH_BITWISE_XOR": "bitowy xor",
  "REPL_DO_YOU_REALLY_Q": "Do You Really?",
  "LANG_VARIABLES_SET_COLLAPSED_TEXT": "ustaw",
  "ORDINAL_NUMBER_SUFFIX": "",
  "LANG_LISTS_ADD_ITEMS_INPUT_LIST": "lista",
  "LISTS_GET_INDEX_TOOLTIP_GET_REMOVE_RANDOM": "Usuwa i zwraca losowy element z listy.",
  "LANG_TEXT_JOIN_TOOLTIP": "Łączy wszystkie dane w jeden ciąg tekstowy.\nJeśli nie ma danych, tworzy pusty ciąg.",
  "LOGIC_BOOLEAN_HELPURL": "https://github.com/google/blockly/wiki/Logic#values",
  "COLOUR_BLEND_RATIO": "proporcja",
  "LANG_LISTS_FROM_CSV_TABLE_TITLE_FROM_CSV": "lista z tabeli CSV",
  "REPL_UPDATE_NO_CONNECTION": "You must be connected to a Companion to update it",
  "VARIABLES_GET_HELPURL": "https://github.com/google/blockly/wiki/Variables#get",
  "PROCEDURES_MUTATORCONTAINER_TITLE": "wejścia",
  "LANG_MATH_ROUND_OPERATOR_CEILING": "zaokrąglenie w górę",
  "MATH_CONSTANT_HELPURL": "https://pl.wikipedia.org/wiki/Stała_(matematyka)",
  "LANG_CONTROLS_WHILEUNTIL_TOOLTIP_UNTIL": "Gdy wartość jest Fałszem, wykonaj kilka instrukcji.",
  "TEXT_TRIM_TOOLTIP": "Zwraca kopię tekstu z usuniętymi spacjami z jednego lub z obu końców tekstu.",
  "LANG_MATH_TRIG_TOOLTIP_SIN": "Podaje sinus kąta w stopniach.",
  "PROCEDURES_CALLRETURN_TOOLTIP": "Uruchom funkcję zdefiniowaną przez użytkownika '%1' i skorzystaj z jej wyniku.",
  "LANG_TEXT_COMPARE_LT": "<",
  "PROCEDURES_DEFNORETURN_HELPURL": "https://en.wikipedia.org/wiki/Procedure_%28computer_science%29",
  "LANG_CONTROLS_DO_THEN_RETURN_INPUT_RETURN": "wynik",
  "LANG_LISTS_INSERT_INPUT_ITEM": "pozycja",
  "CLEAN_UP": "Oczyść bloki",
  "LANG_COMPONENT_BLOCK_TITLE_WHEN": "gdy",
  "TEXT_JOIN_HELPURL": "https://github.com/google/blockly/wiki/Text#text-creation",
  "LANG_LISTS_CREATE_WITH_ITEM_TOOLTIP": "Dodaj element do listy.",
  "TEXT_CHARAT_FROM_START": "pobierz literę #",
  "LANG_MATH_TRIG_TOOLTIP_ATAN": "Podaje kąt w zakresie (-90, +90)\nstopni z daną wartością tangens.",
  "REDO": "Ponów",
  "MATH_TRIG_HELPURL": "https://pl.wikipedia.org/wiki/Funkcje_trygonometryczne",
  "LANG_TEXT_CHANGECASE_OPERATOR_DOWNCASE": "małe litery",
  "LANG_MATH_RANDOM_SEED_TITLE_RANDOM": "losowe ziarno",
  "LANG_COMPONENT_BLOCK_GENERIC_EVENT_TITLE": "gdy jakikolwiek",
  "TEXT_CREATE_JOIN_TOOLTIP": "Dodaj, usuń lub zmień kolejność sekcji, aby zmodyfikować blok tekstowy.",
  "LANG_LOGIC_BOOLEAN_FALSE": "Fałsz",
  "REPL_COMPANION_OUT_OF_DATE_IMMEDIATE": "You are using an out-of-date Companion. You should update the MIT AI2 Companion as soon as possible. If you have auto-update setup in the store, the update will happen by itself shortly.",
  "LANG_PROCEDURES_DEFNORETURN_DEFINE": "do",
  "LANG_LOGIC_BOOLEAN_TOOLTIP_FALSE": "Zwraca wartość logiczną Fałsz.",
  "VARIABLES_GET_CREATE_SET": "Utwórz blok 'ustaw %1'",
  "LANG_CONTROLS_FORRANGE_INPUT_COLLAPSED_SUFFIX": "w zakresie",
  "CONTROLS_WHILEUNTIL_TOOLTIP_WHILE": "Gdy wartość jest prawdziwa, wykonaj kilka instrukcji.",
  "EXPAND_BLOCK": "Rozwiń blok",
  "ERROR_DUPLICATE_EVENT_HANDLER": "Jest to zduplikowana obsługa zdarzeń dla tego komponentu.",
  "LISTS_SPLIT_TOOLTIP_JOIN": "Łączy listę tekstów w jeden tekst, rozdzielany separatorem.",
  "VARIABLES_SET_HELPURL": "https://github.com/google/blockly/wiki/Variables#set",
  "LANG_MATH_TRIG_ATAN2": "atan2",
  "LANG_CONTROLS_IF_IF_TITLE_IF": "Jeśli",
  "LANG_CONTROLS_DO_THEN_RETURN_TITLE": "wykonaj wynik",
  "LANG_CONTROLS_CLOSE_SCREEN_TOOLTIP": "Zamknij bieżący ekran",
  "LANG_LISTS_CREATE_WITH_CONTAINER_TOOLTIP": "Dodaj, usuń lub zmień kolejność sekcji, aby zmienić konfigurację listy bloku.",
  "LANG_MATH_ARITHMETIC_DIVIDE": "/",
  "LISTS_SPLIT_LIST_FROM_TEXT": "stwórz listę z tekstu",
  "MATH_CONSTANT_TOOLTIP": "Zwróć jedną wspólną stałą: π (3.141), e (2.718...), φ (1.618...), sqrt(2) (1.414...), sqrt(½) (0.707...) lub ∞ (nieskończoność).",
  "ENABLE_SNAPPING": "Włącz przyciąganie do siatki",
  "REPL_EMULATOR_STARTED": "Emulator started, waiting ",
  "LISTS_GET_SUBLIST_END_FROM_END": "do # od końca",
  "LANG_COLOUR_DARK_GRAY": "ciemny szary",
  "LANG_LISTS_LOOKUP_IN_PAIRS_INPUT_NOT_FOUND": "nieZnaleziono",
  "LANG_VARIABLES_LOCAL_DECLARATION_EXPRESSION_TRANSLATED_NAME": "inicjuj zmienną lokalną ze zwrotem",
  "REPL_STARTING_COMPANION_ON_PHONE": "Starting the Companion App on the connected phone.",
  "CONTROLS_IF_MSG_ELSEIF": "w przeciwnym razie, jeśli",
  "LANG_LISTS_LENGTH_INPUT": "długość listy  lista %1",
  "DELETE_VARIABLE_CONFIRMATION": "Delete %1 uses of the '%2' variable?",
  "VARIABLE_CATEGORY": "Zmienne",
  "MATH_RANDOM_INT_TOOLTIP": "Zwróć losową liczbę całkowitą w ramach dwóch wyznaczonych granic, włącznie.",
  "LANG_PROCEDURES_DOTHENRETURN_COLLAPSED_TEXT": "wykonaj/wynik",
  "LANG_CONTROLS_EVAL_BUT_IGNORE_TOOLTIP": "Uruchamia połączony blok kodu i ignoruje wartość zwracaną (jeśli istnieje). Przydatne, jeśli trzeba wywołać procedurę z wartością zwracaną, ale nie potrzebujesz wartości.",
  "DO_IT_DISCONNECTED": "Do It (Companion not connected)",
  "MATH_CONSTRAIN_TOOLTIP": "Ogranicz liczbę, aby była w określonych granicach (włącznie).",
  "LANG_MATH_COMPARE_EQ": "=",
  "TEXT_INDEXOF_HELPURL": "https://github.com/google/blockly/wiki/Text#finding-text",
  "LOGIC_NEGATE_HELPURL": "https://github.com/google/blockly/wiki/Logic#not",
  "LANG_CONTROLS_FOR_INPUT_TO": "do",
  "LISTS_SET_INDEX_TOOLTIP_SET_RANDOM": "Ustawia losowy element na liście.",
  "LANG_MATH_FORMAT_AS_DECIMAL_INPUT": "formatuj jako dziesiętną liczba %1 miejsca %2",
  "LANG_CONTROLS_WHILE_TOOLTIP": "Uruchamia bloki w sekcji \u201ewykonaj\u201d, gdy test jest \u201eprawdziwy\u201d.",
  "LANG_MATH_DIVIDE_TOOLTIP_REMAINDER": "Zwraca resztę.",
  "DIALOG_SUBMIT": "Submit",
  "TEXT_CHARAT_HELPURL": "https://github.com/google/blockly/wiki/Text#extracting-text",
  "LANG_CONTROLS_FOREACH_INPUT_INLIST": "na liście",
  "LANG_PROCEDURES_CALLNORETURN_CALL": "wołaj",
  "LANG_LOGIC_OPERATION_AND": "i",
  "COLOUR_RANDOM_HELPURL": "http://randomcolour.com",
  "LANG_LISTS_JOIN_WITH_SEPARATOR_LIST": "lista",
  "LISTS_CREATE_EMPTY_TOOLTIP": "Zwraca listę, o długości 0, nie zawierającą rekordów z danymi",
  "LANG_LISTS_TO_CSV_TABLE_INPUT_LIST": "lista",
  "MATH_ONLIST_OPERATOR_RANDOM": "losowy element z listy",
  "LANG_TEXT_STARTS_AT_INPUT_STARTS_AT": "zaczyna się w",
  "DELETE_BLOCK": "Usuń blok",
  "TIME_SECONDS": "Seconds",
  "LANG_MATH_BITWISE_TOOLTIP_IOR": "Zwraca OR włącznie z dwoma liczbami.",
  "LANG_LOGIC_OPERATION_TOOLTIP_OR": "Zwraca Prawda, jeśli jakieś dane wejściowe są prawdziwe.",
  "LANG_TEXT_SEGMENT_INPUT_LENGTH": "długość",
  "LANG_MATH_DIVIDE_OPERATOR_MODULO": "modulo z",
  "LISTS_GET_INDEX_FROM_END": "# od końca",
  "CONTROLS_IF_MSG_ELSE": "w przeciwnym razie",
  "LOGIC_TERNARY_IF_FALSE": "jeśli fałsz",
  "LANG_MATH_DIVIDE_OPERATOR_REMAINDER": "reszta z",
  "LANG_MATH_COMPARE_GT": ">",
  "LANG_MATH_ROUND_TOOLTIP_FLOOR": "Zaokrągla dane do największej liczby, nie większej niż dana liczba.",
  "LANG_CONTROLS_FOR_INPUT_WITH": "Oblicz z",
  "LANG_TEXT_CONTAINS_INPUT_CONTAINS": "zawiera",
  "MATH_SINGLE_TOOLTIP_ABS": "Zwróć wartość bezwzględną danej liczby.",
  "TEXT_APPEND_TO": "do",
  "WRONG_TYPE_BLOCK_WARINGS": "This block should be connected to an event block or a procedure definition",
  "LISTS_SPLIT_TOOLTIP_SPLIT": "Rozdziela tekst na listę mniejszych tekstów, dzieląc na każdym separatorze.",
  "LISTS_SET_INDEX_TOOLTIP_SET_LAST": "Ustawia ostatni element na liście.",
  "REPL_OK_LOWER": "Ok",
  "LANG_MATH_SINGLE_TOOLTIP_EXP": "Zwraca e (2.71828 ...) do potęgi liczby.",
  "LANG_VARIABLES_LOCAL_DECLARATION_EXPRESSION_IN_RETURN": "w",
  "LISTS_GET_INDEX_FIRST": "pierwszy",
  "LANG_TEXT_SEGMENT_AT_TOOLTIP": "Wyodrębnia człon o podanej długości z podanego tekstu, zaczynając od podanego tekstu począwszy od podanej pozycji. Pozycja 1 oznacza początek tekstu.",
  "LANG_LISTS_LENGTH_INPUT_LIST": "lista",
  "LISTS_GET_INDEX_TOOLTIP_GET_FIRST": "Zwraca pierwszy element z listy.",
  "LANG_TEXT_TEXT_IS_STRING_TOOLTIP": "Zwraca Prawdę, jeśli <code>obiekt<\/code> jest łańcuchem.",
  "TEXT_TRIM_HELPURL": "https://github.com/google/blockly/wiki/Text#trimming-removing-spaces",
  "LANG_MATH_ARITHMETIC_MINUS": "-",
  "CONTROLS_IF_IF_TOOLTIP": "Dodaj, usuń lub zmień kolejność bloków, żeby zmodyfikować ten blok \u201ejeśli\u201d.",
  "LANG_VARIABLES_GLOBAL_PREFIX": "globalna",
  "LANG_TEXT_APPEND_APPENDTEXT": "dołącz tekst",
  "LANG_CONTROLS_CLOSE_SCREEN_WITH_PLAIN_TEXT_TITLE": "zamknij ekran ze zwykłym tekstem",
  "LANG_CONTROLS_WHILEUNTIL_TITLE_REPEAT": "powtórz",
  "CONTROLS_FOR_HELPURL": "https://github.com/google/blockly/wiki/Loops#count-with",
  "LISTS_INDEX_FROM_END_TOOLTIP": "%1 to ostatni element.",
  "LANG_TEXT_SPLIT_OPERATOR_SPLIT": "podziel",
  "LANG_CONTROLS_WHILEUNTIL_TOOLTIP_1": "Runs the blocks in the 'do' section while the test is true.",
  "LANG_MATH_ARITHMETIC_TOOLTIP_DIVIDE": "Zwraca iloczyn dwóch liczb.",
  "LANG_MATH_COMPARE_TOOLTIP_GT": "Zwraca Prawda, jeśli pierwsza liczba jest większa niż druga liczba.",
  "MATH_TRIG_TOOLTIP_ACOS": "Zwróć arcus cosinus danej liczby.",
  "MATH_ONLIST_OPERATOR_MEDIAN": "mediana listy",
  "LANG_TEXT_CONTAINS_INPUT": "zawiera tekst %1 fragment %2",
  "LANG_CONTROLS_CLOSE_SCREEN_WITH_PLAIN_TEXT_TOOLTIP": "Zamyka bieżący ekran i zwraca tekst do aplikacji, która go otworzyła. To polecenie służy do zwracania tekstu do działań innych niż aplikacja Inventor, a nie do ekranów aplikacji Inventor. W przypadku ekranów aplikacji Inventor, podobnie jak w aplikacjach z wieloma ekranami, użyj opcji Zamknij ekran z wartością, a nie Zamknij ekran z prostym tekstem.",
  "LANG_MATH_ROUND_OPERATOR_ROUND": "zaokrąglenie",
  "LANG_PROCEDURES_MUTATORARG_TITLE": "wejście:",
  "LANG_MATH_TRIG_TOOLTIP_COS": "Podaje cosinus kąta w stopniach.",
  "MATH_ONLIST_TOOLTIP_MAX": "Zwróć największą liczbę w liście.",
  "LANG_COLOUR_MAGENTA": "magenta",
  "LANG_MATH_CONVERT_NUMBER_TOOLTIP_DEC_TO_BIN": "Przekształca liczbę całkowitą dodatnią na ciąg stanowiący liczbę binarną",
  "LANG_CONTROLS_BREAK_COLLAPSED_TEXT": "Przerwij",
  "LOGIC_NEGATE_TITLE": "nie %1",
  "CONTROLS_IF_TOOLTIP_4": "Jeśli pierwsza wartość jest prawdziwa, wykonaj pierwszy blok instrukcji.  W przeciwnym razie jeśli druga wartość jest prawdziwa, wykonaj drugi blok instrukcji.  Jeżeli żadna z wartości nie jest prawdziwa, wykonaj ostatni blok instrukcji.",
  "CONTROLS_IF_TOOLTIP_3": "Jeśli pierwsza wartość jest prawdziwa, to wykonaj pierwszy blok instrukcji.  W przeciwnym razie, jeśli druga wartość jest prawdziwa, to wykonaj drugi blok instrukcji.",
  "LANG_CONTROLS_OPEN_ANOTHER_SCREEN_TOOLTIP": "Otwiera nowy ekran w aplikacji z wieloma ekranami.",
  "CONTROLS_IF_TOOLTIP_2": "Jeśli wartość jest prawdziwa, to wykonaj pierwszy blok instrukcji.  W przeciwnym razie, wykonaj drugi blok instrukcji.",
  "CONTROLS_IF_TOOLTIP_1": "Jeśli wartość jest prawdziwa, to wykonaj kilka instrukcji.",
  "MATH_CHANGE_HELPURL": "https://en.wikipedia.org/wiki/Programming_idiom#Incrementing_a_counter",
  "PROCEDURES_DEFNORETURN_TOOLTIP": "Tworzy funkcję bez wyniku.",
  "BACKPACK_CONFIRM_EMPTY": "Czy na pewno chcesz opróżnić plecak?",
  "LISTS_SPLIT_WITH_DELIMITER": "z separatorem",
  "LANG_TEXT_COMPARE_TOOLTIP_NEQ": "Tests whether text strings are different, ie., don't have the same\ncharacters in the same order. This is different from ordinary ≠\nin the case where the text strings are numbers: 123 and 0123 are text ≠\nbut are mathematically =.",
  "LANG_TEXT_COMPARE_TOOLTIP_LT": "Sprawdza czy tekst1 jest leksykograficznie mniejszy niż tekst2.\nJeśli jeden tekst jest prefiksem innego, krótszy tekst jest\nuważany za mniejszy. Wielnie znaki poprzedzają małe znaki.",
  "LANG_CONTROLS_OPEN_ANOTHER_SCREEN_COLLAPSED_TEXT": "otwórz ekran",
  "LANG_MATH_ARITHMETIC_POWER": "^",
  "TEXT_PROMPT_TOOLTIP_NUMBER": "Zapytaj użytkownika  o liczbę.",
  "COPY_ALLBLOCKS": "Skopiuj wszystkie bloki do plecaka",
  "LISTS_REPEAT_HELPURL": "https://github.com/google/blockly/wiki/Lists#create-list-with",
  "LANG_CATEGORY_LOGIC": "Logiczne",
  "LANG_TEXT_STARTS_AT_INPUT_TEXT": "tekst",
  "LANG_LISTS_COPY_TOOLTIP": "Tworzy kopię listy, obejmując kopiowanie wszystkich podlist",
  "LANG_MATH_RANDOM_FLOAT_TOOLTIP": "Zwraca losowy ułamek pomiędzy 0 i 1.",
  "TEXT_GET_SUBSTRING_START_FIRST": "pobierz podciąg od pierwszej litery",
  "MATH_ARITHMETIC_HELPURL": "https://pl.wikipedia.org/wiki/Arytmetyka",
  "REPL_FACTORY_RESET": "This will attempt to reset your Emulator to its 'factory' state. If you had previously updated the Companion installed in the Emulator, you will likely have to do this again.",
  "LANG_TEXT_REPLACE_ALL_TOOLTIP": "Zwraca nowy tekst uzyskany przez zastąpienie wszystkich wystąpień członu zastąpieniem.",
  "PROCEDURES_DEFNORETURN_TITLE": "do",
  "LANG_MATH_COMPARE_TOOLTIP_GTE": "Zwraca Prawda, jeśli pierwsza liczba jest większa lub równa drugiej liczbie.",
  "LANG_LISTS_INSERT_TOOLTIP": "Wstawia element na listę w określonej pozycji.",
  "MATH_TRIG_ACOS": "arccos",
  "LANG_PROCEDURES_CALLNORETURN_PROCEDURE": "funkcja",
  "LISTS_ISEMPTY_TOOLTIP": "Zwraca \"prawda\" jeśli lista jest pusta.",
  "LANG_MATH_COMPARE_TOOLTIP_EQ": "Zwraca Prawda, jeśli obie liczby są sobie równe.",
  "LANG_VARIABLES_LOCAL_DECLARATION_TITLE_INIT": "inicjuj lokalnie",
  "MATH_TRIG_TAN": "tg",
  "LANG_COLOUR_PINK": "różowy",
  "LISTS_SORT_TITLE": "sortuj %1 %2 %3",
  "LANG_TEXT_TEXT_LEFT_QUOTE": "\u201c",
  "SHOW": "Pokaż kontrolki obszaru roboczego",
  "LANG_PROCEDURES_CALLNORETURN_TOOLTIP": "Wywołaj procedurę bez wartości zwracanej.",
  "LANG_CONTROLS_EVAL_BUT_COLLAPSED_TEXT": "eval but ignore",
  "WARNING_DELETE_X_BLOCKS": "Are you sure you want to delete all %1 of these blocks?",
  "LANG_LISTS_PICK_RANDOM_TITLE_PICK_RANDOM": "wybierz losowy element",
  "LANG_CONTROLS_GET_START_VALUE_COLLAPSED_TEXT": "uzyskaj wartość początkową",
  "PROCEDURES_MUTATORARG_TITLE": "nazwa wejścia:",
  "LANG_MATH_ROUND_OPERATOR_FLOOR": "zaokrąglenie w dół",
  "MATH_IS_WHOLE": "jest liczbą całkowitą",
  "LANG_MATH_CONVERT_ANGLES_OP_DEG_TO_RAD": "stopnie na radiany",
  "REPL_COMPANION_OUT_OF_DATE": "Your Companion App is out of date. Click 'OK' to start the update. Watch your ",
  "PROCEDURES_IFRETURN_HELPURL": "http://c2.com/cgi/wiki?GuardClause",
  "PROCEDURES_CALLNORETURN_TOOLTIP": "Uruchom funkcję zdefiniowaną przez użytkownika '%1'.",
  "LISTS_GET_SUBLIST_END_FROM_START": "do #",
  "DIALOG_SECURE_ESTABLISHING": "20 Establishing Secure Connection",
  "LANG_MATH_ARITHMETIC_TOOLTIP_POWER": "Zwraca pierwszą liczbę podniesioną do potęgi drugiej liczby.",
  "CONNECT_TO_DO_IT": "You must be connected to the companion or emulator to use 'Do It'",
  "COLOUR_BLEND_COLOUR2": "kolor 2",
  "MATH_ARITHMETIC_TOOLTIP_POWER": "Zwróć pierwszą liczbę podniesioną do potęgi o wykładniku drugiej liczby.",
  "COLOUR_BLEND_COLOUR1": "kolor 1",
  "LANG_CONTROLS_EVAL_BUT_IGNORE_TITLE": "uruchom, ale ignoruj wynik",
  "LANG_VARIABLES_VARIABLE": "zmienna",
  "LISTS_SET_INDEX_TOOLTIP_INSERT_FROM": "Wstawia element w odpowiednim miejscu na liście.",
  "LISTS_SORT_TYPE_TEXT": "alfabetycznie",
  "LANG_MATH_RANDOM_SEED_INPUT_TO": "do",
  "TEXT_GET_SUBSTRING_END_LAST": "do ostatniej litery",
  "PROCEDURES_BEFORE_PARAMS": "z:",
  "LISTS_REPEAT_TITLE": "stwórz listę, powtarzając element %1 %2 razy",
  "MATH_ONLIST_OPERATOR_MODE": "dominanty listy",
  "PROCEDURE_CATEGORY": "Funkcje",
  "LANG_TEXT_TRIM_TOOLTIP": "Zwraca kopię argumentów ciągu tekstowego z usuniętymi spacjami początkowymi lub końcowymi.",
  "LOGIC_COMPARE_TOOLTIP_LTE": "Zwróć \"prawda\", jeśli pierwsze wejście jest większe lub równe drugiemu.",
  "LISTS_GET_SUBLIST_HELPURL": "https://github.com/google/blockly/wiki/Lists#getting-a-sublist",
  "MATH_MODULO_TOOLTIP": "Zwróć resztę z dzielenia dwóch liczb przez siebie.",
  "LANG_MATH_CONVERT_ANGLES_TOOLTIP_DEG_TO_RAD": "Zwraca wartość w radianach w zakresie\n[-π, +π) w odniesieniu do podanego w stopniach argumentu.",
  "REPL_CONNECTING_USB_CABLE": "Connecting via USB Cable",
  "LANG_PROCEDURES_DOTHENRETURN_RETURN": "wynik",
  "LANG_LOGIC_NEGATE_INPUT_NOT": "nie",
  "TEXT_TRIM_OPERATOR_BOTH": "usuń spacje po obu stronach",
  "LANG_COLOUR_SPLIT_COLOUR": "złóż kolor",
  "LANG_MATH_BITWISE_AND": "bitowo i",
  "CONTROLS_IF_HELPURL": "https://github.com/google/blockly/wiki/IfElse",
  "LISTS_GET_INDEX_RANDOM": "losowy",
  "ERROR_SELECT_VALID_ITEM_FROM_DROPDOWN": "Wybierz prawidłowy element na liście rozwijanej.",
  "LANG_LISTS_COPY_TITLE_COPY": "kopiuj listę",
  "HIDE_ALL_COMMENTS": "Ukryj wszystkie komentarze",
  "LANG_TEXT_SPLIT_INPUT_TEXT": "tekst",
  "LANG_LISTS_REMOVE_ITEM_INPUT": "usuwa element listy   lista %1 indeks %2",
  "COLOUR_RGB_TITLE": "kolor z",
  "LANG_LISTS_TO_CSV_ROW_TOOLTIP": "Interpretuje listę jako wiersz tabeli i zwraca tekst CSV (wartość rozdzielana przecinkami) reprezentujący wiersz. Każdy element na liście wierszy jest uważany za pole i jest cytowany z cudzysłowami w wynikowym tekście CSV. Przedmioty są oddzielone przecinkami. Zwrócony tekst wiersza nie ma na końcu separatora linii.",
  "LANG_CONTROLS_WHILE_INPUT_DO": "wykonaj",
  "LANG_TEXT_ISEMPTY_TOOLTIP": "Zwraca prawdę jeśli długość tekstu\nwynosi 0, fałsz w innym przypadku.",
  "DISABLE_GRID": "Wyłącz siatkę Pulpitu",
  "ERROR_BLOCK_CANNOT_BE_IN_DEFINTION": "Ten blok nie może być w definicji",
  "LISTS_GET_INDEX_GET_REMOVE": "Pobierz i usuń",
  "COLOUR_BLEND_TITLE": "wymieszaj",
  "LANG_MATH_TRIG_TAN": "tan",
  "LANG_COMPONENT_BLOCK_GENERIC_METHOD_TITLE_FOR_COMPONENT": "składnika",
  "COLLAPSE_BLOCK": "Zwiń blok",
  "MATH_RANDOM_FLOAT_TITLE_RANDOM": "losowy ułamek",
  "LANG_LISTS_REPLACE_ITEM_TOOLTIP": "Zastępuje n-ty element na liście.",
  "TEXT_PROMPT_TYPE_TEXT": "poproś o tekst z tą wiadomością",
  "LANG_MATH_SINGLE_TOOLTIP_ROOT": "Zwraca pierwiastek kwadratowy z liczby.",
  "REPL_YOUR_CODE_IS": "Your code is",
  "LANG_MATH_TRIG_ATAN2_X": "x",
  "LANG_CONTROLS_OPEN_ANOTHER_SCREEN_WITH_START_VALUE_COLLAPSED_TEXT": "otwórz ekran z wartością",
  "LANG_MATH_TRIG_ATAN2_Y": "y",
  "TEXT_PROMPT_TOOLTIP_TEXT": "Zapytaj użytkownika o jakiś tekst.",
  "LANG_LISTS_TO_CSV_TABLE_TITLE_TO_CSV": "lista do tabeli CSV",
  "REPL_CONNECT_TO_COMPANION": "Connect to Companion",
  "LANG_TEXT_SPLIT_OPERATOR_SPLIT_AT_ANY": "podziel na dowolnym",
  "LANG_CONTROLS_OPEN_ANOTHER_SCREEN_WITH_START_VALUE_INPUT_SCREENNAME": "nazwaEkranu",
  "LANG_PROCEDURES_DOTHENRETURN_TOOLTIP": "Uruchamia bloki w 'wykonaj' i zwraca wynik. Przydatne, jeśli musisz uruchomić funkcję przed zwróceniem wartości do zmiennej.",
  "LANG_LOGIC_COMPARE_TOOLTIP_EQ": "Sprawdza, czy dwa obiekty są równe. Porównywane mogą być dowolne obiekty, nie tylko liczby. Liczby są uważane za równe drukowanej formie jako łańcuchy, na przykład liczba 0 jest równa tekstowi \u201e0\u201d. Ponadto dwa ciągi reprezentujące liczby są równe, jeśli liczby są równe, na przykład \u201e1\u201d jest równe \u201e01\u201d.",
  "TEXT_LENGTH_TOOLTIP": "Zwraca liczbę liter (łącznie ze spacjami) w podanym tekście.",
  "LANG_CONTROLS_IF_ELSEIF_TITLE_ELSEIF": "inaczej jeśli",
  "LANG_LISTS_COPY_INPUT_LIST": "lista",
  "MATH_NUMBER_HELPURL": "https://en.wikipedia.org/wiki/Number",
  "LANG_CONTROLS_FLOW_STATEMENTS_WARNING": "Ostrzeżenie: ten blok może być używany tylko w pętli.",
  "LANG_LOGIC_COMPARE_EQ": "=",
  "LANG_CONTROLS_CLOSE_SCREEN_WITH_VALUE_COLLAPSED_TEXT": "zamknij ekran z wartością",
  "LANG_TEXT_STARTS_AT_INPUT_PIECE": "fragment",
  "LANG_MATH_ROUND_TOOLTIP_CEILING": "Zaokrągla dane do najmniejszej liczby, nie mniejszej niż dana liczba.",
  "MATH_CONSTRAIN_HELPURL": "https://en.wikipedia.org/wiki/Clamping_%28graphics%29",
  "LANG_CONTROLS_OPEN_ANOTHER_SCREEN_WITH_START_VALUE_TITLE": "otwórz kolejny ekran z wartością początkową",
  "LANG_LISTS_TO_CSV_ROW_INPUT_LIST": "lista",
  "LANG_PROCEDURES_DEFRETURN_RETURN": "wynik",
  "LANG_MATH_ONLIST_TOOLTIP_MIN": "Zwraca minimalny z podanych argumentów..",
  "LANG_LISTS_REPLACE_ITEM_INPUT_LIST": "lista",
  "LANG_LISTS_TO_CSV_TABLE_TOOLTIP": "Interpretuje listę jako tabelę w formacie głównym wiersza i zwraca tekst CSV (wartość rozdzielana przecinkami) reprezentujący tabelę. Każda pozycja na liście powinna sama być listą reprezentującą wiersz tabeli CSV. Każdy element na liście wierszy jest uważany za pole i jest cytowany z cudzysłowami w wynikowym tekście CSV. W zwróconym tekście elementy w wierszach są oddzielone przecinkami, a wiersze oddzielone są CRLF ().",
  "LANG_LISTS_SELECT_ITEM_INPUT_INDEX": "indeks",
  "CHANGE_VALUE_TITLE": "Zmiana waluty:",
  "LANG_LISTS_JOIN_WITH_SEPARATOR_SEPARATOR": "separator",
  "MATH_SINGLE_OP_ROOT": "pierwiastek kwadratowy",
  "TEXT_CHARAT_LAST": "pobierz ostatnią literę",
  "LANG_MATH_CONVERT_ANGLES_TITLE_CONVERT": "przekształcenie",
  "LANG_MATH_ARITHMETIC_TOOLTIP_MINUS": "Zwraca różnicę dwóch liczb.",
  "LANG_MATH_BITWISE_TOOLTIP_XOR": "Zwraca OR włącznie z dwoma liczbami.",
  "LANG_LISTS_IS_LIST_TITLE_IS_LIST": "jest listą?",
  "PROCEDURES_DEFRETURN_TOOLTIP": "Tworzy funkcję z wynikiem.",
  "LANG_LISTS_INSERT_INPUT_LIST": "lista",
  "REPL_NETWORK_ERROR": "Network Error",
  "SORT_C": "Sortuj bloki według kategorii",
  "REPL_CONNECTING": "Connecting...",
  "LANG_MATH_IS_A_NUMBER_INPUT_NUM": "czy liczba?",
  "LISTS_GET_SUBLIST_END_LAST": "do ostatniego",
  "SORT_H": "Sortuj bloki według wysokości",
  "LANG_COMPONENT_BLOCK_GENERIC_SETTER_TITLE_OF_COMPONENT": "składnika",
  "LISTS_GET_INDEX_TOOLTIP_GET_FROM": "Zwraca element z konkretnej pozycji na liście.",
  "REPL_DEVICES": "device's",
  "TEXT_CHANGECASE_OPERATOR_TITLECASE": "zmień na od Wielkich Liter",
  "VARIABLES_SET": "przypisz %1 wartość %2",
  "LANG_CONTROLS_FORRANGE_INPUT_STEP": "przez",
  "SORT_W": "Sortuj bloki według szerokości",
  "LANG_MATH_RANDOM_INT_INPUT": "losowa liczba całkowita od %1 do %2",
  "LANG_LOGIC_COMPARE_TOOLTIP_NEQ": "Zwraca Prawdę, jeśli obie wprowadzone wartości nie są sobie równe.",
  "LANG_CONTROLS_FORRANGE_INPUT_COLLAPSED_PREFIX": "dla",
  "LANG_PROCEDURES_CALLRETURN_TOOLTIP": "Wywołaj procedurę z wartością zwracaną.",
  "LISTS_SPLIT_HELPURL": "https://github.com/google/blockly/wiki/Lists#splitting-strings-and-joining-lists",
  "LANG_LISTS_REPLACE_ITEM_INPUT_INDEX": "indeks",
  "TODAY": "Dzisiaj",
  "LISTS_INLIST": "na liście",
  "LANG_CONTROLS_IF_ELSE_TOOLTIP": "Dodaj ostateczny warunek catch-all do bloku Jeśli.",
  "LOGIC_COMPARE_HELPURL": "https://pl.wikipedia.org/wiki/Nierówność",
  "REPL_USB_CONNECTED_WAIT": "USB Connected, waiting ",
  "LANG_MATH_TRIG_TOOLTIP_ACOS": "Podaje kąt w zakresie [0, 180)\nstopni z daną wartością cosinus.",
  "LANG_COLOUR_BLUE": "niebieski",
  "COLOUR_RANDOM_TITLE": "losowy kolor",
  "LANG_MATH_SINGLE_TOOLTIP_NEG": "Zwraca negację liczby.",
  "LANG_CONTROLS_FOREACH_TOOLTIP": "Uruchamia bloki w sekcji \u201ewykonaj\u201d dla każdego elementu na liście. Użyj podanej nazwy zmiennej, aby odnieść się do bieżącego elementu listy.",
  "LANG_TEXT_REPLACE_ALL_INPUT_SEGMENT": "człon",
  "MATH_ROUND_OPERATOR_ROUNDUP": "zaokrąglij w górę",
  "LANG_TEXT_SPLIT_AT_SPACES_TITLE": "dziel w spacjach",
  "REPL_GIVE_UP": "Give Up",
  "MATH_ROUND_OPERATOR_ROUNDDOWN": "zaokrąglij w dół",
  "LANG_MATH_IS_A_DECIMAL_INPUT_NUM": "czy Base 10?",
  "MATH_ONLIST_TOOLTIP_MODE": "Zwróć listę najczęściej występujących elementów w liście.",
  "LISTS_SET_INDEX_TOOLTIP_INSERT_FIRST": "Wstawia element na początku listy.",
  "LANG_CONTROLS_WHILEUNTIL_TOOLTIP_WHILE": "Gdy wartość jest Prawdą, wykonaj kilka instrukcji.",
  "LANG_LISTS_REMOVE_ITEM_INPUT_LIST": "lista",
  "LANG_MATH_IS_A_HEXADECIMAL_INPUT_NUM": "czy hexadecymalna?",
  "LANG_VARIABLES_GET_COLLAPSED_TEXT": "Pobierz",
  "LANG_MATH_ONLIST_OPERATOR_MAX": "max",
  "LANG_COMPONENT_BLOCK_TITLE_DO": "wykonaj",
  "LANG_CONTROLS_FOR_INPUT_DO": "wykonaj",
  "LANG_CONTROLS_FLOW_STATEMENTS_OPERATOR_CONTINUE": "kontynuuj następną iterację",
  "MATH_ONLIST_HELPURL": "",
  "MATH_CHANGE_TOOLTIP": "Dodaj liczbę do zmiennej '%1'.",
  "LANG_MATH_BITWISE_TOOLTIP_AND": "Zwraca bitowy AND dwóch liczb.",
  "LANG_LISTS_ADD_ITEMS_INPUT_ITEM": "pozycja",
  "TEXT_LENGTH_HELPURL": "https://github.com/google/blockly/wiki/Text#text-modification",
  "PROCEDURES_CALLNORETURN_HELPURL": "https://pl.wikipedia.org/wiki/Podprogram",
  "MISSING_SOCKETS_WARNINGS": "You should fill all of the sockets with blocks",
  "MATH_SINGLE_OP_ABSOLUTE": "wartość bezwzględna",
  "CLEAR_DO_IT_ERROR": "Clear Error",
  "EXTERNAL_INPUTS": "Wejścia zewnętrzne",
  "LANG_PROCEDURES_MUTATORARG_TOOLTIP": "",
  "LANG_MATH_FORMAT_AS_DECIMAL_TITLE": "format dziesiętny",
  "LANG_TEXT_REPLACE_ALL_INPUT": "zastąp cały tekst %1 segment %2 zastąpienie %3",
  "LISTS_INDEX_OF_HELPURL": "https://github.com/google/blockly/wiki/Lists#getting-items-from-a-list",
  "TEXT_PRINT_TITLE": "wydrukuj %1",
  "LANG_TEXT_SPLIT_TOOLTIP_SPLIT_AT_ANY": "Dzieli dany tekst na listę, używając dowolnego elementu z listy 'w' jako 'punktu podziału' i zwraca listę wyników. Dzielenie \u201ejabłka,śliwka,wiśnia,gruszka\u201d z 'ka' jako dwuelementowej listy, której pierwszym elementem jest przecinek, a którego drugim elementem jest 'ka', zwraca listę czterech przedmiotów: '(jabł śliw wiśnia grusz)'",
  "LANG_VARIABLES_GLOBAL_DECLARATION_TOOLTIP": "Tworzy zmienną globalną i nadaje jej wartość dołączonych bloków.",
  "LANG_PROCEDURES_DEFNORETURN_COLLAPSED_PREFIX": "do",
  "LANG_CONTROLS_BREAK_TITLE": "Przerwij",
  "PROCEDURES_HIGHLIGHT_DEF": "Podświetl definicję funkcji",
  "LANG_CATEGORY_CONTROLS": "Kontrola",
  "CONTROLS_WHILEUNTIL_OPERATOR_WHILE": "powtarzaj dopóki",
  "LISTS_GET_INDEX_TOOLTIP_GET_REMOVE_FIRST": "Usuwa i zwraca pierwszy element z listy.",
  "TEXT_CHANGECASE_HELPURL": "https://github.com/google/blockly/wiki/Text#adjusting-text-case",
  "REPL_NOT_NOW": "Not Now",
  "REPL_COMPANION_STARTED_WAITING": "Companion starting, waiting ",
  "NEW_VARIABLE_TITLE": "Nowa nazwa zmiennej:",
  "LISTS_ISEMPTY_HELPURL": "https://github.com/google/blockly/wiki/Lists#is-empty",
  "LISTS_INDEX_FROM_START_TOOLTIP": "%1 to pierwszy element.",
  "LOGIC_TERNARY_HELPURL": "https://en.wikipedia.org/wiki/%3F:",
  "LANG_LISTS_LOOKUP_IN_PAIRS_INPUT_KEY": "klucz",
  "LANG_PROCEDURES_CALLRETURN_COLLAPSED_PREFIX": "wołaj",
  "TIME_DAYS": "Days",
  "CONTROLS_FOREACH_TOOLTIP": "Dla każdego elementu listy ustaw zmienną %1 na ten element, a następnie wykonaj kilka instrukcji.",
  "LISTS_GET_SUBLIST_TOOLTIP": "Tworzy kopię z określoną część listy.",
  "LANG_COLOUR_BLACK": "czarny",
  "LOGIC_NULL_TOOLTIP": "Zwraca nic.",
  "LANG_CONTROLS_GET_START_VALUE_TOOLTIP": "Zwraca wartość, która została przekazana do tego ekranu po jego otwarciu, zazwyczaj przez inny ekran w aplikacji wieloekranowej. Jeśli nie przekazano żadnej wartości, zwraca pusty tekst.",
  "LANG_MATH_ONLIST_TOOLTIP_MAX": "Zwraca maksymalny z podanych argumentów..",
  "LANG_VARIABLES_GLOBAL_DECLARATION_NAME": "nazwa",
  "LANG_PROCEDURES_HIGHLIGHT_DEF": "Zaznacz funkcję",
  "ERROR_BLOCK_IS_NOT_DEFINED": "Ten blok nie jest zdefiniowany. Usuń ten blok!",
  "LANG_MATH_SINGLE_OP_ROOT": "pierwiastek kwadratowy",
  "LISTS_GET_INDEX_REMOVE": "usuń",
  "REPL_OK": "OK",
  "LANG_MATH_SINGLE_OP_LN": "log",
  "MATH_ONLIST_OPERATOR_MAX": "maksymalna wartość z listy",
  "LANG_CONTROLS_OPEN_ANOTHER_SCREEN_WITH_START_VALUE_INPUT_STARTVALUE": "wartośćPoczątkowa",
  "LISTS_INDEX_OF_LAST": "znajduje ostatanie wystąpienie elementu",
  "LISTS_GET_INDEX_TOOLTIP_GET_REMOVE_LAST": "Usuwa i zwraca ostatni element z listy.",
  "LANG_MATH_RANDOM_INT_INPUT_FROM": "z/od",
  "LANG_PROCEDURES_DOTHENRETURN_THEN_RETURN": "wynik",
  "LANG_CONTROLS_FLOW_STATEMENTS_INPUT_OFLOOP": "pętli",
  "VARIABLE_ALREADY_EXISTS": "Zmienna o nazwie '%1' już istnieje.",
  "LANG_LOGIC_OPERATION_OR": "lub",
  "ENABLE_ALL_BLOCKS": "Włącz wszystkie bloki",
  "TEXT_APPEND_APPENDTEXT": "dołącz tekst",
  "LANG_LOGIC_COMPARE_NEQ": "≠",
  "VERTICAL_PARAMETERS": "Rozmieść parametry w pionie",
  "LANG_VARIABLES_LOCAL_DECLARATION_INPUT_TO": "do",
  "CONTROLS_REPEAT_HELPURL": "https://en.wikipedia.org/wiki/For_loop",
  "LANG_LISTS_INSERT_TITLE_INSERT_LIST": "wstaw element listy",
  "UNGENERICIZE_BLOCK": "Określ",
  "PROCEDURES_DEFRETURN_HELPURL": "https://en.wikipedia.org/wiki/Procedure_%28computer_science%29",
  "TEXT_GET_SUBSTRING_TOOLTIP": "Zwraca określoną część tekstu.",
  "LANG_CONTROLS_GET_START_VALUE_TITLE": "uzyskaj wartość początkową",
  "LANG_PROCEDURES_CALLNORETURN_TRANSLATED_NAME": "wołaj bez zwrotu wartości",
  "LISTS_LENGTH_HELPURL": "https://github.com/google/blockly/wiki/Lists#length-of",
  "PROCEDURES_CREATE_DO": "Stwórz '%1'",
  "REPL_GOT_IT": "Got It",
  "LANG_CONTROLS_CLOSE_SCREEN_TITLE": "zamknij ekran",
  "LISTS_SORT_TOOLTIP": "Sortuj kopię listy.",
  "TEXT_ISEMPTY_TOOLTIP": "Zwraca prawda (true), jeśli podany tekst jest pusty.",
  "LANG_CONTROLS_CHOOSE_INPUT_ELSE_RETURN": "inaczej",
  "LANG_MATH_SINGLE_TOOLTIP_ABS": "Zwraca wartość bezwzględną liczby.",
  "PROCEDURES_IFRETURN_WARNING": "Uwaga: Ten blok może być używany tylko w definicji funkcji.",
  "LANG_LISTS_REMOVE_ITEM_INPUT_INDEX": "indeks",
  "LOGIC_OPERATION_TOOLTIP_OR": "Zwróć \"prawda\" jeśli co najmniej jeden dany element ma wartość \"prawda\".",
  "MATH_RANDOM_FLOAT_HELPURL": "https://en.wikipedia.org/wiki/Random_number_generation",
  "CONTROLS_FOREACH_TITLE": "dla każdego elementu %1 na liście %2",
  "LOGIC_NULL_HELPURL": "https://en.wikipedia.org/wiki/Nullable_type",
  "LANG_MATH_ARITHMETIC_MULTIPLY": "*",
  "LANG_LISTS_REMOVE_ITEM_TOOLTIP": "Usuwa element z określonej pozycji listy.",
  "LANG_CONTROLS_OPEN_ANOTHER_SCREEN_INPUT_SCREENNAME": "nazwaEkranu",
  "LANG_MATH_TRIG_TOOLTIP_TAN": "Podaje tangens kąta w stopniach.",
  "REPL_UNABLE_TO_LOAD": "Unable to load update from App Inventor server",
  "LANG_MATH_CONVERT_NUMBER_TOOLTIP_HEX_TO_DEC": "Przekształca ciąg stanowiący liczbę hexadecymalną na ciąg stanowiący liczbę całkowitą dodatnią",
  "LANG_VARIABLES_LOCAL_DECLARATION_IN_DO": "w",
  "LANG_COLOUR_ORANGE": "pomarańczowy",
  "LANG_COLOUR_CYAN": "cyjan",
  "REPL_NETWORK_CONNECTION_ERROR": "Network Connection Error",
  "LANG_LISTS_REMOVE_ITEM_TITLE_REMOVE": "usuwa element listy",
  "LISTS_GET_INDEX_GET": "pobierz",
  "CONFIRM_DELETE": "Potwierdź usunięcie",
  "LANG_TEXT_APPEND_TO": "do",
  "MATH_CHANGE_TITLE": "zmień %1 o %2",
  "LANG_MATH_ONLIST_OPERATOR_MIN": "min",
  "ENABLE_BLOCK": "Włącz blok",
  "LOGIC_BOOLEAN_FALSE": "fałsz",
  "TEXT_CHARAT_FROM_END": "pobierz literę # od końca",
  "LANG_LISTS_POSITION_IN_INPUT": "indeks na liście  obiekt %1 lista %2",
  "COPY_TO_BACKPACK": "Dodaj do plecaka",
  "BACKPACK_EMPTY": "Opróżnij plecak",
  "LANG_MATH_ARITHMETIC_TOOLTIP_ADD": "Zwraca sumę dwóch liczb.",
  "REPL_HELPER_NOT_RUNNING": "The aiStarter helper does not appear to be running<br /><a href='http://appinventor.mit.edu' target='_blank'>Need Help?<\/a>",
  "LANG_MATH_COMPARE_GTE": "≥",
  "LOGIC_OPERATION_AND": "i",
  "LANG_PROCEDURES_DEFNORETURN_DO": "wykonaj",
  "SHOW_BACKPACK_DOCUMENTATION": "Pokaż dokumentację plecaka",
  "CAN_NOT_DO_IT": "Cannot Do it",
  "LANG_TEXT_COMPARE_TOOLTIP_GT": "Sprawdza czy tekst1 jest leksykograficznie większy niż tekst2.\nJeśli jeden tekst jest przefiksem innego, krótszy tekst jest uważany za mniejszy.\nWielkie znaki poprzedzają małe.",
  "LANG_MATH_ROUND_TOOLTIP_ROUND": "Zaokrąglanie liczby w górę lub w dół.",
  "LANG_MATH_IS_A_NUMBER_TOOLTIP": "Sprawdza czy dane są liczbą.",
  "LANG_LISTS_INPUT_LIST": "lista",
  "LANG_TEXT_JOIN_TITLE_CREATEWITH": "stwórz tekst z",
  "LANG_MATH_COMPARE_LT": "<",
  "LISTS_GET_INDEX_TOOLTIP_GET_LAST": "Zwraca ostatni element z listy.",
  "LANG_TEXT_SPLIT_INPUT_AT": "w",
  "LISTS_LENGTH_TOOLTIP": "Zwraca długość listy.",
  "LANG_MATH_COMPARE_TOOLTIP_NEQ": "Zwraca Prawda, jeśli obie liczby nie są sobie równe.",
  "LANG_LISTS_SELECT_ITEM_TITLE_SELECT": "wybierz element listy",
  "LANG_LISTS_POSITION_IN_TOOLTIP": "Odnajduje pozycję obiektu na liście. Jeśli go nie ma, zwraca 0.",
  "LISTS_SET_INDEX_INPUT_TO": "jako",
  "LANG_TEXT_JOIN_TITLE_JOIN": "łącz",
  "UNDEFINED_BLOCK_TOOLTIP": "Ten blok nie jest zdefiniowany. Usuń ten blok!",
  "LANG_PROCEDURES_CALLRETURN_TRANSLATED_NAME": "wołaj ze zwrotem wartości",
  "TEXT_CHARAT_TOOLTIP": "Zwraca literę z określonej pozycji.",
  "LANG_LISTS_ADD_ITEMS_TOOLTIP": "Dodaje elementy na końcu listy.",
  "CONTROLS_REPEAT_TOOLTIP": "Wykonaj niektóre instrukcje kilka razy.",
  "DIALOG_FOUND_COMPANION": "10 Found the Companion",
  "LANG_TEXT_STARTS_AT_TOOLTIP": "Zwraca indeks początkowy fragmentu w tekście, gdzie indeks 1 oznacza początek tekstu. Zwraca 0, jeśli element nie znajduje się w tekście.",
  "LANG_VARIABLES_GLOBAL_DECLARATION_TO": "do",
  "HIDE": "Ukryj kontrolki obszaru roboczego",
  "LANG_MATH_TRIG_COS": "cos",
  "CONTROLS_IF_ELSEIF_TOOLTIP": "Dodaj warunek do bloku \u201ejeśli\u201d.",
  "RENAME_VARIABLE": "Zmień nazwę zmiennej...",
  "LISTS_SET_INDEX_TOOLTIP_INSERT_RANDOM": "Wstawia element w losowym miejscu na liście.",
  "LANG_LISTS_APPEND_LIST_TOOLTIP": "Dołącza wszystkie elementy z listy2 na końcu listy1. Po dołączeniu lista1 będzie zawierać te dodatkowe elementy, ale lista2 pozostanie niezmieniona.",
  "REPL_COMPANION_VERSION_CHECK": "Companion Version Check",
  "PROCEDURES_IFRETURN_TOOLTIP": "Jeśli wartość jest prawdziwa, zwróć drugą wartość.",
  "TEXT_CHARAT_INPUT_INTEXT": "z tekstu",
  "TEXT_CHARAT_RANDOM": "pobierz losową literę",
  "MATH_IS_POSITIVE": "jest dodatnia",
  "EXPORT_IMAGE": "Pobierz bloki jako obraz",
  "REPL_RUNTIME_ERROR": "Runtime Error",
  "REPL_CONNECTION_FAILURE1": "Connection Failure",
  "REPL_NO_START_EMULATOR": "We could not start the MIT AI Companion within the Emulator",
  "LANG_LOGIC_BOOLEAN_TRUE": "Prawda",
  "LANG_TEXT_JOIN_ITEM_TOOLTIP": "",
  "LANG_CONTROLS_FLOW_STATEMENTS_TOOLTIP_CONTINUE": "Pomiń resztę tej pętli i przejdź do następnej iteracji.",
  "MATH_SINGLE_TOOLTIP_ROOT": "Zwróć pierwiastek kwadratowy danej liczby.",
  "MATH_SINGLE_TOOLTIP_NEG": "Zwróć negację danej liczby.",
  "LANG_LISTS_JOIN_WITH_SEPARATOR_TOOLTIP": "Zwraca tekst z elementami listy połączonymi z separatorem",
  "MATH_ONLIST_TOOLTIP_SUM": "Zwróć sumę wszystkich liczb z listy.",
  "MATH_RANDOM_INT_HELPURL": "https://en.wikipedia.org/wiki/Random_number_generation",
  "LANG_COMPONENT_BLOCK_GENERIC_GETTER_TITLE_OF_COMPONENT": "składnika",
  "LANG_CONTROLS_DO_THEN_RETURN_TOOLTIP": "Uruchamia bloki w 'wykonaj' i zwraca rezultat. Przydatne, jeśli musisz uruchomić funkcję przed zwróceniem wartości do zmiennej.",
  "MATH_SINGLE_TOOLTIP_EXP": "Zwróć e do potęgi danej liczby.",
  "TEXT_GET_SUBSTRING_END_FROM_START": "do # litery",
  "MATH_ONLIST_TOOLTIP_MIN": "Zwróć najmniejszą liczbę w liście.",
  "REPL_CANCEL": "Cancel",
  "LISTS_SORT_TYPE_NUMERIC": "numerycznie",
  "LANG_LISTS_FROM_CSV_TABLE_TOOLTIP": "Analizuje tekst jako sformatowaną tabelę CSV (wartość rozdzielana przecinkami), aby utworzyć listę wierszy, z których każdy jest listą pól. Wiersze mogą być oddzielone znakami nowej linii () lub CRLF ().",
  "LANG_VARIABLES_GET_TITLE_GET": "uzyskaj",
  "LANG_TEXT_SPLIT_TOOLTIP_SPLIT": "Dzieli tekst na kawałki, używając tekstu 'w' jako punktów podziału i tworzy listę wyników. Podział 'jeden,dwa,trzy,cztery' na ',' (przecinek) zwraca listę '(jeden dwa trzy cztery)'. Podział 'jeden ziemniak,dwa ziemniaki,trzy ziemniaki,cztery ziemniaki' w 'ziemniaki' zwraca listę '(jeden dwa trzy cztery)'.",
  "REPL_TRY_AGAIN1": "Failed to Connect to the MIT AI2 Companion, try again.",
  "MATH_TRIG_TOOLTIP_COS": "Zwróć wartość cosinusa o stopniu (nie w radianach).",
  "TEXT_GET_SUBSTRING_HELPURL": "https://github.com/google/blockly/wiki/Text#extracting-a-region-of-text",
  "LANG_CONTROLS_FOR_INPUT_VAR": "x",
  "MATH_MODULO_HELPURL": "https://pl.wikipedia.org/wiki/Modulo",
  "LANG_TEXT_APPEND_TOOLTIP": "Dodaje jakiś tekst do zmiennej '%1'.",
  "CONTROLS_FLOW_STATEMENTS_OPERATOR_CONTINUE": "przejdź do kolejnej iteracji pętli",
  "REPL_WEBRTC_CONNECTION_ERROR": "Companion Connection Error",
  "LISTS_GET_INDEX_TOOLTIP_REMOVE_RANDOM": "Usuwa losowy element z listy.",
  "MATH_ARITHMETIC_TOOLTIP_MINUS": "Zwróć różnicę dwóch liczb.",
  "LANG_LISTS_FROM_CSV_TABLE_INPUT_TEXT": "tekst",
  "PROCEDURES_DEFNORETURN_COMMENT": "Opisz tę funkcję...",
  "LANG_COLOUR_MAKE_COLOUR": "stwórz kolor",
  "LANG_MATH_TRIG_ASIN": "asin",
  "LANG_LISTS_POSITION_IN_TITLE_POSITION": "indeks na liście",
  "TEXT_CHANGECASE_TOOLTIP": "Zwraca kopię tekstu z inną wielkością liter.",
  "LANG_VARIABLES_LOCAL_DECLARATION_EXPRESSION_TOOLTIP": "Pozwala tworzyć zmienne, które są dostępne tylko w części powrotnej tego bloku.",
  "VARIABLES_DEFAULT_NAME": "element",
  "LISTS_SET_INDEX_HELPURL": "https://github.com/google/blockly/wiki/Lists#in-list--set",
  "LANG_CONTROLS_IF_ELSEIF_TOOLTIP": "Dodaj warunek do bloku Jeśli.",
  "LANG_COLOUR_GRAY": "szary",
  "GENERATE_YAIL": "Generate Yail",
  "LANG_MATH_IS_A_HEXADECIMAL_TOOLTIP": "Sprawdza czy dane są ciągiem reprezentującym liczbę hexadecymalną.",
  "LANG_LISTS_LENGTH_TOOLTIP": "Zlicza liczbę elementów na liście.",
  "REPL_HELPER_Q": "Helper?",
  "LANG_CONTROLS_IF_TOOLTIP_4": "Jeśli pierwsza wartość jest prawdziwa, wtedy wykonuje pierwszy blok instrukcji.\nInaczej, jeśli druga wartość jest prawdziwa, wykonuje drugi blok instrukcji.\nJeśli żadna z podanych wartości nie jest prawdziwa wykonuje ostatni blok instrukcji.",
  "REPL_VERIFYING_COMPANION": "Verifying that the Companion Started....",
  "LANG_CONTROLS_IF_TOOLTIP_2": "Jeśli wartość jest prawdziwa, wtedy wykonuje pierwszy blok instrukcji.\nInaczej, wykonuje drugi blok instrukcji.",
  "LANG_CONTROLS_IF_TOOLTIP_3": "Jeśli pierwsza wartość jest prawdziwa, wtedy wykonuje pierwszy blok instrukcji.\nInaczej, jeśli druga wartość jest prawdziwa, wykonuje drugi blok instrukcji.",
  "LANG_CONTROLS_IF_TOOLTIP_1": "Jeśli wartość jest prawdziwa, wykonaj podany kod.",
  "LANG_LISTS_FROM_CSV_ROW_TITLE_FROM_CSV": "lista z wiersza CSV",
  "LANG_LISTS_JOIN_WITH_SEPARATOR_INPUT": "łączy elementy za pomocą separatora %1 lista %2",
  "LANG_MATH_CONVERT_NUMBER_OP_BIN_TO_DEC": "binarna na dodatnią całkowitą",
  "TEXT_INDEXOF_TOOLTIP": "Zwraca indeks pierwszego/ostatniego wystąpienia pierwszego tekstu w drugim tekście. Zwraca wartość %1, jeśli tekst nie został znaleziony.",
  "LANG_CONTROLS_WHILEUNTIL_OPERATOR_WHILE": "gdy",
  "LANG_TEXT_SPLIT_AT_TOOLTIP": "Podziel tekst na kawałki oddzielone spacjami.",
  "LANG_PROCEDURES_DEFRETURN_COLLAPSED_PREFIX": "do",
  "MATH_TRIG_TOOLTIP_ASIN": "Zwróć arcus sinus danej liczby.",
  "LANG_PROCEDURES_CALLNORETURN_COLLAPSED_PREFIX": "wołaj",
  "LANG_COMPONENT_BLOCK_SETTER_TITLE_TO": "do",
  "LANG_CONTROLS_FORRANGE_TOOLTIP": "Uruchamia bloki w sekcji 'wykonaj' dla każdej wartości liczbowej w zakresie od początku do końca, zwiększając wartość za każdym razem. Użyj podanej nazwy zmiennej, aby odnieść się do bieżącej wartości",
  "LISTS_GET_INDEX_TAIL": "",
  "LANG_LISTS_ADD_ITEMS_TITLE_ADD": "dodaj elementy do listy",
  "MATH_DIVISION_SYMBOL": "/",
  "MATH_RANDOM_INT_TITLE": "losowa liczba całkowita od %1 do %2",
  "TEXT_CHARAT_TAIL": "",
  "CONTROLS_IF_ELSE_TOOLTIP": "Dodaj ostatni warunek do bloku \u201ejeśli\u201d, gdy żaden wcześniejszy nie był spełniony.",
  "LANG_CONTROLS_CLOSE_SCREEN_WITH_VALUE_TOOLTIP": "Zamyka bieżący ekran i zwraca wynik na ekran, który otworzył ten ekran.",
  "LANG_MATH_RANDOM_SEED_TOOLTIP": "określa cyfrowe ziarno\ndla generatoea liczb losowych",
  "CONTROLS_WHILEUNTIL_TOOLTIP_UNTIL": "Gdy wartość jest nieprawdziwa, wykonaj kilka instrukcji.",
  "LANG_COMPONENT_BLOCK_GENERIC_SETTER_TITLE_SET": "ustaw",
  "REPL_COMPANION_WRONG_PACKAGE": "The Companion you are using was built for different instance of App Inventor. To obtain the correct companion look on the App Inventor screen under Help->Companion Information menu.",
  "LANG_CONTROLS_IF_MSG_ELSE": "inaczej",
  "LANG_CONTROLS_FORRANGE_INPUT_VAR": "numeru",
  "LANG_TEXT_APPEND_VARIABLE": "pozycja",
  "LANG_TEXT_TEXT_OBFUSCATE_TOOLTIP": "Tworzy tekst jako blok tekstowy. Różnica jest taka, że\ntekst nie jest łatwo wykrywany przez aplikacje podsłuchujące. Użyj, gdy tworzysz aplikacje,\nktóre przekazują poufne dane np. klucze API.\nUwaga: Zapewnia jedynie niską ochronę wobez zaawansowanych snifferów.",
  "REMOVE_COMMENT": "Usuń komentarz",
  "LANG_TEXT_COMPARE_NEQ": " ≠",
  "LANG_PROCEDURES_MUTATORCONTAINER_TITLE": "wejścia",
  "LANG_LOGIC_COMPARE_TRANSLATED_NAME": "logiczne równa się",
  "REPL_AI_NO_SEE_DEVICE": "AI2 does not see your device, make sure the cable is plugged in and drivers are correct.",
  "MATH_RANDOM_FLOAT_TOOLTIP": "Zwróć losowy ułamek między 0.0 (włącznie), a 1.0 (wyłącznie).",
  "LANG_LISTS_IS_IN_INPUT": "jest na liście? obiekt %1 lista %2",
  "LANG_VARIABLES_GET_TOOLTIP": "Zwraca wartość tej zmiennej.",
  "TEXT_GET_SUBSTRING_START_FROM_START": "pobierz podciąg od # litery",
  "LANG_TEXT_TEXT_OBFUSCATE": "Zaciemniony Tekst",
  "NEW_VARIABLE": "Nowa zmienna ...",
  "LANG_LISTS_APPEND_LIST_INPUT_LIST2": "list2",
  "LISTS_GET_INDEX_TOOLTIP_REMOVE_FIRST": "Usuwa pierwszy element z listy.",
  "CONTROLS_FOREACH_HELPURL": "https://github.com/google/blockly/wiki/Loops#for-each",
  "LANG_CONTROLS_FLOW_STATEMENTS_OPERATOR_BREAK": "przerwa",
  "LANG_LISTS_APPEND_LIST_INPUT_LIST1": "list1",
  "LANG_CONTROLS_FORRANGE_INPUT_ITEM": "dla każdego",
  "LANG_CONTROLS_WHILE_TITLE": "gdy",
  "LANG_LISTS_FROM_CSV_ROW_TOOLTIP": "Analizuje tekst jako sformatowany wiersz w formacie CSV (wartość rozdzielana przecinkami), aby utworzyć listę pól. Jest błędem, że tekst wiersza zawiera niezmienione znaki nowej linii wewnątrz pól (efektywnie, wiele linii). W porządku jest, aby tekst wiersza kończył się pojedynczym znakiem nowej linii lub CRLF.",
  "LANG_VARIABLES_LOCAL_MUTATOR_CONTAINER_TOOLTIP": "",
  "LISTS_GET_INDEX_TOOLTIP_REMOVE_LAST": "Usuwa ostatni element z listy.",
  "LISTS_SORT_TYPE_IGNORECASE": "alfabetycznie, bez uwzględniania wielkości liter",
  "DUPLICATE_BLOCK": "Duplikuj",
  "LANG_LISTS_SELECT_ITEM_INPUT": "wybierz element listy   lista %1 indeks %2",
  "MATH_SINGLE_TOOLTIP_LOG10": "Zwraca logarytm dziesiętny danej liczby.",
  "LANG_MATH_IS_A_DECIMAL_TOOLTIP": "Sprawdza czy dane są ciągiem reprezentującym dodatnią liczbę całkowitą base 10.",
  "LANG_TEXT_SPLIT_TOOLTIP_SPLIT_AT_FIRST_OF_ANY": "Dzieli dany tekst na listę dwuelementową, wykorzystując pierwszą lokalizację dowolnego elementu \u201ew\u201d na liście jako punkt podziału. Dzielenie \u201eUwielbiam jabłka banany winogrona\u201d na liście \u201e(ja, ba)\u201d zwraca listę dwóch pozycji, z których pierwszym jest \u201eUwielbiam\u201d, a drugim \u201ebłka banany winogrona\u201d.",
  "LOGIC_TERNARY_TOOLTIP": "Sprawdź warunek w \u201etest\u201d. Jeśli warunek jest prawdziwy, to zwróci \u201ejeśli prawda\u201d; jeśli nie jest prawdziwy to zwróci \u201ejeśli fałsz\u201d.",
  "LANG_LISTS_LENGTH_INPUT_LENGTH": "długość listy",
  "LANG_VARIABLES_LOCAL_MUTATOR_ARG_TITLE_NAME": "nazwa",
  "TIME_MONTHS": "Months",
  "COLOUR_RGB_RED": "czerwony",
  "LANG_LISTS_IS_IN_TITLE_IS_IN": "jest na liście?",
  "VARIABLES_GET_TOOLTIP": "Zwraca wartość tej zmiennej.",
  "LANG_LISTS_REVERSE_TITLE_REVERSE": "odwróć listę",
  "LANG_LISTS_CREATE_WITH_CONTAINER_TITLE_ADD": "lista",
  "REPL_UNABLE_TO_UPDATE": "Unable to send update to device/emulator",
  "HORIZONTAL_PARAMETERS": "Rozmieść parametry w poziomie",
  "LANG_MATH_CONVERT_NUMBER_OP_HEX_TO_DEC": "hex na dodatnią całkowitą",
  "LISTS_CREATE_WITH_TOOLTIP": "Utwórz listę z dowolną ilością elementów.",
  "LANG_LISTS_INSERT_INPUT_INDEX": "indeks",
  "LANG_TEXT_CONTAINS_INPUT_TEXT": "tekst",
  "LOGIC_NULL": "nic",
  "TEXT_INDEXOF_OPERATOR_FIRST": "znajdź pierwsze wystąpienie tekstu",
  "LANG_PROCEDURES_DEFNORETURN_TOOLTIP": "Funkcja, która nie zwraca wartości.",
  "LANG_TEXT_TEXT_IS_STRING_TITLE": "czy tekst?",
  "LANG_COMPONENT_BLOCK_SETTER_TITLE_SET": "ustaw",
  "MATH_ONLIST_OPERATOR_AVERAGE": "średnia elementów listy",
  "LANG_CONTROLS_FORRANGE_INPUT_START": "od",
  "REPL_EMULATOR_ONLY": "You can only use this option to update the Emulator",
  "DIALOG_ENTER_VALUES": "Enter values for:",
  "MATH_IS_ODD": "jest nieparzysta",
  "LANG_MATH_NUMBER_TOOLTIP": "Używa wprowadzonej liczby.",
  "LISTS_SET_INDEX_SET": "ustaw",
  "LANG_CONTROLS_WHILE_COLLAPSED_TEXT": "gdy",
  "LANG_TEXT_SPLIT_TOOLTIP_SPLIT_AT_FIRST": "Dzieli dany tekst na dwie części, wykorzystując położenie pierwszego wystąpienia tekstu 'w' jako punktu podziału i zwraca listę dwóch elementów, składającą się z części przed punktem podziału i części po punkcie podziału. Podział 'jabłko, banan, wiśnia, pies' z przecinkiem jako punkt podziału zwraca listę dwóch elementów: pierwszy to tekst 'jabłko', a drugi to tekst \u201ebanan, wiśnia, pies'. Zauważ, że przecinek po 'jabłko' nie pojawia się w wyniku, ponieważ jest to punkt podziału.",
  "LANG_PROCEDURES_MUTATORCONTAINER_TOOLTIP": "",
  "REPL_UPDATE_INFO": "The update is now being installed on your device. Watch your device (or emulator) screen and approve the software installation when prompted.<br /><br />IMPORTANT: When the update finishes, choose 'DONE' (don't click 'open'). Then go to App Inventor in your web browser, click the 'Connect' menu and choose 'Reset Connection'.  Then reconnect the device.",
  "HIDE_WARNINGS": "Hide Warnings",
  "LISTS_GET_SUBLIST_START_FROM_END": "Pobierz listę podrzędną z # od końca",
  "LANG_COLOUR_GREEN": "zielony",
  "LANG_MATH_FORMAT_AS_DECIMAL_TOOLTIP": "Zwraca liczbę sformatowaną jako dziesiętną\nz określoną ilością miejsc po przecinku.",
  "LANG_CATEGORY_TEXT": "Tekst",
  "LANG_COLOUR_LIGHT_GRAY": "jasny szary",
  "REPL_COMPANION_OUT_OF_DATE2": "Your Companion App is out of date. Restart the Companion and use it to scan the QRCode below in order to update",
  "LISTS_CREATE_EMPTY_TITLE": "utwórz pustą listę",
  "LANG_TEXT_SEGMENT_INPUT_TEXT": "tekst",
  "MATH_ROUND_TOOLTIP": "Zaokrąglij w górę lub w dół.",
  "COLOUR_RGB_TOOLTIP": "Połącz czerwony, zielony i niebieski w odpowiednich proporcjach, tak aby powstał nowy kolor. Zawartość każdego z nich określa liczba z przedziału od 0 do 100.",
  "CONTROLS_IF_MSG_IF": "jeśli",
  "DIALOG_SECURE_ESTABLISHED": "30 Secure Connection Established",
  "LISTS_GET_INDEX_FROM_START": "#",
  "REPL_COMPANION_OUT_OF_DATE1": "The Companion you are using is out of date.<br/><br/>This Version of App Inventor should be used with Companion version",
  "LANG_TEXT_SPLIT_OPERATOR_SPLIT_AT_FIRST": "podziel na pierwszym",
  "LANG_CONTROLS_CHOOSE_INPUT_THEN_RETURN": "wtedy",
  "TEXT_CREATE_JOIN_TITLE_JOIN": "połącz",
  "LANG_MATH_TRIG_TOOLTIP_ASIN": "Podaje kąt w zakresie (-90,+90]\nstopni z daną wartością sinus.",
  "PROCEDURES_DEFNORETURN_DO": "",
  "LANG_PROCEDURES_DEFRETURN_TOOLTIP": "Funkcja zwracająca wartość wyniku.",
  "LANG_MATH_COMPARE_NEQ": "≠",
  "LANG_LOGIC_OPERATION_TOOLTIP_AND": "Zwraca Prawda, jeśli wszystkie dane wejściowe są prawdziwe.",
  "REPL_NOW_DOWNLOADING": "We are now downloading update from the App Inventor Server, please standby",
  "LOGIC_BOOLEAN_TRUE": "prawda",
  "LANG_MATH_SINGLE_OP_NEG": "neg",
  "LANG_MATH_SINGLE_OP_ABSOLUTE": "absolutny",
  "LANG_MATH_RANDOM_INT_TITLE_RANDOM": "losowa liczba całkowita",
  "DO_IT": "Do It",
  "LANG_PROCEDURES_DOTHENRETURN_DO": "wykonaj",
  "TEXT_TEXT_HELPURL": "https://pl.wikipedia.org/wiki/Tekstowy_typ_danych",
  "LANG_VARIABLES_LOCAL_DECLARATION_TRANSLATED_NAME": "inicjuj lokalnie w do",
  "LOGIC_COMPARE_TOOLTIP_GTE": "Zwróć \"prawda\", jeśli pierwsze wejście jest większe lub równe drugiemu.",
  "LANG_LISTS_IS_IN_INPUT_THING": "obiekt",
  "ERROR_BREAK_ONLY_IN_LOOP": "Blok przerwania powinien być używany tylko w pętlach",
  "LANG_TEXT_CHANGECASE_TOOLTIP_DOWNCASE": "Zwraca kopię argumentu ciągu tekstowego przekonwertowanego na małe litery.",
  "LANG_CONTROLS_BREAK_INPUT_TEXT": "wartość",
  "TEXT_APPEND_HELPURL": "https://github.com/google/blockly/wiki/Text#text-modification",
  "LANG_CONTROLS_FOREACH_INPUT_VAR": "pozycji",
  "COLOUR_RGB_BLUE": "niebieski",
  "LANG_TEXT_SPLIT_OPERATOR_SPLIT_AT_FIRST_OF_ANY": "podziel na pierwszym z jakiegokolwiek",
  "LANG_VARIABLES_GLOBAL_DECLARATION_TITLE_INIT": "inicjuj globalną",
  "MATH_ONLIST_OPERATOR_STD_DEV": "odchylenie standardowe listy",
  "LANG_CONTROLS_IF_MSG_THEN": "wtedy",
  "REPL_STARTING_COMPANION_IN_EMULATOR": "Starting the Companion App in the emulator.",
  "LANG_CONTROLS_DO_THEN_RETURN_COLLAPSED_TEXT": "wykonaj/wynik",
  "COLOUR_BLEND_HELPURL": "http://meyerweb.com/eric/tools/color-blend/",
  "LANG_VARIABLES_LOCAL_DECLARATION_COLLAPSED_TEXT": "lokalna",
  "REPL_UNABLE_TO_LOAD_NO_RESPOND": "Unable to load update from App Inventor server (server not responding)",
  "TEXT_GET_SUBSTRING_START_FROM_END": "pobierz podciąg od # litery od końca",
  "LISTS_CREATE_WITH_CONTAINER_TITLE_ADD": "lista",
  "MATH_IS_NEGATIVE": "jest ujemna",
  "LANG_CONTROLS_GET_START_VALUE_INPUT_STARTVALUE": "wartośćPoczątkowa",
  "LANG_MATH_SINGLE_TOOLTIP_LN": "Zwraca logarytm naturalny liczby, tj. Logarytm do podstawy e (2,71828 ...)",
  "TEXT_CHANGECASE_OPERATOR_LOWERCASE": "zmień na małe litery",
  "LANG_CATEGORY_LISTS": "Listy",
  "COLOUR_PICKER_HELPURL": "https://en.wikipedia.org/wiki/Color",
  "REPL_NO_ERROR_FIVE_SECONDS": "<br/><i>Note:<\/i>&nbsp;You will not see another error reported for 5 seconds.",
  "LANG_LISTS_REPLACE_ITEM_INPUT_REPLACEMENT": "zastąpienie",
  "LANG_PROCEDURES_DEFRETURN_DEFINE": "do",
  "TEXT_PRINT_TOOLTIP": "Drukuj określony tekst, liczbę lub inną wartość.",
  "LANG_TEXT_REPLACE_ALL_TITLE_REPLACE_ALL": "Zamień wszystko",
  "REPL_PLUGGED_IN_Q": "Plugged In?",
  "LANG_LISTS_ADD_ITEMS_CONTAINER_TOOLTIP": "Dodaj, usuń lub zmień kolejność sekcji, aby zmienić konfigurację, tej listy bloku.",
  "REPL_EMULATORS": "emulator's",
  "LANG_VARIABLES_LOCAL_MUTATOR_ARG_DEFAULT_VARIABLE": "x",
  "LANG_LISTS_PICK_RANDOM_ITEM_INPUT_LIST": "lista",
  "LANG_TEXT_JOIN_ITEM_TITLE_ITEM": "tekst",
  "LOGIC_OPERATION_OR": "lub",
  "REPL_SOFTWARE_UPDATE": "Software Update",
  "LANG_MATH_TRIG_ATAN": "atan",
  "REPL_UPDATE_NO_UPDATE": "No Update is Available",
  "LANG_MATH_IS_A_BINARY_INPUT_NUM": "czy binarna?",
  "TEXT_GET_SUBSTRING_TAIL": "",
  "LANG_COLOUR_RED": "czerwony",
  "LOGIC_OPERATION_TOOLTIP_AND": "Zwróć \"prawda\" jeśli oba dane elementy mają wartość \"prawda\".",
  "LANG_CONTROLS_GET_START_VALUE_INPUT_SCREENNAME": "nazwaEkranu",
  "LANG_MATH_ARITHMETIC_ADD": "+",
  "CONTROLS_REPEAT_TITLE": "powtórz %1 razy",
  "MATH_ROUND_OPERATOR_ROUND": "zaokrąglij",
  "LANG_MATH_CONVERT_NUMBER_OP_DEC_TO_BIN": "dodatnia całkowita na binarną",
  "LISTS_GET_INDEX_LAST": "ostatni",
  "MATH_MODULO_TITLE": "reszta z dzielenia %1 przez %2",
  "LANG_MATH_FORMAT_AS_DECIMAL_INPUT_PLACES": "miejsca",
  "LANG_MATH_RANDOM_FLOAT_TITLE_RANDOM": "losowy ułamek",
  "REPL_ERROR_FROM_COMPANION": "Error from Companion",
  "DISABLE_SNAPPING": "Wyłącz przyciąganie do siatki",
  "LANG_LISTS_LOOKUP_IN_PAIRS_TOOLTIP": "Zwraca wartość powiązaną z kluczem na liście par",
  "ERROR_COMPONENT_DOES_NOT_EXIST": "Komponent nie istnieje",
  "MATH_TRIG_ASIN": "arcsin",
  "LANG_MATH_COMPARE_TOOLTIP_LTE": "Zwraca Prawda, jeśli pierwsza liczba jest mniejsza lub równa drugiej liczbie.",
  "LANG_MATH_SINGLE_OP_EXP": "e^",
  "LISTS_GET_INDEX_TOOLTIP_GET_REMOVE_FROM": "Usuwa i zwraca element z określonej pozycji na liście.",
  "ADD_COMMENT": "Dodaj komentarz",
  "LANG_CONTROLS_GET_PLAIN_START_TEXT_TITLE": "uzyskaj zwykły tekst początkowy",
  "LANG_CONTROLS_GET_PLAIN_START_TEXT_COLLAPSED_TEXT": "uzyskaj zwykły tekst początkowy",
  "MATH_SINGLE_TOOLTIP_LN": "Zwróć logarytm naturalny danej liczby.",
  "LANG_CONTROLS_OPEN_ANOTHER_SCREEN_WITH_START_VALUE_TOOLTIP": "Otwiera nowy ekran w aplikacji z wieloma ekranami i przekazuje wartość początkową do tego ekranu.",
  "LISTS_SORT_HELPURL": "https://github.com/google/blockly/wiki/Lists#sorting-a-list",
  "PROCEDURES_CALLRETURN_HELPURL": "https://pl.wikipedia.org/wiki/Podprogram",
  "DIALOG_UNBOUND_VAR": "Unbound Variables",
  "LANG_LISTS_LOOKUP_IN_PAIRS_INPUT": "przegląda pary  klucz %1 pary %2 nieZnaleziono %3",
  "LANG_LISTS_CREATE_WITH_TOOLTIP": "Utwórz listę z dowolną liczbą elementów.",
  "DELETE_ALL_BLOCKS": "Usunąć wszystkie %1 bloki?",
  "REPL_DISMISS": "Dismiss",
  "PROCEDURES_MUTATORARG_TOOLTIP": "Dodaj dane wejściowe do funkcji.",
  "HELP": "Pomoc",
  "TEXT_JOIN_TITLE_CREATEWITH": "utwórz tekst z",
  "TEXT_ISEMPTY_HELPURL": "https://github.com/google/blockly/wiki/Text#checking-for-empty-text",
  "LANG_LISTS_SELECT_ITEM_TOOLTIP": "Zwraca element o danym indeksie na liście.",
  "LANG_TEXT_STARTS_AT_INPUT": "zaczyna się   tekst %1 fragment %2",
  "LANG_LISTS_POSITION_IN_INPUT_THING": "obiekt",
  "CONTROLS_REPEAT_INPUT_DO": "wykonaj",
  "LANG_LISTS_PICK_RANDOM_TOOLTIP": "Wybierz losowy element z listy.",
  "LANG_CONTROLS_CHOOSE_TOOLTIP": "Jeśli sprawdzany warunek jest prawdą,zwraca wynik uruchomionego wyrażenia dołączonego do bloku 'wtedy-zwróć';inaczej zwraca wynik uruchomionego wyrażenia dołączonego do bloku 'inaczej-zwróć';w większości jedno ze zwracanych bloków wyrażeń będzie uruchomionych.",
  "LANG_LISTS_REVERSE_TOOLTIP": "Odwraca kolejność listy wprowadzania i zwraca ją jako nową listę.",
  "PROCEDURES_CALL_BEFORE_PARAMS": "z:",
  "LANG_CONTROLS_IF_MSG_IF": "Jeśli",
  "LANG_CONTROLS_FORRANGE_INPUT_COLLAPSED_TEXT": "dla numeru w zasięgu",
  "PROCEDURES_DEF_DUPLICATE_WARNING": "Uwaga: Ta funkcja ma powtórzone parametry.",
  "EXPAND_ALL": "Rozwiń bloki",
  "LISTS_SET_INDEX_TOOLTIP_SET_FROM": "Ustawia element w określonym miejscu na liście.",
  "LANG_TEXT_SEGMENT_INPUT_START": "start",
  "LISTS_CREATE_WITH_ITEM_TOOLTIP": "Dodaj element do listy.",
  "LANG_COLOUR_YELLOW": "żółty",
  "LANG_COLOUR_MAKE_COLOUR_TOOLTIP": "Kolor z podanymi komponentami czerwony, zielony, niebieski i opcjonalnie alfa",
  "LISTS_CREATE_WITH_CONTAINER_TOOLTIP": "Dodaj, usuń lub zmień kolejność sekcji żeby skonfigurować ten blok listy.",
  "LANG_LISTS_APPEND_LIST_TITLE_APPEND": "dołącz do listy",
  "MATH_TRIG_SIN": "sin",
  "MATH_ONLIST_OPERATOR_SUM": "suma elementów listy",
  "RENAME_VARIABLE_TITLE": "Zmień nazwę wszystkich zmiennych \u201e%1\u201d na:",
  "LISTS_INDEX_OF_FIRST": "znaleźć pierwsze wystąpienie elementu",
  "COLOUR_RGB_GREEN": "zielony",
  "LANG_CONTROLS_FLOW_STATEMENTS_TOOLTIP_BREAK": "Wyjdź z pętli zawierającej.",
  "TIME_MINUTES": "Minutes",
  "LANG_LISTS_REPLACE_ITEM_TITLE_REPLACE": "zamień element listy",
  "LANG_MATH_CONVERT_NUMBER_TITLE_CONVERT": "przekształć liczbę",
  "LANG_TEXT_REPLACE_ALL_INPUT_REPLACEMENT": "zastąpienie",
  "LANG_LISTS_ADD_ITEM_TOOLTIP": "Dodaj element do listy.",
  "LISTS_ISEMPTY_TITLE": "%1 jest pusty",
  "LANG_LISTS_APPEND_LIST_INPUT": "dołącz do listy  lista1 %1 lista2 %2",
  "LANG_LISTS_INSERT_INPUT": "wstawia element listy   lista %1 indeks %2 pozycja %3",
  "MATH_ARITHMETIC_TOOLTIP_ADD": "Zwróć sumę dwóch liczb.",
  "TEXT_TRIM_OPERATOR_LEFT": "usuń spacje z lewej strony",
  "DELETE_VARIABLE": "Delete the '%1' variable",
  "LANG_CONTROLS_CLOSE_SCREEN_WITH_VALUE_INPUT_RESULT": "wynik",
  "LANG_TEXT_CONTAINS_TOOLTIP": "Sprawdza, czy fragment jest zawarty w tekście.",
  "LANG_TEXT_LENGTH_TOOLTIP": "Zwraca liczbę znaków (włączając spacje)\nw podanym tekście.",
  "MATH_ONLIST_OPERATOR_MIN": "minimalna wartość z listy",
  "LANG_CONTROLS_FORRANGE_INPUT_END": "do",
  "GENERICIZE_BLOCK": "Stwórz rodzajowy",
  "DELETE_X_BLOCKS": "Usuń %1 bloków",
  "TEXT_CHARAT_FIRST": "pobierz pierwszą literę",
  "MATH_SUBTRACTION_SYMBOL": "-",
  "LANG_TEXT_TEXT_IS_STRING_INPUT_THING": "obiekt",
  "LANG_LISTS_TITLE_IS_EMPTY": "czy lista pusta?",
  "LANG_LISTS_ADD_ITEMS_CONTAINER_TITLE_ADD": "lista",
  "LANG_MATH_DIVIDE_OPERATOR_QUOTIENT": "iloraz z",
  "LANG_LISTS_POSITION_IN_INPUT_LIST": "lista",
  "MATH_TRIG_TOOLTIP_TAN": "Zwróć tangens o stopniu (nie w radianach).",
  "LANG_LOGIC_BOOLEAN_TOOLTIP_TRUE": "Zwraca wartość logiczną Prawda.",
  "MATH_IS_TOOLTIP": "Sprawdź, czy liczba jest parzysta, nieparzysta, pierwsza, całkowita, dodatnia, ujemna, lub czy jest podzielna przez podaną liczbę. Zwraca wartość \"prawda\" lub \"fałsz\".",
  "LANG_TEXT_TRIM_TITLE_TRIM": "trim",
  "CONTROLS_WHILEUNTIL_HELPURL": "https://github.com/google/blockly/wiki/Loops#repeat",
  "MATH_POWER_SYMBOL": "^",
  "LANG_MATH_CONVERT_ANGLES_TOOLTIP_RAD_TO_DEG": "Zwraca wartość w stopniach w zakresie\n[0, 360) w odniesieniu do podanego w radianach argumentu.",
  "MATH_IS_EVEN": "jest parzysta",
  "LANG_CONTROLS_CLOSE_SCREEN_WITH_VALUE_TITLE": "zamknij ekran z wartością",
  "LISTS_INDEX_OF_TOOLTIP": "Zwraca indeks pierwszego/ostatniego wystąpienia elementu na liście. Zwraca wartość %1, jeśli tekst nie zostanie znaleziony.",
  "LANG_TEXT_SEGMENT_INPUT": "człon  tekst %1 start %2 długość %3",
  "DISABLE_ALL_BLOCKS": "Wyłącz wszystkie bloki",
  "LANG_LISTS_IS_LIST_TOOLTIP": "Sprawdza, czy dane są listą.",
  "TEXT_INDEXOF_TAIL": "",
  "REPL_NETWORK_ERROR_RESTART": "Network Error Communicating with Companion.<br />Try restarting the Companion and reconnecting",
  "LISTS_SET_INDEX_TOOLTIP_INSERT_LAST": "Dodaj element na koniec listy.",
  "LANG_CONTROLS_FOR_TOOLTIP": "Policz od numeru początkowego do numeru końcowego. Dla każdego licznika ustaw bieżący numer licznika na zmienną \u201e%1\u201d, a następnie wykonaj kilka instrukcji.",
  "MATH_MULTIPLICATION_SYMBOL": "×",
  "LANG_LISTS_REPLACE_ITEM_INPUT": "zastąp element listy  lista %1 indeks %2 zastąpienie %3",
  "LISTS_SPLIT_TEXT_FROM_LIST": "stwórz tekst z listy",
  "LANG_VARIABLES_LOCAL_DECLARATION_TOOLTIP": "Pozwala tworzyć zmienne, które są dostępne tylko w części do tego bloku.",
  "LOGIC_TERNARY_IF_TRUE": "jeśli prawda"
}