{
    "@metadata.author": "Ellen Spertus <ellen.spertus@gmail.com>",
    "@metadata.lastupdated": "2019-12-17 17:00:00.862075",
    "@metadata.locale": "ko",
    "@metadata.messagedocumentation": "qqq",
    "Blockly.Msg.UNDO": "실행 취소",
    "Blockly.Msg.REDO": "다시 실행",
    "Blockly.Msg.CLEAN_UP": "모든 블록 정리하기",
    "Blockly.Msg.HIDE": "작업공간 제어 도구 숨기기",
    "Blockly.Msg.SHOW": "작업공간 제어 도구 나타내기",
    "Blockly.Msg.DUPLICATE_BLOCK": "복제하기",
    "Blockly.Msg.REMOVE_COMMENT": "주석 지우기",
    "Blockly.Msg.ADD_COMMENT": "주석 넣기",
    "Blockly.Msg.EXTERNAL_INPUTS": "외부 입력",
    "Blockly.Msg.INLINE_INPUTS": "내부 입력",
    "Blockly.Msg.HORIZONTAL_PARAMETERS": "매개변수 가로로 보기",
    "Blockly.Msg.VERTICAL_PARAMETERS": "매개변수 세로로 보기",
    "Blockly.Msg.CONFIRM_DELETE": "삭제 확인",
    "Blockly.Msg.DELETE_ALL_BLOCKS": "'%1개의 블록을 모두 삭제할까요?'",
    "Blockly.Msg.DELETE_BLOCK": "블록 삭제하기",
    "Blockly.Msg.DELETE_X_BLOCKS": "블록 %1개 삭제하기",
    "Blockly.Msg.COLLAPSE_BLOCK": "블록 접기",
    "Blockly.Msg.EXPAND_BLOCK": "블록 펼치기",
    "Blockly.Msg.DISABLE_BLOCK": "블록 비활성화하기",
    "Blockly.Msg.ENABLE_BLOCK": "블록 활성화하기",
    "Blockly.Msg.HELP": "도움말",
    "Blockly.Msg.EXPORT_IMAGE": "모든 블록 이미지 파일로 저장하기",
    "Blockly.Msg.COLLAPSE_ALL": "모든 블록 접기",
    "Blockly.Msg.EXPAND_ALL": "모든 블록 펼치기",
    "Blockly.Msg.ARRANGE_H": "모든 블록 가로로 정리하기",
    "Blockly.Msg.ARRANGE_V": "모든 블록 세로로 정리하기",
    "Blockly.Msg.ARRANGE_S": "모든 블록 대각선으로 정리하기",
    "Blockly.Msg.SORT_W": "모든 블록 너비 순으로 정렬하기",
    "Blockly.Msg.SORT_H": "모든 블록 높이 순으로 정렬하기",
    "Blockly.Msg.SORT_C": "모든 블록 카테고리별로 정렬하기",
    "Blockly.Msg.COPY_TO_BACKPACK": "배낭에 넣기",
    "Blockly.Msg.COPY_ALLBLOCKS": "모든 블록 배낭에 넣기",
    "Blockly.Msg.REMOVE_FROM_BACKPACK": "배낭에서 삭제",
    "Blockly.Msg.BACKPACK_GET": "배낭에서 모든 블록 가져오기",
    "Blockly.Msg.BACKPACK_EMPTY": "배낭 비우기",
    "Blockly.Msg.BACKPACK_CONFIRM_EMPTY": "배낭에 있는 블록을 모두 삭제할까요?",
    "Blockly.Msg.BACKPACK_DOC_TITLE": "배낭 정보",
    "Blockly.Msg.SHOW_BACKPACK_DOCUMENTATION": "배낭 설명서 표시",
    "Blockly.Msg.BACKPACK_DOCUMENTATION": "배낭은 복사/붙여넣기 기능입니다. 하나의 프로젝트 또는 스크린에서 블록을 복사하여 다른 프로젝트 또는 스크린에 붙여넣을 수 있습니다. 복사하려면 블록을 배낭으로 끌어다 놓을 수 있습니다. 붙여넣으려면 배낭 아이콘을 클릭하고 블록을 작업 영역으로 끌어다 놓으세요.</p> <p>배낭에 남아있으면 앱인벤터를 종료해도 다음에 로그인할 때도 이 블록이 그대로 있습니다. </p> <p> <a href='/reference/other/backpack.html' target='_blank'> 여기를 클릭</a>하여 자세한 문서와 '튜토리얼' 비디오를 확인하세요.",
    "Blockly.Msg.ENABLE_GRID": "작업공간 격자 활성화",
    "Blockly.Msg.DISABLE_GRID": "작업공간 격자 비활성화",
    "Blockly.Msg.ENABLE_SNAPPING": "격자에 맞추기 활성화",
    "Blockly.Msg.DISABLE_SNAPPING": "격자에 맞추기 비활성화",
    "Blockly.Msg.DISABLE_ALL_BLOCKS": "모든 블록 비활성화",
    "Blockly.Msg.ENABLE_ALL_BLOCKS": "모든 블록 활성화",
    "Blockly.Msg.HIDE_ALL_COMMENTS": "모든 주석 숨기기",
    "Blockly.Msg.SHOW_ALL_COMMENTS": "모든 주석 보이기",
    "Blockly.Msg.GENERICIZE_BLOCK": "공통 블록 만들기",
    "Blockly.Msg.UNGENERICIZE_BLOCK": "일반 블록 만들기",
    "Blockly.Msg.CHANGE_VALUE_TITLE": "값 바꾸기:",
    "Blockly.Msg.NEW_VARIABLE": "새 변수...",
    "Blockly.Msg.NEW_VARIABLE_TITLE": "새 변수 이름:",
    "Blockly.Msg.RENAME_VARIABLE": "변수 이름 바꾸기...",
    "Blockly.Msg.RENAME_VARIABLE_TITLE": "모든 변수 '%1'의 이름을 다음으로 변경하세요:",
    "Blockly.Msg.VARIABLE_CATEGORY": "변수",
    "Blockly.Msg.PROCEDURE_CATEGORY": "함수",
    "Blockly.Msg.ERROR_BLOCK_CANNOT_BE_IN_DEFINTION": "이 블록은 정의될 수 없습니다",
    "Blockly.Msg.ERROR_SELECT_VALID_ITEM_FROM_DROPDOWN": "드롭 다운에서 유효한 항목을 선택하세요.",
    "Blockly.Msg.ERROR_DUPLICATE_EVENT_HANDLER": "이 컴포넌트의 같은 이벤트 핸들러 블록이 여러 개 있습니다.",
    "Blockly.Msg.ERROR_COMPONENT_DOES_NOT_EXIST": "컴포넌트가 없습니다",
    "Blockly.Msg.ERROR_BLOCK_IS_NOT_DEFINED": "이 블록은 정의되지 않았습니다. 이 블록을 삭제하세요!",
    "Blockly.Msg.ERROR_BREAK_ONLY_IN_LOOP": "'멈추기' 블록은 반복문 안에서만 사용할 수 있습니다",
    "Blockly.Msg.LANG_COLOUR_PICKER_TOOLTIP": "사각형을 클릭해서 색깔을 선택하세요.",
    "Blockly.Msg.LANG_COLOUR_BLACK": "검정",
    "Blockly.Msg.LANG_COLOUR_WHITE": "흰색",
    "Blockly.Msg.LANG_COLOUR_RED": "빨강",
    "Blockly.Msg.LANG_COLOUR_PINK": "분홍",
    "Blockly.Msg.LANG_COLOUR_ORANGE": "주황",
    "Blockly.Msg.LANG_COLOUR_YELLOW": "노랑",
    "Blockly.Msg.LANG_COLOUR_GREEN": "초록",
    "Blockly.Msg.LANG_COLOUR_CYAN": "청록",
    "Blockly.Msg.LANG_COLOUR_BLUE": "파랑",
    "Blockly.Msg.LANG_COLOUR_MAGENTA": "자홍색",
    "Blockly.Msg.LANG_COLOUR_LIGHT_GRAY": "밝은 회색",
    "Blockly.Msg.LANG_COLOUR_DARK_GRAY": "짙은 회색",
    "Blockly.Msg.LANG_COLOUR_GRAY": "회색",
    "Blockly.Msg.LANG_COLOUR_SPLIT_COLOUR": "색깔 나누기",
    "Blockly.Msg.LANG_COLOUR_SPLIT_COLOUR_TOOLTIP": "빨강, 초록, 파랑 그리고 투명도 값을 리스트로 돌려줍니다. 각각 0부터 255의 범위를 갖고 있습니다.",
    "Blockly.Msg.LANG_COLOUR_MAKE_COLOUR": "색깔 만들기",
    "Blockly.Msg.LANG_COLOUR_MAKE_COLOUR_TOOLTIP": "빨강, 초록, 파랑 그리고 투명도 값으로 색깔을 만듭니다.",
    "Blockly.Msg.LANG_CATEGORY_CONTROLS": "제어",
    "Blockly.Msg.LANG_CONTROLS_IF_MSG_IF": "만약",
    "Blockly.Msg.LANG_CONTROLS_IF_MSG_ELSEIF": "아니면 만약",
    "Blockly.Msg.LANG_CONTROLS_IF_MSG_ELSE": "아니면",
    "Blockly.Msg.LANG_CONTROLS_IF_MSG_THEN": "(이)라면",
    "Blockly.Msg.LANG_CONTROLS_IF_IF_TITLE_IF": "만약",
    "Blockly.Msg.LANG_CONTROLS_IF_IF_TOOLTIP": "조건을 추가 또는 삭제하거나 순서를 바꾸어 만약 블럭을 재설정합니다.",
    "Blockly.Msg.LANG_CONTROLS_IF_ELSEIF_TITLE_ELSEIF": "아니면 만약",
    "Blockly.Msg.LANG_CONTROLS_IF_ELSEIF_TOOLTIP": "만약 블록에 조건을 추가합니다.",
    "Blockly.Msg.LANG_CONTROLS_IF_ELSE_TITLE_ELSE": "아니면",
    "Blockly.Msg.LANG_CONTROLS_IF_ELSE_TOOLTIP": "만약 블록의 모든 조건을 검사한 후 실행될 마지막 조건을 추가합니다.",
    "Blockly.Msg.LANG_CONTROLS_WHILEUNTIL_TITLE_REPEAT": "반복",
    "Blockly.Msg.LANG_CONTROLS_WHILEUNTIL_INPUT_DO": "실행",
    "Blockly.Msg.LANG_CONTROLS_WHILEUNTIL_OPERATOR_WHILE": "반복",
    "Blockly.Msg.LANG_CONTROLS_WHILEUNTIL_OPERATOR_UNTIL": "할 때까지",
    "Blockly.Msg.LANG_CONTROLS_WHILEUNTIL_TOOLTIP_WHILE": "주어진 값이 참이면, 계속하여 명령문을 실행합니다.",
    "Blockly.Msg.LANG_CONTROLS_WHILEUNTIL_TOOLTIP_UNTIL": "주어진 값이 거짓이면, 계속하여 명령문을 실행합니다.",
    "Blockly.Msg.LANG_CONTROLS_FOR_INPUT_WITH": "숫자 세기",
    "Blockly.Msg.LANG_CONTROLS_FOR_INPUT_VAR": "x",
    "Blockly.Msg.LANG_CONTROLS_FOR_INPUT_FROM": "부터",
    "Blockly.Msg.LANG_CONTROLS_FOR_INPUT_TO": "까지",
    "Blockly.Msg.LANG_CONTROLS_FOR_INPUT_DO": "실행",
    "Blockly.Msg.LANG_CONTROLS_FOR_TOOLTIP": "시작 숫자부터 마지막 숫자까지 숫자를 셉니다.\n 각 숫자마다, 현재 숫자를 변수 '%1'에 지정하고\n 해당 명령문을 실행합니다.",
    "Blockly.Msg.LANG_CONTROLS_FORRANGE_INPUT_ITEM": "반복",
    "Blockly.Msg.LANG_CONTROLS_FORRANGE_INPUT_VAR": "숫자",
    "Blockly.Msg.LANG_CONTROLS_FORRANGE_INPUT_START": "부터",
    "Blockly.Msg.LANG_CONTROLS_FORRANGE_INPUT_END": "까지",
    "Blockly.Msg.LANG_CONTROLS_FORRANGE_INPUT_STEP": "씩",
    "Blockly.Msg.LANG_CONTROLS_FORRANGE_INPUT_DO": "실행",
    "Blockly.Msg.LANG_CONTROLS_FORRANGE_INPUT_COLLAPSED_TEXT": "범위 내의 숫자마다",
    "Blockly.Msg.LANG_CONTROLS_FORRANGE_INPUT_COLLAPSED_PREFIX": "각 ",
    "Blockly.Msg.LANG_CONTROLS_FORRANGE_INPUT_COLLAPSED_SUFFIX": " 범위 내의",
    "Blockly.Msg.LANG_CONTROLS_FORRANGE_TOOLTIP": "\"실행\" 영역에서 시작부터 끝까지 각 숫자 값에 대해 블록을 실행하고 매번 값을 증가시킵니다. 주어진 변수 이름을 사용하여 현재 숫자를 가져올 수 있습니다.",
    "Blockly.Msg.LANG_CONTROLS_FOREACH_INPUT_ITEM": "반복",
    "Blockly.Msg.LANG_CONTROLS_FOREACH_INPUT_VAR": "항목",
    "Blockly.Msg.LANG_CONTROLS_FOREACH_INPUT_INLIST": "리스트",
    "Blockly.Msg.LANG_CONTROLS_FOREACH_INPUT_DO": "실행",
    "Blockly.Msg.LANG_CONTROLS_FOREACH_INPUT_COLLAPSED_TEXT": "리스트의 항목으로 반복",
    "Blockly.Msg.LANG_CONTROLS_FOREACH_INPUT_COLLAPSED_PREFIX": "각 ",
    "Blockly.Msg.LANG_CONTROLS_FOREACH_INPUT_COLLAPSED_SUFFIX": " 리스트",
    "Blockly.Msg.LANG_CONTROLS_FOREACH_TOOLTIP": "리스트의 각 항목의 개수만큼 첫 번째 항목부터 참조하며 반복합니다. 주어진 \"항목\" 변수로 현재 참조 중인 값을 가져올 수 있습니다.",
    "Blockly.Msg.LANG_CONTROLS_FLOW_STATEMENTS_INPUT_OFLOOP": "반복의",
    "Blockly.Msg.LANG_CONTROLS_FLOW_STATEMENTS_OPERATOR_BREAK": "벗어나기",
    "Blockly.Msg.LANG_CONTROLS_FLOW_STATEMENTS_OPERATOR_CONTINUE": "이번 반복 건너뛰기",
    "Blockly.Msg.LANG_CONTROLS_FLOW_STATEMENTS_TOOLTIP_BREAK": "현재 반복문을 멈추고 벗어납니다.",
    "Blockly.Msg.LANG_CONTROLS_FLOW_STATEMENTS_TOOLTIP_CONTINUE": "이번에 실행될 블록들은 무시하고 다음 반복으로 넘어갑니다.",
    "Blockly.Msg.LANG_CONTROLS_FLOW_STATEMENTS_WARNING": "경고: 이 블럭은 반복문 안에서만 사용할 수 있습니다.",
    "Blockly.Msg.LANG_CONTROLS_WHILE_TITLE": "반복",
    "Blockly.Msg.LANG_CONTROLS_WHILE_INPUT_TEST": "조건",
    "Blockly.Msg.LANG_CONTROLS_WHILE_INPUT_DO": "실행",
    "Blockly.Msg.LANG_CONTROLS_WHILE_COLLAPSED_TEXT": "반복",
    "Blockly.Msg.LANG_CONTROLS_WHILE_TOOLTIP": "조건이 '참'인 동안 '실행'영역의 블록이 실행됩니다.",
    "Blockly.Msg.LANG_CONTROLS_CHOOSE_TITLE": "만약",
    "Blockly.Msg.LANG_CONTROLS_CHOOSE_INPUT_THEN_RETURN": "(이)라면",
    "Blockly.Msg.LANG_CONTROLS_CHOOSE_INPUT_ELSE_RETURN": "아니면",
    "Blockly.Msg.LANG_CONTROLS_CHOOSE_COLLAPSED_TEXT": "만약",
    "Blockly.Msg.LANG_CONTROLS_DO_THEN_RETURN_INPUT_DO": "실행",
    "Blockly.Msg.LANG_CONTROLS_DO_THEN_RETURN_INPUT_RETURN": "결과",
    "Blockly.Msg.LANG_CONTROLS_DO_THEN_RETURN_TOOLTIP": "'실행'영역의 블록을 실행합니다. 값을 변수에 돌려주기 전에 프로시저를 실행할 때 유용합니다.",
    "Blockly.Msg.LANG_CONTROLS_DO_THEN_RETURN_COLLAPSED_TEXT": "실행/결과",
    "Blockly.Msg.LANG_CONTROLS_DO_THEN_RETURN_TITLE": "결과 실행",
    "Blockly.Msg.LANG_CONTROLS_EVAL_BUT_IGNORE_TITLE": "결과 무시하고 실행",
    "Blockly.Msg.LANG_CONTROLS_EVAL_BUT_COLLAPSED_TEXT": "무시하고 실행",
    "Blockly.Msg.LANG_CONTROLS_EVAL_BUT_IGNORE_TOOLTIP": "연결된 코드 블록을 실행하고 반환 값을 무시합니다(반환 값이 있는 경우). 반환 값을 가진 형태의 함수를 호출해야 하지만 반환 값은 필요가 없는 경우 유용합니다.",
    "Blockly.Msg.LANG_CONTROLS_OPEN_ANOTHER_SCREEN_TITLE": "다른 스크린 열기",
    "Blockly.Msg.LANG_CONTROLS_OPEN_ANOTHER_SCREEN_INPUT_SCREENNAME": "스크린 이름",
    "Blockly.Msg.LANG_CONTROLS_OPEN_ANOTHER_SCREEN_COLLAPSED_TEXT": "스크린 열기",
    "Blockly.Msg.LANG_CONTROLS_OPEN_ANOTHER_SCREEN_TOOLTIP": "다중 스크린 앱에서 새 스크린을 엽니다. Screen1로 돌아갈 때 이 블록을 쓰지 말고, 대신 스크린 닫기 블록을 쓰세요.",
    "Blockly.Msg.LANG_CONTROLS_OPEN_ANOTHER_SCREEN_WITH_START_VALUE_TITLE": "시작 값을 전달하며 다른 스크린 열기",
    "Blockly.Msg.LANG_CONTROLS_OPEN_ANOTHER_SCREEN_WITH_START_VALUE_INPUT_SCREENNAME": "스크린 이름",
    "Blockly.Msg.LANG_CONTROLS_OPEN_ANOTHER_SCREEN_WITH_START_VALUE_INPUT_STARTVALUE": "시작 값",
    "Blockly.Msg.LANG_CONTROLS_OPEN_ANOTHER_SCREEN_WITH_START_VALUE_COLLAPSED_TEXT": "값 전달하며 스크린 열기",
    "Blockly.Msg.LANG_CONTROLS_OPEN_ANOTHER_SCREEN_WITH_START_VALUE_TOOLTIP": "다중 스크린 앱에서 새 스크린을 열면서 시작 값을 전달해요.",
    "Blockly.Msg.LANG_CONTROLS_GET_START_VALUE_TITLE": "시작 값 가져오기",
    "Blockly.Msg.LANG_CONTROLS_GET_START_VALUE_INPUT_SCREENNAME": "스크린 이름",
    "Blockly.Msg.LANG_CONTROLS_GET_START_VALUE_INPUT_STARTVALUE": "시작 값",
    "Blockly.Msg.LANG_CONTROLS_GET_START_VALUE_COLLAPSED_TEXT": "시작 값 가져오기",
    "Blockly.Msg.LANG_CONTROLS_GET_START_VALUE_TOOLTIP": "일반적으로 다중 스크린 앱의 다른 화면에서 이 화면을 열 때 이 화면에 전달된 값을 반환합니다. 값이 전달되지 않으면 빈 텍스트를 반환합니다.",
    "Blockly.Msg.LANG_CONTROLS_CLOSE_SCREEN_TITLE": "스크린 닫기",
    "Blockly.Msg.LANG_CONTROLS_CLOSE_SCREEN_COLLAPSED_TEXT": "스크린 닫기",
    "Blockly.Msg.LANG_CONTROLS_CLOSE_SCREEN_TOOLTIP": "현재 스크린 닫기",
    "Blockly.Msg.LANG_CONTROLS_CLOSE_SCREEN_WITH_VALUE_TITLE": "값을 반환하며 스크린 닫기",
    "Blockly.Msg.LANG_CONTROLS_CLOSE_SCREEN_WITH_VALUE_INPUT_RESULT": "결과",
    "Blockly.Msg.LANG_CONTROLS_CLOSE_SCREEN_WITH_VALUE_COLLAPSED_TEXT": "값을 전달하며 스크린 닫기",
    "Blockly.Msg.LANG_CONTROLS_CLOSE_SCREEN_WITH_VALUE_TOOLTIP": "현재의 스크린을 닫고 결괏값을 스크린에 반환합니다.",
    "Blockly.Msg.LANG_CONTROLS_CLOSE_APPLICATION_TITLE": "앱 종료하기",
    "Blockly.Msg.LANG_CONTROLS_CLOSE_APPLICATION_COLLAPSED_TEXT": "앱 종료하기",
    "Blockly.Msg.LANG_CONTROLS_CLOSE_APPLICATION_TOOLTIP": "이 앱의 모든 스크린을 닫고 앱을 종료시킵니다.",
    "Blockly.Msg.LANG_CONTROLS_GET_PLAIN_START_TEXT_TITLE": "시작 텍스트 가져오기",
    "Blockly.Msg.LANG_CONTROLS_GET_PLAIN_START_TEXT_COLLAPSED_TEXT": "시작 텍스트 가져오기",
    "Blockly.Msg.LANG_CONTROLS_GET_PLAIN_START_TEXT_TOOLTIP": "다른 앱에 의해 시작되었을 때, 이 화면에 전달 된 일반 텍스트를 반환합니다. 값이 전달되지 않으면 빈 텍스트를 반환합니다. 같은 앱에서 연 경우 이 블록 대신 시작 값 가져오기 블록을 사용하십시오.",
    "Blockly.Msg.LANG_CONTROLS_CLOSE_SCREEN_WITH_PLAIN_TEXT_TITLE": "텍스트를 전달하며 스크린 닫기",
    "Blockly.Msg.LANG_CONTROLS_CLOSE_SCREEN_WITH_PLAIN_TEXT_INPUT_TEXT": "텍스트",
    "Blockly.Msg.LANG_CONTROLS_CLOSE_SCREEN_WITH_PLAIN_TEXT_COLLAPSED_TEXT": "텍스트를 전달하며 스크린 닫기",
    "Blockly.Msg.LANG_CONTROLS_CLOSE_SCREEN_WITH_PLAIN_TEXT_TOOLTIP": "현재 스크린을 닫고 이 스크린을 연 액티비티로 값을 반환합니다. 이 값은 다른 앱에서 스크린을 연 경우 반환 값을 지정합니다. 같은 앱에서 열었고 닫을 때 반환할 텍스트는 이 블록이 아닌 \"값을 반환하며 스크린 닫기\" 블록을 쓰세요.",
    "Blockly.Msg.LANG_CONTROLS_BREAK_TITLE": "멈추기",
    "Blockly.Msg.LANG_CONTROLS_BREAK_INPUT_TEXT": "값",
    "Blockly.Msg.LANG_CONTROLS_BREAK_COLLAPSED_TEXT": "멈추기",
    "Blockly.Msg.LANG_CATEGORY_LOGIC": "논리",
    "Blockly.Msg.LANG_LOGIC_COMPARE_TOOLTIP_EQ": "두 값이 동일한지 아닌지 검사합니다.\n 비교되는 값들은 숫자 뿐 아니라 다른 유형의 값도 될 수 있습니다.\n 숫자는 보이는 형태의 문자열과 동일한 값으로 간주합니다.\n 예를 들어, 숫자 0은 텍스트 '0'과 동일합니다. 또한 두 문자열이 나타내는\n 숫자가 동일한 값이라면, 두 문자열은 서로 동일합니다. 예를 들어\n '1'은 '01'과 동일합니다.",
    "Blockly.Msg.LANG_LOGIC_COMPARE_TOOLTIP_NEQ": "만약 두 값이 서로 다르면 참을 반환합니다.",
    "Blockly.Msg.LANG_LOGIC_COMPARE_TRANSLATED_NAME": "동일한 식",
    "Blockly.Msg.LANG_LOGIC_COMPARE_EQ": "=",
    "Blockly.Msg.LANG_LOGIC_COMPARE_NEQ": "≠",
    "Blockly.Msg.LANG_LOGIC_OPERATION_AND": "그리고",
    "Blockly.Msg.LANG_LOGIC_OPERATION_OR": "또는",
    "Blockly.Msg.LANG_LOGIC_OPERATION_TOOLTIP_AND": "모든 조건이 참이면 참을 반환합니다.",
    "Blockly.Msg.LANG_LOGIC_OPERATION_TOOLTIP_OR": "조건 중 하나라도 참이면 참을 반환합니다.",
    "Blockly.Msg.LANG_LOGIC_NEGATE_INPUT_NOT": "아니다",
    "Blockly.Msg.LANG_LOGIC_NEGATE_TOOLTIP": "만약 조건이 거짓이면 참을 반환합니다. 만약 조건이 참이면 거짓을 반환합니다.",
    "Blockly.Msg.LANG_LOGIC_BOOLEAN_TRUE": "참",
    "Blockly.Msg.LANG_LOGIC_BOOLEAN_FALSE": "거짓",
    "Blockly.Msg.LANG_LOGIC_BOOLEAN_TOOLTIP_TRUE": "불리언값 참(true)을 반환합니다.",
    "Blockly.Msg.LANG_LOGIC_BOOLEAN_TOOLTIP_FALSE": "불리언값 거짓(거짓)을 반환합니다.",
    "Blockly.Msg.LANG_CATEGORY_MATH": "수학",
    "Blockly.Msg.LANG_MATH_NUMBER_TOOLTIP": "빈칸에 입력한 숫자를 값으로 사용합니다.",
    "Blockly.Msg.LANG_MATH_MUTATOR_ITEM_INPUT_NUMBER": "숫자",
    "Blockly.Msg.LANG_MATH_COMPARE_TOOLTIP_EQ": "만약 두 수가 서로 같으면 참을 반환합니다.",
    "Blockly.Msg.LANG_MATH_COMPARE_TOOLTIP_NEQ": "만약 두 수가 서로 다르면 참을 반환합니다.",
    "Blockly.Msg.LANG_MATH_COMPARE_TOOLTIP_LT": "만약 앞의 수가 뒤의 수보다 작으면 참을 반환합니다.",
    "Blockly.Msg.LANG_MATH_COMPARE_TOOLTIP_LTE": "만약 앞의 수가 뒤의 수보다 작거나 같으면 참을 반환합니다.",
    "Blockly.Msg.LANG_MATH_COMPARE_TOOLTIP_GT": "만약 앞의 수가 뒤의 수보다 크면 참을 반환합니다.",
    "Blockly.Msg.LANG_MATH_COMPARE_TOOLTIP_GTE": "만약 앞의 수가 뒤의 수보다 크거나 같으면 참을 반환합니다.",
    "Blockly.Msg.LANG_MATH_COMPARE_EQ": "=",
    "Blockly.Msg.LANG_MATH_COMPARE_NEQ": "≠",
    "Blockly.Msg.LANG_MATH_COMPARE_LT": "<",
    "Blockly.Msg.LANG_MATH_COMPARE_LTE": "≤",
    "Blockly.Msg.LANG_MATH_COMPARE_GT": ">",
    "Blockly.Msg.LANG_MATH_COMPARE_GTE": "≥",
    "Blockly.Msg.LANG_MATH_ARITHMETIC_TOOLTIP_ADD": "두 수를 더한 값을 반환합니다.",
    "Blockly.Msg.LANG_MATH_ARITHMETIC_TOOLTIP_MINUS": "두 수를 뺀 값을 반환합니다.",
    "Blockly.Msg.LANG_MATH_ARITHMETIC_TOOLTIP_MULTIPLY": "두 수를 곱한 값을 반환합니다.",
    "Blockly.Msg.LANG_MATH_ARITHMETIC_TOOLTIP_DIVIDE": "두 수를 나눈 값을 반환합니다.",
    "Blockly.Msg.LANG_MATH_ARITHMETIC_TOOLTIP_POWER": "앞의 수를 뒤의 수만큼 제곱한 값을 반환합니다.",
    "Blockly.Msg.LANG_MATH_BITWISE_TOOLTIP_AND": "두 숫자에 AND 비트 연산을 합니다.",
    "Blockly.Msg.LANG_MATH_BITWISE_TOOLTIP_IOR": "두 숫자에 OR 비트 연산을 합니다.",
    "Blockly.Msg.LANG_MATH_BITWISE_TOOLTIP_XOR": "두 숫자에 XOR 비트 연산을 합니다.",
    "Blockly.Msg.LANG_MATH_ARITHMETIC_ADD": "+",
    "Blockly.Msg.LANG_MATH_ARITHMETIC_MINUS": "-",
    "Blockly.Msg.LANG_MATH_ARITHMETIC_MULTIPLY": "*",
    "Blockly.Msg.LANG_MATH_ARITHMETIC_DIVIDE": "/",
    "Blockly.Msg.LANG_MATH_ARITHMETIC_POWER": "^",
    "Blockly.Msg.LANG_MATH_BITWISE_AND": "비트 연산 AND",
    "Blockly.Msg.LANG_MATH_BITWISE_IOR": "비트 연산 OR",
    "Blockly.Msg.LANG_MATH_BITWISE_XOR": "비트 연산 XOR",
    "Blockly.Msg.LANG_MATH_SINGLE_OP_ROOT": "제곱근",
    "Blockly.Msg.LANG_MATH_SINGLE_OP_ABSOLUTE": "절댓값",
    "Blockly.Msg.LANG_MATH_SINGLE_OP_NEG": "음수",
    "Blockly.Msg.LANG_MATH_SINGLE_OP_LN": "로그",
    "Blockly.Msg.LANG_MATH_SINGLE_OP_EXP": "e^",
    "Blockly.Msg.LANG_MATH_SINGLE_TOOLTIP_ROOT": "해당 숫자의 제곱근을 반환합니다.",
    "Blockly.Msg.LANG_MATH_SINGLE_TOOLTIP_ABS": "해당 숫자의 절댓값을 반환합니다.",
    "Blockly.Msg.LANG_MATH_SINGLE_TOOLTIP_NEG": "해당 숫자의 음수를 반환합니다.",
    "Blockly.Msg.LANG_MATH_SINGLE_TOOLTIP_LN": "해당 숫자의 자연로그값을 반환합니다. 즉, 밑이 e(2.71828…)인 로그값을 반환합니다",
    "Blockly.Msg.LANG_MATH_SINGLE_TOOLTIP_EXP": "해당 숫자의 e (2.71828…) 거듭제곱 값을 반환합니다.",
    "Blockly.Msg.LANG_MATH_ROUND_TOOLTIP_ROUND": "해당 숫자를 반올림합니다.",
    "Blockly.Msg.LANG_MATH_ROUND_TOOLTIP_CEILING": "입력받은 숫자에 소수점이 있고, 소수점이 0이 아닐때\n정수 부분에 1을 더합니다",
    "Blockly.Msg.LANG_MATH_ROUND_TOOLTIP_FLOOR": "입력받은 숫자의 소수점 아래를 버립니다",
    "Blockly.Msg.LANG_MATH_ROUND_OPERATOR_ROUND": "반올림",
    "Blockly.Msg.LANG_MATH_ROUND_OPERATOR_CEILING": "올림",
    "Blockly.Msg.LANG_MATH_ROUND_OPERATOR_FLOOR": "내림",
    "Blockly.Msg.LANG_MATH_TRIG_SIN": "sin",
    "Blockly.Msg.LANG_MATH_TRIG_COS": "cos",
    "Blockly.Msg.LANG_MATH_TRIG_TAN": "tan",
    "Blockly.Msg.LANG_MATH_TRIG_ASIN": "asin",
    "Blockly.Msg.LANG_MATH_TRIG_ACOS": "acos",
    "Blockly.Msg.LANG_MATH_TRIG_ATAN": "atan",
    "Blockly.Msg.LANG_MATH_TRIG_ATAN2": "atan2",
    "Blockly.Msg.LANG_MATH_TRIG_ATAN2_X": "x",
    "Blockly.Msg.LANG_MATH_TRIG_ATAN2_Y": "y",
    "Blockly.Msg.LANG_MATH_TRIG_TOOLTIP_SIN": "주어진 각도의 사인(sine)값으로 변환합니다.",
    "Blockly.Msg.LANG_MATH_TRIG_TOOLTIP_COS": "주어진 각도의 코사인(cosine)값으로 변환합니다.",
    "Blockly.Msg.LANG_MATH_TRIG_TOOLTIP_TAN": "주어진 각도의 탄젠트(tangent)값으로 변환합니다.",
    "Blockly.Msg.LANG_MATH_TRIG_TOOLTIP_ASIN": "주어진 사인(sine) 값을 가지게 되는 각도로 변환합니다.\n반환되는 각도 범위는 (-90, +90] 입니다.",
    "Blockly.Msg.LANG_MATH_TRIG_TOOLTIP_ACOS": "주어진 코사인(cosine) 값을 가지게 되는 각도로 변환합니다.\n변환되는 각도 범위는 [0, 180) 입니다.",
    "Blockly.Msg.LANG_MATH_TRIG_TOOLTIP_ATAN": "주어진 탄젠트(tangent) 값을 가지게 되는 각도로 변환합니다.\n변환되는 각도 범위는 (-90, +90) 입니다.",
    "Blockly.Msg.LANG_MATH_TRIG_TOOLTIP_ATAN2": "주어진 두 값이 직각좌표(y/x)를 이루게 되는 각도를 반환합니다.\n반환되는 각도 범위는 (-180, +180] 입니다.",
    "Blockly.Msg.LANG_MATH_ONLIST_OPERATOR_MIN": "최솟값",
    "Blockly.Msg.LANG_MATH_ONLIST_OPERATOR_MAX": "최댓값",
    "Blockly.Msg.LANG_MATH_DIVIDE": "÷",
    "Blockly.Msg.LANG_MATH_DIVIDE_OPERATOR_MODULO": "모듈로",
    "Blockly.Msg.LANG_MATH_DIVIDE_OPERATOR_REMAINDER": "나머지",
    "Blockly.Msg.LANG_MATH_DIVIDE_OPERATOR_QUOTIENT": "몫",
    "Blockly.Msg.LANG_MATH_DIVIDE_TOOLTIP_MODULO": "모듈로 연산 결과를 반환합니다.",
    "Blockly.Msg.LANG_MATH_DIVIDE_TOOLTIP_REMAINDER": "나머지를 반환합니다.",
    "Blockly.Msg.LANG_MATH_DIVIDE_TOOLTIP_QUOTIENT": "몫을 반환합니다.",
    "Blockly.Msg.LANG_MATH_RANDOM_INT_TITLE_RANDOM": "임의의 정수",
    "Blockly.Msg.LANG_MATH_RANDOM_INT_INPUT_FROM": "시작",
    "Blockly.Msg.LANG_MATH_RANDOM_INT_INPUT_TO": "끝",
    "Blockly.Msg.LANG_MATH_RANDOM_INT_INPUT": "임의의 정수 시작 %1 끝 %2",
    "Blockly.Msg.LANG_MATH_RANDOM_INT_TOOLTIP": "주어진 범위 내의 임의의 정수를 반환합니다.\n 최대 범위는 2**30보다 작은 수로 자동으로 변환됩니다.",
    "Blockly.Msg.LANG_MATH_RANDOM_FLOAT_TITLE_RANDOM": "임의의 분수",
    "Blockly.Msg.LANG_MATH_RANDOM_FLOAT_TOOLTIP": "0부터 1 사이의 임의의 수를 반환합니다.",
    "Blockly.Msg.LANG_MATH_RANDOM_SEED_TITLE_RANDOM": "난수 시드 지정하기",
    "Blockly.Msg.LANG_MATH_RANDOM_SEED_INPUT_TO": "시드",
    "Blockly.Msg.LANG_MATH_RANDOM_SEED_TOOLTIP": "난수 생성에 사용할 시드(seed)값을\n지정합니다",
    "Blockly.Msg.LANG_MATH_CONVERT_ANGLES_TITLE_CONVERT": "변환",
    "Blockly.Msg.LANG_MATH_CONVERT_ANGLES_OP_RAD_TO_DEG": "라디안을 각도로",
    "Blockly.Msg.LANG_MATH_CONVERT_ANGLES_OP_DEG_TO_RAD": "각도를 라디안으로",
    "Blockly.Msg.LANG_MATH_CONVERT_ANGLES_TOOLTIP_RAD_TO_DEG": "해당 라디안값에 대응되는 [0, 360) 범위의 각도값을 반환합니다.",
    "Blockly.Msg.LANG_MATH_CONVERT_ANGLES_TOOLTIP_DEG_TO_RAD": "해당 각도값에 대응되는 [-π, +π) 범위의 라디안값을 반환합니다.",
    "Blockly.Msg.LANG_MATH_FORMAT_AS_DECIMAL_TITLE": "소수로 나타내기",
    "Blockly.Msg.LANG_MATH_FORMAT_AS_DECIMAL_INPUT_NUM": "숫자",
    "Blockly.Msg.LANG_MATH_FORMAT_AS_DECIMAL_INPUT_PLACES": "자릿수",
    "Blockly.Msg.LANG_MATH_FORMAT_AS_DECIMAL_INPUT": "소수로 나타내기 숫자 %1 자릿수 %2",
    "Blockly.Msg.LANG_MATH_FORMAT_AS_DECIMAL_TOOLTIP": "주어진 소수점 이하의 자릿수까지 나타내는 형태로 반환합니다.",
    "Blockly.Msg.LANG_MATH_IS_A_NUMBER_INPUT_NUM": "숫자인가요?",
    "Blockly.Msg.LANG_MATH_IS_A_NUMBER_TOOLTIP": "주어진 값이 숫자인지 검사합니다.",
    "Blockly.Msg.LANG_MATH_IS_A_DECIMAL_INPUT_NUM": "10진수인가요?",
    "Blockly.Msg.LANG_MATH_IS_A_DECIMAL_TOOLTIP": "주어진 값이 양의 10진수를 나타내는 문자열인지 검사합니다.",
    "Blockly.Msg.LANG_MATH_IS_A_HEXADECIMAL_INPUT_NUM": "16진수인가요?",
    "Blockly.Msg.LANG_MATH_IS_A_HEXADECIMAL_TOOLTIP": "주어진 값이 16진수를 나타내는 문자열인지 검사합니다.",
    "Blockly.Msg.LANG_MATH_IS_A_BINARY_INPUT_NUM": "2진수인가요?",
    "Blockly.Msg.LANG_MATH_IS_A_BINARY_TOOLTIP": "주어진 값이 2진수를 나타내는 문자열인지 검사합니다.",
    "Blockly.Msg.LANG_MATH_CONVERT_NUMBER_TITLE_CONVERT": "진법 바꾸기",
    "Blockly.Msg.LANG_MATH_CONVERT_NUMBER_OP_DEC_TO_HEX": "10진수를 16진수로",
    "Blockly.Msg.LANG_MATH_CONVERT_NUMBER_TOOLTIP_DEC_TO_HEX": "10진수인 양의 정수를 16진수로 변환한 문자열을 반환합니다",
    "Blockly.Msg.LANG_MATH_CONVERT_NUMBER_OP_HEX_TO_DEC": "16진수를 10진수로",
    "Blockly.Msg.LANG_MATH_CONVERT_NUMBER_TOOLTIP_HEX_TO_DEC": "16진수를 나타내는 문자열을 10진수로 변환한 문자열을 반환합니다",
    "Blockly.Msg.LANG_MATH_CONVERT_NUMBER_OP_DEC_TO_BIN": "10진수를 2진수로",
    "Blockly.Msg.LANG_MATH_CONVERT_NUMBER_TOOLTIP_DEC_TO_BIN": "10진수인 양의 정수를 2진수로 변환한 문자열을 반환합니다",
    "Blockly.Msg.LANG_MATH_CONVERT_NUMBER_OP_BIN_TO_DEC": "2진수를 10진수로",
    "Blockly.Msg.LANG_MATH_CONVERT_NUMBER_TOOLTIP_BIN_TO_DEC": "2진수를 나타내는 문자열을 10진수로 변환한 문자열을 반환합니다",
    "Blockly.Msg.LANG_CATEGORY_TEXT": "텍스트",
    "Blockly.Msg.LANG_TEXT_TEXT_TOOLTIP": "빈칸에 입력한 텍스트를 입력합니다.",
    "Blockly.Msg.LANG_TEXT_TEXT_LEFT_QUOTE": "'",
    "Blockly.Msg.LANG_TEXT_TEXT_RIGHT_QUOTE": "'",
    "Blockly.Msg.LANG_TEXT_JOIN_TITLE_CREATEWITH": "텍스트 만들기",
    "Blockly.Msg.LANG_TEXT_JOIN_TOOLTIP": "모든 입력들을 하나의 텍스트 문자열로 합칩니다.\n 만약 아무런 입력값이 없다면, 빈 텍스트를 만듭니다.",
    "Blockly.Msg.LANG_TEXT_JOIN_TITLE_JOIN": "합치기",
    "Blockly.Msg.LANG_TEXT_JOIN_ITEM_TITLE_ITEM": "문자열",
    "Blockly.Msg.LANG_TEXT_JOIN_ITEM_TOOLTIP": " ",
    "Blockly.Msg.LANG_TEXT_APPEND_TO": "~에",
    "Blockly.Msg.LANG_TEXT_APPEND_APPENDTEXT": "텍스트 이어붙이기",
    "Blockly.Msg.LANG_TEXT_APPEND_VARIABLE": "항목",
    "Blockly.Msg.LANG_TEXT_APPEND_TOOLTIP": "텍스트를 변수 '%1'에 잇기.",
    "Blockly.Msg.LANG_TEXT_LENGTH_INPUT_LENGTH": "길이",
    "Blockly.Msg.LANG_TEXT_LENGTH_TOOLTIP": "주어진 텍스트를 구성하고 있는 문자 개수(공백,띄어쓰기 포함)를 반환합니다.",
    "Blockly.Msg.LANG_TEXT_ISEMPTY_INPUT_ISEMPTY": "비어있는가",
    "Blockly.Msg.LANG_TEXT_ISEMPTY_TOOLTIP": "텍스트 길이가 0이면 참을, 그렇지 않으면 거짓을 반환합니다.",
    "Blockly.Msg.LANG_TEXT_COMPARE_LT": " <",
    "Blockly.Msg.LANG_TEXT_COMPARE_EQUAL": "=",
    "Blockly.Msg.LANG_TEXT_COMPARE_NEQ": " ≠",
    "Blockly.Msg.LANG_TEXT_COMPARE_GT": " >",
    "Blockly.Msg.LANG_TEXT_COMPARE_INPUT_COMPARE": "텍스트 비교하기",
    "Blockly.Msg.LANG_TEXT_COMPARE_TOOLTIP_LT": "텍스트1과 텍스트2를 사전순으로 봤을 때 순서의 크기를 비교했을 때 텍스트1이 텍스트2보다 작은지 확인합니다.\n만약 텍스트의 앞부분이 같다면 길이가 더 짧은쪽이 더 작습니다.\n대문자가 소문자보다 큽니다.",
    "Blockly.Msg.LANG_TEXT_COMPARE_TOOLTIP_EQUAL": "텍스트 문자열이 동일한지 검사합니다.\n즉, 똑같은 문자들이 똑같은 순서인지 확인합니다. 이는 보통의 = 와는 다릅니다.\n예를 들어 텍스트를 숫자로 비교하는 경우 123과 0123은 같지만\n 텍스트로서는 같지 않습니다.",
    "Blockly.Msg.LANG_TEXT_COMPARE_TOOLTIP_GT": "텍스트1과 텍스트2를 사전순으로 봤을 때 순서의 크기를 비교했을 때 텍스트1이 텍스트2보다 큰지 확인합니다.\n만약 텍스트의 앞부분이 같다면 길이가 더 짧은쪽이 더 작습니다.\n대문자가 소문자보다 큽니다.",
    "Blockly.Msg.LANG_TEXT_TEXT_OBFUSCATE_TOOLTIP": "입력된 텍스트를 읽기 어려운 형태의 새로운 텍스트 블록으로 만듭니다. \n 이는 앱에 보안이 중요한 정보를 포함하여 배포해야 할 때 사용하세요. 예를 들면 API 키 같은 경우에요. \n경고: 전문가 수준에서는 매우 낮은 수준의 보안만 제공합니다.",
    "Blockly.Msg.LANG_TEXT_TEXT_OBFUSCATE": "텍스트 난독화",
    "Blockly.Msg.LANG_TEXT_CHANGECASE_OPERATOR_UPPERCASE": "대문자",
    "Blockly.Msg.LANG_TEXT_CHANGECASE_OPERATOR_DOWNCASE": "소문자",
    "Blockly.Msg.LANG_TEXT_CHANGECASE_TOOLTIP_UPPERCASE": "대문자로 변환한 텍스트 문자열의 복사본을 반환합니다.",
    "Blockly.Msg.LANG_TEXT_CHANGECASE_TOOLTIP_DOWNCASE": "소문자로 변환한 텍스트 문자열의 복사본을 반환합니다.",
    "Blockly.Msg.LANG_TEXT_TRIM_TITLE_TRIM": "앞뒤 공백 제거",
    "Blockly.Msg.LANG_TEXT_TRIM_TOOLTIP": "앞과 뒤쪽의 공백이 제거된 텍스트 문자열 인수의 복사본을 반환합니다.",
    "Blockly.Msg.LANG_TEXT_STARTS_AT_INPUT_STARTS_AT": "위치 찾기",
    "Blockly.Msg.LANG_TEXT_STARTS_AT_INPUT_TEXT": "텍스트",
    "Blockly.Msg.LANG_TEXT_STARTS_AT_INPUT_PIECE": "단어",
    "Blockly.Msg.LANG_TEXT_STARTS_AT_INPUT": "텍스트에서 단어 위치찾기  텍스트 %1 단어 %2",
    "Blockly.Msg.LANG_TEXT_STARTS_AT_TOOLTIP": "텍스트에서 특정 단어의 시작 위치를 반환합니다. 여기서 위치 1은 텍스트의 시작을 나타냅니다. 단어가 텍스트에 없으면 0을 반환합니다.",
    "Blockly.Msg.LANG_TEXT_CONTAINS_INPUT_CONTAINS": "포함",
    "Blockly.Msg.LANG_TEXT_CONTAINS_INPUT_TEXT": "텍스트",
    "Blockly.Msg.LANG_TEXT_CONTAINS_INPUT_PIECE": "조각",
    "Blockly.Msg.LANG_TEXT_CONTAINS_INPUT": "%1 텍스트 %2 %3 %4",
    "Blockly.Msg.LANG_TEXT_CONTAINS_TOOLTIP": "텍스트에 해당 조각이 있는지 검사해요.",
    "Blockly.Msg.LANG_TEXT_SPLIT_INPUT_TEXT": "텍스트",
    "Blockly.Msg.LANG_TEXT_SPLIT_INPUT_AT": "구분자",
    "Blockly.Msg.LANG_TEXT_SPLIT_INPUT_AT_LIST": "구분자 (리스트)",
    "Blockly.Msg.LANG_TEXT_SPLIT_OPERATOR_SPLIT_AT_FIRST": "텍스트 한 번만 분할하기",
    "Blockly.Msg.LANG_TEXT_SPLIT_OPERATOR_SPLIT_AT_FIRST_OF_ANY": "먼저 나오는 구분자로 한번 분할",
    "Blockly.Msg.LANG_TEXT_SPLIT_OPERATOR_SPLIT": "분할하기",
    "Blockly.Msg.LANG_TEXT_SPLIT_OPERATOR_SPLIT_AT_ANY": "일치하는 모든 위치 분할",
    "Blockly.Msg.LANG_TEXT_SPLIT_TOOLTIP_SPLIT_AT_FIRST": "주어진 텍스트를 두개의 조각으로 분할해서 리스트로 반환합니다.\n문자열 \"A,B,C,D\"를 구분자 쉼표( , )를 이용해서 분할하려 하면 리스트의 첫번째 요소는 \"A\"가 되고, 두번째 요소는 \"B,C,D\"가 됩니다.\n여기서 \"A\" 뒤에 있던 쉼표는 사라지는데, 그 지점이 분할 기준점이기 때문입니다.",
    "Blockly.Msg.LANG_TEXT_SPLIT_TOOLTIP_SPLIT_AT_FIRST_OF_ANY": "구분자 리스트의 구분자들 중 입력받은 문자열의 앞에서 부터 탐색할 때 가장 먼저 등장하는 리스트의 요소를 이용해서 텍스트를 한번만 분할 후 두개의 값을 가진 리스트로 반환합니다.\n\n예를 들어 문자열 \"가나다라마\"를\n\n구분자 리스트 (\"나\", \"다\")로 분할한다면,\n요소 중 \"나\"가 먼저 나오므로\n첫번째 요소는 \"가\",\n두번째 요소는 \"다라마\"가 됩니다.\n\n만약 구분자 리스트 (\"바\", \"라\", \"다\")로 분할한다면,\n요소 중 문자열에서 \"다\"가 먼저 나오므로\n첫번째 요소는 \"가나\",\n두번째 요소는 \"라마\"가 됩니다.",
    "Blockly.Msg.LANG_TEXT_SPLIT_TOOLTIP_SPLIT": "입력받은 텍스트에서 구분자와 일치하는 부분을 기준으로 모두 분할해서 리스트로 반환합니다.\n\n예시로 텍스트 \"하나,둘,셋,넷\"을 구분자 쉼표 \",\"로 분할면 결과는 (\"하나\", \"둘\", \"셋\", \"넷\") 이 됩니다.",
    "Blockly.Msg.LANG_TEXT_SPLIT_TOOLTIP_SPLIT_AT_ANY": "텍스트에서 리스트로 주어진 구분자에 해당하는 모든 지점을 분할하여 리스트로 반환합니다.\n \n예시로 텍스트 \"A&B+C&D+E&F\"를 구분자 리스트 (\"&\", \"+\")로 분할하면 결과는\n(\"A\", \"B\", \"C\", \"D\", \"E\", \"F\") 가 됩니다.",
    "Blockly.Msg.LANG_TEXT_SPLIT_AT_SPACES_TITLE": "빈칸을 기준으로 분할하기",
    "Blockly.Msg.LANG_TEXT_SPLIT_AT_TOOLTIP": "텍스트를 빈칸( )을 기준으로 분할합니다. 빈칸이 여러 개 붙어있어도 하나로 칩니다.\r\n\r\n예시로 텍스트 \"a b   c\"는 b와 c 사이에 빈칸이 3개가 있지만, 결과는 (\"a\", \"b\", \"c\")가 됩니다.",
    "Blockly.Msg.LANG_TEXT_SEGMENT_TITLE_SEGMENT": "텍스트에서 문자열 추출하기",
    "Blockly.Msg.LANG_TEXT_SEGMENT_INPUT_START": "시작 위치",
    "Blockly.Msg.LANG_TEXT_SEGMENT_INPUT_LENGTH": "문자열 길이",
    "Blockly.Msg.LANG_TEXT_SEGMENT_INPUT_TEXT": "텍스트",
    "Blockly.Msg.LANG_TEXT_SEGMENT_INPUT": "텍스트에서 문자열 추출하기  텍스트 %1 시작위치 %2 길이 %3",
    "Blockly.Msg.LANG_TEXT_SEGMENT_AT_TOOLTIP": "지정된 텍스트로에서, 지정된 위치로부터 시작해서 지정된 길이의 문자열을 추출합니다. 위치 1은 텍스트의 시작을 나타냅니다.",
    "Blockly.Msg.LANG_TEXT_REPLACE_ALL_INPUT_SEGMENT": "찾을 문자열",
    "Blockly.Msg.LANG_TEXT_REPLACE_ALL_INPUT_TEXT": "텍스트",
    "Blockly.Msg.LANG_TEXT_REPLACE_ALL_TITLE_REPLACE_ALL": "텍스트에서 문자열 교체하기",
    "Blockly.Msg.LANG_TEXT_REPLACE_ALL_INPUT_REPLACEMENT": "바꿀 문자열",
    "Blockly.Msg.LANG_TEXT_REPLACE_ALL_INPUT": "텍스트에서 문자열 교체하기 텍스트 %1 찾을문자열 %2 바꿀문자열 %3",
    "Blockly.Msg.LANG_TEXT_REPLACE_ALL_TOOLTIP": "문자열의 모든 찾은 문자열을 바꿀 문자열로 대체한 새 텍스트를 반환합니다.",
    "Blockly.Msg.LANG_TEXT_TEXT_IS_STRING_TITLE": "텍스트인가요?",
    "Blockly.Msg.LANG_TEXT_TEXT_IS_STRING_INPUT_THING": "값",
    "Blockly.Msg.LANG_TEXT_TEXT_IS_STRING_TOOLTIP": "<code>값</code>이 문자열이면 참을 반환합니다.",
    "Blockly.Msg.LANG_CATEGORY_LISTS": "리스트",
    "Blockly.Msg.LANG_LISTS_CREATE_EMPTY_TITLE": "빈 리스트 만들기",
    "Blockly.Msg.LANG_LISTS_CREATE_WITH_TITLE_MAKE_LIST": "리스트 만들기",
    "Blockly.Msg.LANG_LISTS_CREATE_WITH_TOOLTIP": "여러 개의 항목을 가진 리스트를 만듭니다.",
    "Blockly.Msg.LANG_LISTS_CREATE_WITH_CONTAINER_TITLE_ADD": "리스트",
    "Blockly.Msg.LANG_LISTS_CREATE_WITH_CONTAINER_TOOLTIP": "추가, 삭제 또는 리스트 블록 재구성을 위한 섹션 재 정렬하기",
    "Blockly.Msg.LANG_LISTS_CREATE_WITH_ITEM_TITLE": "항목",
    "Blockly.Msg.LANG_LISTS_CREATE_WITH_ITEM_TOOLTIP": "항목을 리스트에 추가합니다.",
    "Blockly.Msg.LANG_LISTS_ADD_ITEM_TITLE": "항목",
    "Blockly.Msg.LANG_LISTS_ADD_ITEM_TOOLTIP": "항목을 리스트에 추가합니다.",
    "Blockly.Msg.LANG_LISTS_SELECT_ITEM_TITLE_SELECT": "항목 선택하기",
    "Blockly.Msg.LANG_LISTS_SELECT_ITEM_INPUT_LIST": "리스트",
    "Blockly.Msg.LANG_LISTS_SELECT_ITEM_INPUT_INDEX": "위치",
    "Blockly.Msg.LANG_LISTS_SELECT_ITEM_INPUT": "항목 선택하기  리스트 %1 위치 %2",
    "Blockly.Msg.LANG_LISTS_SELECT_ITEM_TOOLTIP": "리스트 안에서 해당 위치에 있는 값을 반환합니다.",
    "Blockly.Msg.LANG_LISTS_IS_IN_TITLE_IS_IN": "리스트 안에 있나요?",
    "Blockly.Msg.LANG_LISTS_IS_IN_INPUT_THING": "항목",
    "Blockly.Msg.LANG_LISTS_IS_IN_INPUT_LIST": "리스트",
    "Blockly.Msg.LANG_LISTS_IS_IN_INPUT": "리스트에 있는가?  항목 %1 리스트 %2",
    "Blockly.Msg.LANG_LISTS_IS_IN_TOOLTIP": "항목이 리스트에 있으면 '참'를 반환하고 그렇지 않으면 '거짓'를 반환합니다.",
    "Blockly.Msg.LANG_LISTS_POSITION_IN_TITLE_POSITION": "리스트에서의 위치",
    "Blockly.Msg.LANG_LISTS_POSITION_IN_INPUT_THING": "항목",
    "Blockly.Msg.LANG_LISTS_POSITION_IN_INPUT_LIST": "리스트",
    "Blockly.Msg.LANG_LISTS_POSITION_IN_INPUT": "위치 구하기  항목 %1 리스트 %2",
    "Blockly.Msg.LANG_LISTS_POSITION_IN_TOOLTIP": "리스트에서 항목의 위치를 가져옵니다. 리스트에 없는 경우 0을 반환합니다.",
    "Blockly.Msg.LANG_LISTS_PICK_RANDOM_TITLE_PICK_RANDOM": "임의의 항목 선택하기",
    "Blockly.Msg.LANG_LISTS_PICK_RANDOM_ITEM_INPUT_LIST": "리스트",
    "Blockly.Msg.LANG_LISTS_PICK_RANDOM_TOOLTIP": "리스트에서 임의의 항목(랜덤)을 선택합니다.",
    "Blockly.Msg.LANG_LISTS_REPLACE_ITEM_TITLE_REPLACE": "항목 교체하기",
    "Blockly.Msg.LANG_LISTS_REPLACE_ITEM_INPUT_LIST": "리스트",
    "Blockly.Msg.LANG_LISTS_REPLACE_ITEM_INPUT_INDEX": "위치",
    "Blockly.Msg.LANG_LISTS_REPLACE_ITEM_INPUT_REPLACEMENT": "바꿀 항목",
    "Blockly.Msg.LANG_LISTS_REPLACE_ITEM_INPUT": "항목 교체하기  리스트 %1 위치 %2 바꿀항목 %3",
    "Blockly.Msg.LANG_LISTS_REPLACE_ITEM_TOOLTIP": "리스트에서 해당 위치의 항목을 교체하고자 하는 항목으로 변경합니다.",
    "Blockly.Msg.LANG_LISTS_REMOVE_ITEM_TITLE_REMOVE": "항목 삭제하기",
    "Blockly.Msg.LANG_LISTS_REMOVE_ITEM_INPUT_LIST": "리스트",
    "Blockly.Msg.LANG_LISTS_REMOVE_ITEM_INPUT_INDEX": "위치",
    "Blockly.Msg.LANG_LISTS_REMOVE_ITEM_INPUT": "항목 삭제하기  리스트 %1 위치 %2",
    "Blockly.Msg.LANG_LISTS_REMOVE_ITEM_TOOLTIP": "리스트의 지정된 위치에 있는 항목을 삭제합니다.",
    "Blockly.Msg.LANG_LISTS_LENGTH_INPUT_LENGTH": "길이 구하기",
    "Blockly.Msg.LANG_LISTS_LENGTH_INPUT_LIST": "리스트",
    "Blockly.Msg.LANG_LISTS_LENGTH_INPUT": "리스트 길이 리스트 %1",
    "Blockly.Msg.LANG_LISTS_LENGTH_TOOLTIP": "리스트에 몇 개의 항목이 있는지 세어서 그 값을 반환합니다.",
    "Blockly.Msg.LANG_LISTS_APPEND_LIST_TITLE_APPEND": "리스트 합치기",
    "Blockly.Msg.LANG_LISTS_APPEND_LIST_INPUT": "리스트 합치기  리스트1 %1 리스트2 %2",
    "Blockly.Msg.LANG_LISTS_APPEND_LIST_TOOLTIP": "리스트1의 뒤에 리스트2를 이어붙입니다.\r\n이 작업 이후 리스트1은 리스트2와 합쳐진 값이 되지만, 리스트2에는 아무런 변화도 없습니다.",
    "Blockly.Msg.LANG_LISTS_ADD_ITEMS_TITLE_ADD": "항목 추가하기",
    "Blockly.Msg.LANG_LISTS_ADD_ITEMS_INPUT_LIST": " 리스트",
    "Blockly.Msg.LANG_LISTS_ADD_ITEMS_INPUT_ITEM": "항목",
    "Blockly.Msg.LANG_LISTS_ADD_ITEMS_INPUT": "항목 추가 리스트 %1 항목 %2",
    "Blockly.Msg.LANG_LISTS_ADD_ITEMS_TOOLTIP": "리스트의 마지막에 항목을 추가합니다.",
    "Blockly.Msg.LANG_LISTS_ADD_ITEMS_CONTAINER_TITLE_ADD": "리스트",
    "Blockly.Msg.LANG_LISTS_ADD_ITEMS_CONTAINER_TOOLTIP": "이 리스트 블록에 요소를 추가, 삭제, 재정렬 하기 위해서는 이 블록을 수정하세요.",
    "Blockly.Msg.LANG_LISTS_COPY_TITLE_COPY": "리스트 복사하기",
    "Blockly.Msg.LANG_LISTS_COPY_INPUT_LIST": "리스트",
    "Blockly.Msg.LANG_LISTS_COPY_TOOLTIP": "입력받은 리스트의 복사본을 만듭니다.",
    "Blockly.Msg.LANG_LISTS_IS_LIST_TITLE_IS_LIST": "리스트인가요?",
    "Blockly.Msg.LANG_LISTS_IS_LIST_INPUT_THING": "값",
    "Blockly.Msg.LANG_LISTS_IS_LIST_TOOLTIP": "리스트인지 검사합니다.",
    "Blockly.Msg.LANG_LISTS_REVERSE_TITLE_REVERSE": "역순으로 바꾸기",
    "Blockly.Msg.LANG_LISTS_REVERSE_INPUT_LIST": "리스트",
    "Blockly.Msg.LANG_LISTS_REVERSE_TOOLTIP": "리스트의 요소의 순서를 역순으로 재정렬해서 반환합니다.",
    "Blockly.Msg.LANG_LISTS_TO_CSV_ROW_TITLE_TO_CSV": "CSV 행으로 바꾸기",
    "Blockly.Msg.LANG_LISTS_TO_CSV_ROW_INPUT_LIST": "리스트",
    "Blockly.Msg.LANG_LISTS_TO_CSV_ROW_TOOLTIP": "리스트의 각 항목을 쉼표( , )로 구분하여 나타내는 CSV 행(줄)으로 변환하여 반환합니다. 리스트의 각 항목은 큰따옴표로 표시됩니다. 항목들은 쉼표로 구분됩니다. 반환되는 CSV 텍스트는 개행문자 없이 오직 한 줄입니다.",
    "Blockly.Msg.LANG_LISTS_FROM_CSV_ROW_TITLE_FROM_CSV": "CSV 행을 리스트로 바꾸기",
    "Blockly.Msg.LANG_LISTS_FROM_CSV_ROW_INPUT_TEXT": "텍스트",
    "Blockly.Msg.LANG_LISTS_FROM_CSV_ROW_TOOLTIP": "CSV 행 문자열을 리스트로 변환합니다. 만약 행 안에서 줄 바뀜이 일어나면 오류가 발생합니다. 다만 행의 제일 뒤에서 줄 바꿈이 되거나 CSRF가 있는 경우는 괜찮습니다.",
    "Blockly.Msg.LANG_LISTS_TO_CSV_TABLE_TITLE_TO_CSV": "CSV 표로 바꾸기",
    "Blockly.Msg.LANG_LISTS_TO_CSV_TABLE_INPUT_LIST": "리스트",
    "Blockly.Msg.LANG_LISTS_TO_CSV_TABLE_TOOLTIP": "리스트를 CSV 행 여러 줄로 이루어진 표 형식의 CSV 표로 변환합니다. 리스트의 각 항목은 CSV 표를 나타내는 CSV 행이 됩니다. CSV 행 안의 항목은 큰따옴표로 표시됩니다. 각 CSV 행의 항목들은 쉼표로, 리스트의 각 항목은 줄 바꿈( \\r\\n )으로 구분됩니다.",
    "Blockly.Msg.LANG_LISTS_FROM_CSV_TABLE_TITLE_FROM_CSV": "CSV 표를 리스트로 바꾸기",
    "Blockly.Msg.LANG_LISTS_FROM_CSV_TABLE_INPUT_TEXT": "텍스트",
    "Blockly.Msg.LANG_LISTS_FROM_CSV_TABLE_TOOLTIP": "CSV(쉼표로 구분된 값) 형식의 표로 이루어진 텍스트를 리스트로 변환합니다. 각 줄은 개행문자 ( \\n ) 또는 CRLF( \\r\\n )으로 구분됩니다.",
    "Blockly.Msg.LANG_LISTS_INSERT_TITLE_INSERT_LIST": "항목 삽입하기",
    "Blockly.Msg.LANG_LISTS_INSERT_INPUT_LIST": "리스트",
    "Blockly.Msg.LANG_LISTS_INSERT_INPUT_INDEX": "위치",
    "Blockly.Msg.LANG_LISTS_INSERT_INPUT_ITEM": "항목",
    "Blockly.Msg.LANG_LISTS_INSERT_INPUT": "항목 삽입하기  리스트 %1 위치 %2 항목 %3",
    "Blockly.Msg.LANG_LISTS_INSERT_TOOLTIP": "해당 항목을 지정된 위치의 리스트에 삽입합니다.",
    "Blockly.Msg.LANG_LISTS_TITLE_IS_EMPTY": "리스트가 비어있는가?",
    "Blockly.Msg.LANG_LISTS_INPUT_LIST": "리스트",
    "Blockly.Msg.LANG_LISTS_IS_EMPTY_TOOLTIP": "리스트가 비어있다면 참을 반환합니다.",
    "Blockly.Msg.LANG_LISTS_LOOKUP_IN_PAIRS_TITLE_LOOKUP_IN_PAIRS": "짝을 지어 찾기",
    "Blockly.Msg.LANG_LISTS_LOOKUP_IN_PAIRS_INPUT_KEY": "첫 번째 항목",
    "Blockly.Msg.LANG_LISTS_LOOKUP_IN_PAIRS_INPUT_PAIRS": "2차원 리스트",
    "Blockly.Msg.LANG_LISTS_LOOKUP_IN_PAIRS_INPUT_NOT_FOUND": "찾지 못함",
    "Blockly.Msg.LANG_LISTS_LOOKUP_IN_PAIRS_INPUT": "2차원 리스트에서 두 번째 항목 찾기 첫 번째항목 %1 2차원리스트 %2 찾지못함 %3",
    "Blockly.Msg.LANG_LISTS_LOOKUP_IN_PAIRS_TOOLTIP": "쌍으로 된 리스트에서 키와 연관된 값을 찾아 반환합니다\r\n\r\n예시로 2차원 리스트가\r\n((가 가락지) (나 나비) (다 다람쥐))이고,\r\n첫 번째 항목이 \"나\" 이면\r\n반환 값은 \"나비\"입니다.",
    "Blockly.Msg.LANG_LISTS_JOIN_WITH_SEPARATOR_TITLE": "구분자로 결합하기",
    "Blockly.Msg.LANG_LISTS_JOIN_WITH_SEPARATOR_SEPARATOR": "구분자",
    "Blockly.Msg.LANG_LISTS_JOIN_WITH_SEPARATOR_LIST": "리스트",
    "Blockly.Msg.LANG_LISTS_JOIN_WITH_SEPARATOR_INPUT": "항목 합치기 구분자 %1 리스트 %2",
    "Blockly.Msg.LANG_LISTS_JOIN_WITH_SEPARATOR_TOOLTIP": "리스트의 각 요소를 구분자로 구분되게 연결해서 문자열로 반환합니다.\r\nex) 리스트가 [A, B, C]이고, 구분자가 / 이면\r\n반환 값은문자열  \"A/B/C\" 입니다.",
    "Blockly.Msg.LANG_VARIABLES_GLOBAL_DECLARATION_TITLE_INIT": "전역변수 초기화",
    "Blockly.Msg.LANG_VARIABLES_GLOBAL_DECLARATION_NAME": "이름",
    "Blockly.Msg.LANG_VARIABLES_GLOBAL_DECLARATION_TO": "초깃값",
    "Blockly.Msg.LANG_VARIABLES_GLOBAL_DECLARATION_COLLAPSED_TEXT": "전역변수",
    "Blockly.Msg.LANG_VARIABLES_GLOBAL_DECLARATION_TOOLTIP": "전역변수를 만들고 연결된 블록의 값을 해당 변수에 지정합니다.",
    "Blockly.Msg.LANG_VARIABLES_GLOBAL_PREFIX": "전역변수",
    "Blockly.Msg.LANG_VARIABLES_GET_TITLE_GET": "가져오기",
    "Blockly.Msg.LANG_VARIABLES_LOCAL_DECLARATION_EXPRESSION_IN_RETURN": "실행",
    "Blockly.Msg.LANG_VARIABLES_GET_COLLAPSED_TEXT": "가져오기",
    "Blockly.Msg.LANG_VARIABLES_GET_TOOLTIP": "이 변수의 값을 가져옵니다.",
    "Blockly.Msg.LANG_VARIABLES_SET_TITLE_SET": "지정하기",
    "Blockly.Msg.LANG_VARIABLES_SET_TITLE_TO": "값",
    "Blockly.Msg.LANG_VARIABLES_SET_COLLAPSED_TEXT": "지정하기",
    "Blockly.Msg.LANG_VARIABLES_SET_TOOLTIP": "이 변수의 값을 입력값으로 지정합니다.",
    "Blockly.Msg.LANG_VARIABLES_VARIABLE": " 변수",
    "Blockly.Msg.LANG_VARIABLES_LOCAL_DECLARATION_TITLE_INIT": "지역변수 초기화",
    "Blockly.Msg.LANG_VARIABLES_LOCAL_DECLARATION_DEFAULT_NAME": "이름",
    "Blockly.Msg.LANG_VARIABLES_LOCAL_DECLARATION_INPUT_TO": "초깃값",
    "Blockly.Msg.LANG_VARIABLES_LOCAL_DECLARATION_IN_DO": "실행",
    "Blockly.Msg.LANG_VARIABLES_LOCAL_DECLARATION_COLLAPSED_TEXT": "지역변수",
    "Blockly.Msg.LANG_VARIABLES_LOCAL_DECLARATION_TOOLTIP": "이 블록의 영역 내부에서만 사용할 수 있는 변수를 생성합니다.",
    "Blockly.Msg.LANG_VARIABLES_LOCAL_DECLARATION_TRANSLATED_NAME": "사용할 지역변수 초기화",
    "Blockly.Msg.LANG_VARIABLES_LOCAL_DECLARATION_EXPRESSION_COLLAPSED_TEXT": "지역변수",
    "Blockly.Msg.LANG_VARIABLES_LOCAL_DECLARATION_EXPRESSION_TOOLTIP": "이 블록의 반환 값에서만 접근 가능한 변수를 만듭니다.",
    "Blockly.Msg.LANG_VARIABLES_LOCAL_DECLARATION_EXPRESSION_TRANSLATED_NAME": "반환 시 지역변수를 초기화하세요",
    "Blockly.Msg.LANG_VARIABLES_LOCAL_MUTATOR_CONTAINER_TITLE_LOCAL_NAMES": "지역변수 이름",
    "Blockly.Msg.LANG_VARIABLES_LOCAL_MUTATOR_CONTAINER_TOOLTIP": " ",
    "Blockly.Msg.LANG_VARIABLES_LOCAL_MUTATOR_ARG_TITLE_NAME": "이름",
    "Blockly.Msg.LANG_VARIABLES_LOCAL_MUTATOR_ARG_DEFAULT_VARIABLE": "x",
    "Blockly.Msg.LANG_PROCEDURES_DEFNORETURN_DEFINE": "함수 만들기",
    "Blockly.Msg.LANG_PROCEDURES_DEFNORETURN_PROCEDURE": "함수",
    "Blockly.Msg.LANG_PROCEDURES_DEFNORETURN_DO": "실행",
    "Blockly.Msg.LANG_PROCEDURES_DEFNORETURN_COLLAPSED_PREFIX": "함수 만들기 ",
    "Blockly.Msg.LANG_PROCEDURES_DEFNORETURN_TOOLTIP": "반환 값을 가지지 않는 함수입니다.",
    "Blockly.Msg.LANG_PROCEDURES_DOTHENRETURN_THEN_RETURN": "결과",
    "Blockly.Msg.LANG_PROCEDURES_DOTHENRETURN_DO": "실행",
    "Blockly.Msg.LANG_PROCEDURES_DOTHENRETURN_RETURN": "결괏값 반환",
    "Blockly.Msg.LANG_PROCEDURES_DOTHENRETURN_TOOLTIP": "'실행' 영역에 있는 블록을 실행하고 결과를 반환합니다. 변수에 값을 반환하기 전에 함수를 실행해야 하는 경우 유용합니다.",
    "Blockly.Msg.LANG_PROCEDURES_DOTHENRETURN_COLLAPSED_TEXT": "실행/결과",
    "Blockly.Msg.LANG_PROCEDURES_DEFRETURN_DEFINE": "함수 만들기",
    "Blockly.Msg.LANG_PROCEDURES_DEFRETURN_RETURN": "결괏값 반환",
    "Blockly.Msg.LANG_PROCEDURES_DEFRETURN_COLLAPSED_PREFIX": "함수 만들기 ",
    "Blockly.Msg.LANG_PROCEDURES_DEFRETURN_TOOLTIP": "결괏값을 반환하는 함수입니다.",
    "Blockly.Msg.LANG_PROCEDURES_DEF_DUPLICATE_WARNING": "경고:\n이 함수는 중복된 입력값을 가지고 있습니다.",
    "Blockly.Msg.LANG_PROCEDURES_CALLNORETURN_CALL": "함수 호출하기 ",
    "Blockly.Msg.LANG_PROCEDURES_CALLNORETURN_PROCEDURE": "함수",
    "Blockly.Msg.LANG_PROCEDURES_CALLNORETURN_COLLAPSED_PREFIX": "함수 호출하기 ",
    "Blockly.Msg.LANG_PROCEDURES_CALLNORETURN_TOOLTIP": "반환 값이 없는 함수를 호출합니다.",
    "Blockly.Msg.LANG_PROCEDURES_CALLNORETURN_TRANSLATED_NAME": "반환을 호출하지 않습니다.",
    "Blockly.Msg.LANG_PROCEDURES_CALLRETURN_COLLAPSED_PREFIX": "함수 호출하기 ",
    "Blockly.Msg.LANG_PROCEDURES_CALLRETURN_TOOLTIP": "결과값을 반환하는 함수를 호출합니다.",
    "Blockly.Msg.LANG_PROCEDURES_CALLRETURN_TRANSLATED_NAME": "결괏값을 가지는 함수를 호출합니다",
    "Blockly.Msg.LANG_PROCEDURES_MUTATORCONTAINER_TITLE": "입력값",
    "Blockly.Msg.LANG_PROCEDURES_MUTATORARG_TITLE": "입력:",
    "Blockly.Msg.LANG_PROCEDURES_HIGHLIGHT_DEF": "하이라이트 함수",
    "Blockly.Msg.LANG_PROCEDURES_MUTATORCONTAINER_TOOLTIP": " ",
    "Blockly.Msg.LANG_PROCEDURES_MUTATORARG_TOOLTIP": " ",
    "Blockly.Msg.UNDEFINED_BLOCK_TOOLTIP": "이 블록은 정의되지 않았습니다. 이 블록을 삭제하세요!",
    "Blockly.Msg.LANG_COMPONENT_BLOCK_TITLE_WHEN": "언제 ",
    "Blockly.Msg.LANG_COMPONENT_BLOCK_TITLE_DO": "실행",
    "Blockly.Msg.LANG_COMPONENT_BLOCK_GENERIC_EVENT_TITLE": "무엇이든 ",
    "Blockly.Msg.LANG_COMPONENT_BLOCK_METHOD_TITLE_CALL": "호출 ",
    "Blockly.Msg.LANG_COMPONENT_BLOCK_GENERIC_METHOD_TITLE_CALL": "호출 ",
    "Blockly.Msg.LANG_COMPONENT_BLOCK_GENERIC_METHOD_TITLE_FOR_COMPONENT": "컴포넌트",
    "Blockly.Msg.LANG_COMPONENT_BLOCK_GENERIC_GETTER_TITLE_OF_COMPONENT": "컴포넌트",
    "Blockly.Msg.LANG_COMPONENT_BLOCK_SETTER_TITLE_SET": "지정하기 ",
    "Blockly.Msg.LANG_COMPONENT_BLOCK_SETTER_TITLE_TO": " 값",
    "Blockly.Msg.LANG_COMPONENT_BLOCK_GENERIC_SETTER_TITLE_SET": "지정하기 ",
    "Blockly.Msg.LANG_COMPONENT_BLOCK_GENERIC_SETTER_TITLE_TO": " 값",
    "Blockly.Msg.LANG_COMPONENT_BLOCK_GENERIC_SETTER_TITLE_OF_COMPONENT": "컴포넌트",
    "Blockly.Msg.DOWNLOAD_BLOCKS_AS_PNG": "이미지 파일로 저장하기",
    "Blockly.Msg.REPL_NO_START_EMULATOR": "에뮬레이터에서 컴패니언을 실행할 수 없습니다.",
    "Blockly.Msg.DIALOG_ENTER_VALUES": "다음에 대한 값 입력:",
    "Blockly.Msg.DIALOG_UNBOUND_VAR": "값이 할당되지 않은 변수",
    "Blockly.Msg.DIALOG_SUBMIT": "제출",
    "Blockly.Msg.DIALOG_FOUND_COMPANION": "10 컴패니언 찾기",
    "Blockly.Msg.DIALOG_SECURE_ESTABLISHED": "30 보안 연결 설정됨",
    "Blockly.Msg.DIALOG_SECURE_ESTABLISHING": "20 보안 연결 설정",
    "Blockly.Msg.DIALOG_RENDEZVOUS_NEGOTIATING": "15 랑데부 (기다려 주세요)",
    "Blockly.Msg.TIME_DURATION": "기간",
    "Blockly.Msg.TIME_SECONDS": "초",
    "Blockly.Msg.TIME_MINUTES": "분",
    "Blockly.Msg.TIME_HOURS": "시",
    "Blockly.Msg.TIME_DAYS": "일",
    "Blockly.Msg.TIME_WEEKS": "주",
    "Blockly.Msg.TIME_MONTHS": "월",
    "Blockly.Msg.TIME_YEARS": "년",
    "Blockly.Msg.CONNECT_TO_DO_IT": "'실행'을 사용하기 위해 반드시 컴패니언이나 에뮬레이터에 연결되어 있어야 합니다",
    "Blockly.Msg.CAN_NOT_DO_IT": "실행할 수 없음",
    "Blockly.Msg.DO_IT_DISCONNECTED": "실행 (컴패니언 연결 안 됨)",
    "Blockly.Msg.DO_IT": "실행",
    "Blockly.Msg.CLEAR_DO_IT_ERROR": "초기화 에러",
    "Blockly.Msg.GENERATE_YAIL": "Yail 생성",
    "Blockly.Msg.WARNING_DELETE_X_BLOCKS": "정말 블록 %1개를 모두 삭제하시겠습니까?",
    "Blockly.Msg.REPL_EMULATOR_ONLY": "에뮬레이터를 업데이트할 때 오직 이 옵션만 사용할 수 있습니다",
    "Blockly.Msg.REPL_WEBRTC_CONNECTION_ERROR": "컴패니언 연결 실패",
    "Blockly.Msg.REPL_FACTORY_RESET": "당신의 애뮬레이터를 초기 상태로 되돌립니다. 만약 설치된 업데이트가 있다면 초기화 후 다시 설치해야 합니다.",
    "Blockly.Msg.REPL_DO_YOU_REALLY_Q": "정말 그렇게 하겠습니까?",
    "Blockly.Msg.REPL_YOUR_CODE_IS": "당신의 코드는",
    "Blockly.Msg.REPL_TRY_AGAIN1": "컴패니언 연결에 실패했습니다. 다시 시도해주세요.",
    "Blockly.Msg.REPL_CONNECT_TO_COMPANION": "컴패니언에 연결",
    "Blockly.Msg.REPL_VERIFYING_COMPANION": "컴패니언이 시작됐는지 확인 중...",
    "Blockly.Msg.REPL_COMPANION_STARTED_WAITING": "컴패니언 시작 중. ",
    "Blockly.Msg.REPL_STARTING_COMPANION_IN_EMULATOR": "에뮬레이터에서 컴패니언 앱을 실행합니다.",
    "Blockly.Msg.REPL_STARTING_COMPANION_ON_PHONE": "연결된 기기에서 컴패니언 앱을 실행합니다.",
    "Blockly.Msg.REPL_EMULATOR_STARTED": "에뮬레이터 시작됨. 잠시만 기다려주세요 ",
    "Blockly.Msg.REPL_SECONDS_ENSURE_RUNNING": " 초: 모든 것이 작동 중인지 확인 중입니다.",
    "Blockly.Msg.REPL_USB_CONNECTED_WAIT": "USB 연결됨. 잠시만 기다려 주세요 ",
    "Blockly.Msg.REPL_HELPER_NOT_RUNNING": "aiStarter가 작동 중이 아닌 것 같습니다.<br /><a href='http://appinventor.mit.edu' target='_blank'>도움이 필요한가요?</a>",
    "Blockly.Msg.REPL_HELPER_Q": "aiStarter가 작동 중인가요?",
    "Blockly.Msg.REPL_AI_NO_SEE_DEVICE": "당신의 기기를 찾을 수 없습니다. 케이블 연결상태와 드라이버 설치 상태를 확인하세요.",
    "Blockly.Msg.REPL_PLUGGED_IN_Q": "연결됐나요?",
    "Blockly.Msg.REPL_CONNECTION_FAILURE1": "연결 실패",
    "Blockly.Msg.REPL_KEEP_TRYING": "계속 시도",
    "Blockly.Msg.REPL_GIVE_UP": "포기",
    "Blockly.Msg.REPL_CANCEL": "취소",
    "Blockly.Msg.REPL_CONNECTING": "연결 중...",
    "Blockly.Msg.REPL_STARTING_EMULATOR": "안드로이드 에뮬레이터를 실행 중입니다<br/>1~2분 정도 기다려 주세요.",
    "Blockly.Msg.REPL_CONNECTING_USB_CABLE": "USB 케이블로 연결하기",
    "Blockly.Msg.REPL_NO_ERROR_FIVE_SECONDS": "<br/><i>참고:</i>&nbsp;5초 동안은 다른 오류가 표시되지 않습니다.",
    "Blockly.Msg.REPL_UPDATE_INFO": "업데이트가 당신의 기기(혹은 에뮬레이터)에 설치됩니다. 기기에 뜨는 설치 알림을 확인해 주세요.<br /><br />중요: 업데이트가 끝난 후, 반드시 \"open\" 버튼이 아닌 \"DONE\" 버튼을 눌러주세요. 그리고서 앱인벤터의 \"연결\" 메뉴에서 \"다시 연결하기\"를 누른 후 재연결해주세요.",
    "Blockly.Msg.REPL_COMPANION_WRONG_PACKAGE": "현재 사용 중인 컴패니언은 다른 앱인벤터 인스턴스를 위해 빌드됐습니다. 올바른 컴패니언을 찾으려면 상단 메뉴에서 \"도움말\" > \"컴패니언 정보\"를 눌러보세요.",
    "Blockly.Msg.REPL_COMPANION_OUT_OF_DATE_IMMEDIATE": "최신 버전이 아닌 컴패니언을 사용중입니다. 가능한 한 빨리 업데이트를 하세요. 만약 스토어에서 자동 업데이트가 활성화되어 있으면 스스로 곧 자동으로 업데이트될 것입니다.",
    "Blockly.Msg.LANG_CONTROLS_CHOOSE_TOOLTIP": "만약 조건이 참이라면 '(이)라면'의 값을 돌려줍니다. 그렇지 않다면 '아니면'의 값을 돌려줍니다.",
    "Blockly.Msg.REPL_UPDATE_NO_CONNECTION": "컴패니언을 업데이트하기 위해서 컴패니언을 연결해야합니다",
    "Blockly.Msg.REPL_NOW_DOWNLOADING": "앱인벤터 서버에서 업데이트를 다운로드 중입니다. 잠시만 기다려주세요",
    "Blockly.Msg.REPL_RUNTIME_ERROR": "런타임 에러",
    "Blockly.Msg.REPL_UNABLE_TO_LOAD_NO_RESPOND": "앱인벤터 서버에서 업데이트를 가져올 수 없습니다. (서버가 응답하지 않음)",
    "Blockly.Msg.REPL_UNABLE_TO_LOAD": "앱인벤터 서버에서 업데이트를 가져올 수 없습니다",
    "Blockly.Msg.REPL_UNABLE_TO_UPDATE": "장치/에뮬레이터에 업데이트를 보낼 수 없습니다",
    "Blockly.Msg.REPL_UPDATE_NO_UPDATE": "업데이트가 존재하지 않습니다",
    "Blockly.Msg.REPL_GOT_IT": "확인",
    "Blockly.Msg.REPL_OK_LOWER": "확인",
    "Blockly.Msg.REPL_SOFTWARE_UPDATE": "소프트웨어 업데이트",
    "Blockly.Msg.REPL_APPROVE_UPDATE": " 업데이트를 묻는 화면을 표시.",
    "Blockly.Msg.REPL_NETWORK_ERROR_RESTART": "컴패니언과 통신 중 네트워크 에러.<br/>컴패니언을 재시작 후 재연결해보세요",
    "Blockly.Msg.LANG_TEXT_COMPARE_TOOLTIP_NEQ": "텍스트 문자열이 다른지 검사합니다.\n즉, 두 텍스트들이 똑같은 순서가 아닌지 확인합니다. 이는 보통의 ≠ 와는 다릅니다.\n예를 들어 문자열을 텍스트로비교하는 경우 123과 0123은 다르지만 숫자로서는 같습니다.",
    "Blockly.Msg.REPL_DISMISS": "닫기",
    "Blockly.Msg.MISSING_SOCKETS_WARNINGS": "블록의 모든 소켓을 채워야 합니다.",
    "Blockly.Msg.REPL_COMPANION_OUT_OF_DATE1": "사용 중인 컴패니언은 최신 버전이 아닙니다.<br/><br/> 이 버전의 앱인벤터는 다음 컴패니언 버전을 써야 합니다:",
    "Blockly.Msg.REPL_NOT_NOW": "나중에",
    "Blockly.Msg.REPL_DEVICES": "디바이스",
    "Blockly.Msg.REPL_EMULATORS": "에뮬레이터",
    "Blockly.Msg.REPL_COMPANION_OUT_OF_DATE2": "이 컴패니언은 구버전입니다. 컴패니언을 재시작하고 QR코드를 스캔하여 업데이트하세요",
    "Blockly.Msg.REPL_COMPANION_OUT_OF_DATE": "이 컴패니언은 구버전입니다. 확인을 눌러 업데이트하세요. ",
    "Blockly.Msg.REPL_COMPANION_VERSION_CHECK": "컴패니언 버전 체크",
    "Blockly.Msg.REPL_OK": "확인",
    "Blockly.Msg.REPL_NETWORK_ERROR": "네트워크 에러",
    "Blockly.Msg.REPL_NETWORK_CONNECTION_ERROR": "네트워크 연결 에러",
    "Blockly.Msg.REPL_ERROR_FROM_COMPANION": "컴패니언 에러",
    "Blockly.Msg.WRONG_TYPE_BLOCK_WARINGS": "이 블록은 이벤트 블록이나 함수 정의 블록에 연결되어 있어야 합니다",
    "Blockly.Msg.HIDE_WARNINGS": "경고 숨기기",
    "Blockly.Msg.SHOW_WARNINGS": "경고 보이기",
    "Blockly.Msg.LANG_LISTS_APPEND_LIST_INPUT_LIST2": "리스트2",
    "Blockly.Msg.LANG_LISTS_APPEND_LIST_INPUT_LIST1": "리스트1",
    "Blockly.Msg.LANG_MATH_ONLIST_TOOLTIP_MAX": "입력받은 값 중 최댓값을 반환합니다.",
    "Blockly.Msg.LANG_MATH_ONLIST_TOOLTIP_MIN": "입력받은 값 중 최솟값을 반환합니다.",
    "Blockly.Msg.LANG_CONTROLS_CHOOSE_INPUT_TEST": " ",
    "Blockly.Msg.LANG_CONTROLS_WHILEUNTIL_TOOLTIP_1": "조건이 참인 동안 계속해서 실행 영역의 블록을 실행합니다.",
    "Blockly.Msg.LANG_CONTROLS_IF_TOOLTIP_4": "만약 첫 번째 조건이 참이라면, 첫 번째 영역의 블록을 실행해요. 그렇지 않고 두 번째 조건이 참이라면, 두 번째 영역의 블록을 실행해요.\n만약 모든 조건이 참이 아니라면, 마지막 영역의 블록을 실행해요.",
    "Blockly.Msg.LANG_CONTROLS_IF_TOOLTIP_3": "만약 첫 번째 조건이 참이라면, 첫 번째 영역의 블록을 실행해요. 그렇지 않고 두 번째 조건이 참이라면, 두 번째 영역의 블록을 실행해요.",
    "Blockly.Msg.LANG_CONTROLS_IF_TOOLTIP_2": "만약 조건이 참이라면, 첫 번째 영역의 블록을 실행해요. 그렇지 않다면, 두 번째 영역의 블록을 실행해요.",
    "Blockly.Msg.LANG_CONTROLS_IF_TOOLTIP_1": "만약 조건이 참이라면, 블록을 실행합니다.",
    "Blockly.Msg.LANG_DICTIONARIES_DICTIONARY_RECURSIVE_SET_TITLE": "딕셔너리에서 키 경로로 값 저장하기",
    "Blockly.Msg.LANG_DICTIONARIES_DICTIONARY_RECURSIVE_LOOKUP_TOOLTIP": "해당 키 경로에서 값을 가져옵니다.",
    "Blockly.Msg.LANG_TEXT_REPLACE_ALL_MAPPINGS_TOOLTIP_DICTIONARY_ORDER": "모든 해당하는 텍스트를 교체후 교체된 텍스트를 반환합니다.\n딕셔너리로부터 입력받은 원본문자열-교체할문자열 쌍에 따라 입력받은 텍스트에서 키에 해당하는 문자열을 찾아 그 키의 값에 해당하는 문자열로 교체합니다.\n키가 여러개 있을 때 키를 사전순으로 배열했을 때 먼저 오는 키 부터 교체됩니다.",
    "Blockly.Msg.LANG_TEXT_REPLACE_ALL_MAPPINGS_TOOLTIP_LONGEST_STRING_FIRST": "모든 해당하는 텍스트를 교체후 교체된 텍스트를 반환합니다.",
    "Blockly.Msg.LANG_DICTIONARIES_CREATE_WITH_CONTAINER_TOOLTIP": "블록들을 추가, 제거 또는 재배치하여 생성할 키-값 쌍을 조절하세요",
    "Blockly.Msg.LANG_TEXT_REPLACE_ALL_MAPPINGS_OPERATOR_LONGEST_STRING_FIRST": "키의 길이가 긴 것 먼저",
    "Blockly.Msg.LANG_TEXT_REPLACE_ALL_MAPPINGS_TITLE": "딕셔너리로 문자열 교체하기",
    "Blockly.Msg.LANG_TEXT_REPLACE_ALL_MAPPINGS_OPERATOR_DICTIONARY_ORDER": "키가 딕셔너리 순서에서 빠른 것 먼저",
    "Blockly.Msg.LANG_TEXT_REPLACE_ALL_MAPPINGS_INPUT_ORDER": "교체",
    "Blockly.Msg.LANG_TEXT_REPLACE_ALL_MAPPINGS_INPUT_ORDER_PREFIX": "교체 순서",
    "Blockly.Msg.LANG_TEXT_REPLACE_ALL_MAPPINGS_INPUT_TEXT": "텍스트",
    "Blockly.Msg.LANG_PROCEDURES_DEFRETURN_PROCEDURE": "함수 만들기",
    "Blockly.Msg.LANG_DICTIONARIES_WALK_TREE_ALL_TOOLTIP": "키 경로를 나타내는 리스트에 쓰이며, 키 경로를 따라 내려가다 이 블록이 실행되면 현재 층의 모든 노드를 탐색합니다.",
    "Blockly.Msg.LANG_DICTIONARIES_WALK_TREE_TOOLTIP": "주어진 딕셔너리에서 시작하여 키 경로에 따라 자식 키를 따라 내려갑니다. 그리고 경로의 끝에 해당하는 딕셔너리 노드를 리스트로 반환합니다.",
    "Blockly.Msg.LANG_DICTIONARIES_COMBINE_DICTS_TITLE": "딕셔너리 합치기",
    "Blockly.Msg.LANG_DICTIONARIES_DICTIONARY_RECURSIVE_SET_TOOLTIP": "주어진 키 경로에 키-값 쌍을 저장합니다.",
    "Blockly.Msg.LANG_DICTIONARIES_DICTIONARY_RECURSIVE_LOOKUP_TITLE": "딕셔너리에서 키 경로로 값 가져오기",
    "Blockly.Msg.LANG_DICTIONARIES_DICTIONARY_LOOKUP_TITLE": "키에 해당하는 값 가져오기",
    "Blockly.Msg.LANG_DICTIONARIES_SET_PAIR_TOOLTIP": "딕셔너리에 키-값 쌍을 저장합니다.",
    "Blockly.Msg.LANG_DICTIONARIES_SET_PAIR_TITLE": "딕셔너리에 키와 값 추가하기",
    "Blockly.Msg.LANG_TEXT_REVERSE_TOOLTIP": "주어진 텍스트를 뒤집습니다.",
    "Blockly.Msg.LANG_TEXT_REVERSE_INPUT": "뒤집기",
    "Blockly.Msg.LANG_DICTIONARIES_IS_DICT_TOOLTIP": "주어진 것이 딕셔너리 형식인지 확인합니다.",
    "Blockly.Msg.LANG_DICTIONARIES_IS_DICT_TITLE": "딕셔너리인가요? %1",
    "Blockly.Msg.LANG_DICTIONARIES_WALK_TREE_ALL_TITLE": "경로의 모든 값 가져오기",
    "Blockly.Msg.LANG_DICTIONARIES_WALK_TREE_TITLE": "키 경로에서 값들 가져오기 키 경로 %1 딕셔너리 또는 리스트 %2",
    "Blockly.Msg.LANG_DICTIONARIES_COMBINE_DICTS_TOOLTIP": "첫 번째로 입력받은 딕셔너리에 두 번째로 입력 받은 딕셔너리의 키-값 쌍을 합칩니다. 중복되는 키는 덮어쓰게 됩니다.",
    "Blockly.Msg.LANG_DICTIONARIES_COMBINE_DICTS_INPUT": "딕셔너리 합치기 %1 합칠 딕셔너리 %2",
    "Blockly.Msg.LANG_DICTIONARIES_COPY_TOOLTIP": "주어진 딕셔너리의 복사본을 만들어 반환합니다.",
    "Blockly.Msg.LANG_DICTIONARIES_COPY_INPUT": "딕셔너리",
    "Blockly.Msg.LANG_DICTIONARIES_COPY_TITLE": "딕셔너리 복제하기",
    "Blockly.Msg.LANG_DICTIONARIES_DICT_TO_ALIST_TOOLTIP": "딕셔너리를 키-값 쌍의 리스트의 리스트로 변환합니다.",
    "Blockly.Msg.LANG_DICTIONARIES_DICT_TO_ALIST_INPUT": "딕셔너리",
    "Blockly.Msg.LANG_DICTIONARIES_DICT_TO_ALIST_TITLE": "딕셔너리를 쌍 리스트로 바꾸기",
    "Blockly.Msg.LANG_DICTIONARIES_ALIST_TO_DICT_TOOLTIP": "키-값 형식의 리스트의 리스트로 이루어진 리스트를 딕셔너리 형식으로 변환하여 반환합니다.",
    "Blockly.Msg.LANG_DICTIONARIES_ALIST_TO_DICT_INPUT": "쌍",
    "Blockly.Msg.LANG_DICTIONARIES_ALIST_TO_DICT_TITLE": "쌍 리스트를 딕셔너리로 바꾸기",
    "Blockly.Msg.LANG_DICTIONARIES_LENGTH_TOOLTIP": "해당 딕셔너리에 있는 키-값 쌍의 개수를 가져옵니다.",
    "Blockly.Msg.LANG_DICTIONARIES_LENGTH_INPUT": "딕셔너리",
    "Blockly.Msg.LANG_DICTIONARIES_LENGTH_TITLE": "길이 구하기",
    "Blockly.Msg.LANG_DICTIONARIES_IS_KEY_IN_TITLE": "키가 딕셔너리에 있는가?",
    "Blockly.Msg.LANG_DICTIONARIES_IS_KEY_IN_TOOLTIP": "키가 해당 딕셔너리에 있는지 확인합니다.",
    "Blockly.Msg.LANG_DICTIONARIES_IS_KEY_IN_INPUT": "딕셔너리에 키가 있는가? 키 %1 딕셔너리 %2",
    "Blockly.Msg.LANG_DICTIONARIES_MAKE_PAIR_TITLE": "쌍 만들기",
    "Blockly.Msg.LANG_DICTIONARIES_PAIR_TITLE": "키-값 쌍",
    "Blockly.Msg.LANG_DICTIONARIES_GET_VALUES_TYPEBLOCK": "값 리스트 가져오기",
    "Blockly.Msg.LANG_DICTIONARIES_GET_VALUES_TOOLTIP": "딕셔너리의 모든 값을 리스트로 가져옵니다.",
    "Blockly.Msg.LANG_DICTIONARIES_GET_VALUES_INPUT": "딕셔너리",
    "Blockly.Msg.LANG_DICTIONARIES_GET_VALUES_TITLE": "값 리스트",
    "Blockly.Msg.LANG_DICTIONARIES_GET_KEYS_TOOLTIP": "딕셔너리의 모든 키를 리스트로 가져옵니다.",
    "Blockly.Msg.LANG_DICTIONARIES_GET_KEYS_TYPEBLOCK": "키 리스트 가져오기",
    "Blockly.Msg.LANG_DICTIONARIES_GET_KEYS_INPUT": "딕셔너리",
    "Blockly.Msg.LANG_DICTIONARIES_GET_KEYS_TITLE": "키 리스트",
    "Blockly.Msg.LANG_DICTIONARIES_GETTERS_TITLE": "가져오기",
    "Blockly.Msg.LANG_DICTIONARIES_DICTIONARY_RECURSIVE_SET_INPUT": "키 경로로 값 저장하기  키 경로 %1 딕셔너리 %2 값 %3",
    "Blockly.Msg.LANG_DICTIONARIES_DICTIONARY_RECURSIVE_LOOKUP_INPUT": "값 가져오기  키 경로 %1 딕셔너리 %2 키가 없으면 %3",
    "Blockly.Msg.LANG_DICTIONARIES_DICTIONARY_LOOKUP_INPUT": "값 가져오기 키 %1 딕셔너리 %2 키가 없으면 %3",
    "Blockly.Msg.LANG_DICTIONARIES_DELETE_PAIR_TITLE": "딕셔너리에서 주어진 키를 가지는 키-값 쌍을 삭제합니다.",
    "Blockly.Msg.LANG_DICTIONARIES_DELETE_PAIR_INPUT": "쌍 삭제하기 키 %2 딕셔너리 %1",
    "Blockly.Msg.LANG_DICTIONARIES_SET_PAIR_INPUT": "값 추가하기 키 %1 딕셔너리 %2 값 %3",
    "Blockly.Msg.LANG_DICTIONARIES_DICTIONARY_LOOKUP_TOOLTIP": "해당 딕셔너리에서 주어진 키와 연결된 값을 가져옵니다.",
    "Blockly.Msg.LANG_DICTIONARIES_DELETE_PAIR_TOOLTIP": "주어진 키를 가지는 키-값 쌍을 해당 딕셔너리에서 제거합니다.",
    "Blockly.Msg.LANG_DICTIONARIES_MAKE_PAIR_TOOLTIP": "입력받은 키와 값으로 키-값 쌍을 만듭니다.",
    "Blockly.Msg.LANG_DICTIONARIES_PAIR_INPUT": "키 %1 값 %2",
    "Blockly.Msg.LANG_DICTIONARIES_CREATE_WITH_CONTAINER_TITLE_ADD": "딕셔너리",
    "Blockly.Msg.LANG_DICTIONARIES_MAKE_DICTIONARY_TOOLTIP": "딕셔너리 자료형을 만듭니다.",
    "Blockly.Msg.LANG_DICTIONARIES_MAKE_DICTIONARY_TITLE": "딕셔너리 만들기",
    "Blockly.Msg.LANG_DICTIONARIES_CREATE_EMPTY_TITLE": "빈 딕셔너리 만들기",
    "Blockly.Msg.LANG_CATEGORY_DICTIONARIES": "딕셔너리",
    "Blockly.Msg.DO_IT_RESULT": "실행 결과:",
    "Blockly.Msg.REPL_WEBRTC_CONNECTION_CLOSED": "컴패니언과의 연결이 끊어졌습니다",
    "Blockly.Msg.LANG_DICTIONARIES_PAIR_TOOLTIP": "쌍을 딕셔너리에 추가합니다.",
    "Blockly.Msg.LANG_TEXT_CONTAINS_TOOLTIP_CONTAINS_ALL": "텍스트가 단어 리스트의 단어들을 모두 포함하는지 검사합니다.",
    "Blockly.Msg.LANG_TEXT_CONTAINS_TOOLTIP_CONTAINS_ANY": "텍스트가 단어 리스트의 단어들 중 하나라도 포함하는지 검사합니다.",
    "Blockly.Msg.LANG_TEXT_CONTAINS_TOOLTIP_CONTAINS": "텍스트가 단어를 포함하는지 검사합니다.",
    "Blockly.Msg.LANG_TEXT_CONTAINS_OPERATOR_CONTAINS_ALL": "모두 포함",
    "Blockly.Msg.LANG_TEXT_CONTAINS_OPERATOR_CONTAINS_ANY": "일부 포함",
    "Blockly.Msg.LANG_TEXT_CONTAINS_OPERATOR_CONTAINS": "포함",
    "Blockly.Msg.LANG_TEXT_CONTAINS_INPUT_PIECE_LIST": "단어 리스트",
    "Blockly.Msg.LANG_MATH_NUMBER_RADIX_TITLE": "숫자 진법",
    "Blockly.Msg.LANG_MATH_NUMBER_RADIX_TOOLTIP": "주어진 숫자를 정수(십진법) 형식으로 변환합니다.",
    "Blockly.Msg.LANG_MATH_HEXADECIMAL_FORMAT": "16진수",
    "Blockly.Msg.LANG_MATH_OCTAL_FORMAT": "8진수",
    "Blockly.Msg.LANG_MATH_BINARY_FORMAT": "2진수",
    "Blockly.Msg.LANG_MATH_DECIMAL_FORMAT": "10진수",
    "Blockly.Msg.LANG_CONTROLS_FOREACH_DICT_TOOLTIP": "딕셔너리의 각각의 키-값 구조에 대해 '실행' 영역에서 블록을 실행힙니다.\n키/값이라는 이름으로 제공되는 변수를 이용하여 현재 딕셔너리 항목을 가져올 수 있습니다.",
    "Blockly.Msg.LANG_CONTROLS_FOREACH_DICT_TITLE": "딕셔너리의 항목 각각에 대한 반복작업을 합니다.",
    "Blockly.Msg.LANG_CONTROLS_FOREACH_DICT_INPUT_VALUE": "값",
    "Blockly.Msg.LANG_CONTROLS_FOREACH_DICT_INPUT_KEY": "키",
    "Blockly.Msg.LANG_CONTROLS_FOREACH_DICT_INPUT_DO": "실행",
    "Blockly.Msg.LANG_CONTROLS_FOREACH_DICT_INPUT": "각각 반복 %1 %2 딕셔너리 %3",
    "Blockly.Msg.ERROR_INVALID_NUMBER_CONTENT": "이 텍스트 블록은 유효한 숫자를 포함하고있지 않습니다",
    "Blockly.Msg.LANG_NO_ASSETS": "존재하는 에셋이 없음",
    "Blockly.Msg.LANG_SCREENS_TITLE": "스크린 이름: "
}
